Workbook

Sheet Legenda
A1: Gabarito (ground-truth)
A3: Origem | B3: Programas da CBSA na pasta ORIGINAL do repositório da base de dados (commit e22475691524ef72a92ee77f7040233e098ab1b9, ijmitch/cics-banking-sample-application-cbsa). Números de linha referem-se aos arquivos do ORIGINAL.
A4: Arquivos (SHA-256) | B4: DBCRFUN.cbl: 632917d17138331d540b05823c840eb204675ddb79ac9eac0d8d6d847982056f XFRFUN.cbl: 9c642ade5e1211b77b7c264eaea18f8cf88cb035af32ed55c66278482e51013e BNK1CRA.cbl: 061d73de30c1a3635db44b1f9dc8faebc71ea8e024fee48db499ad1ecda4ab97 BNK1TFN.cbl: 8bbc799b498a756a367ccf6dfb52d1d15579fe72332efbb86906e729edf519e2
A5: Como foi gerado | B5: Extração automática (script monta_planilha.py). Cada bloco de comentário da PROCEDURE DIVISION é pareado ao código que o segue, até o próximo comentário. O trecho exibido é limitado a 50 linhas, mas o filtro avalia o bloco inteiro. Quando o comentário vem logo após uma linha IF, ELSE, WHEN ou EVALUATE, essa linha (cabeçalho) é usada para reter o par se o corpo não tiver decisão nem falha, e aparece com o prefixo [cab.].
A6: Filtro (E4, seção 1.3) | B6: Retido: trecho com IF, EVALUATE ou WHEN, ou com tratamento de falha (ABEND, SQLCODE, HANDLE, DFHRESP, EIBRESP, EIBRCODE). O filtro é sintático: trechos de infraestrutura pura (rollback, ABEND de DB2/VSAM, storm drain) também aparecem aqui, porque contêm essas palavras-chave; a exclusão semântica é feita na revisão manual (coluna Categoria), não pelo script. Os demais (sem decisão nem falha) ficam na aba Descartados, para que o critério seja auditável.
A7: O que preencher | B7: Aba Candidatos, colunas J a M (fundo amarelo): Regra de negócio extraída, Categoria, Status e Observação, mesmas colunas usadas na revisão manual do DBCRFUN. Colunas O e P (amarelas): ID atômico (sub-regra), preenchido com a, b, c apenas quando o bloco contiver mais de uma regra, e Comentário defasado? (Sim ou Não), preenchido em toda linha revisada. Na aba Descartados, coluna I.
A8: Valores da revisão | B8: Categoria: regra de negócio, infraestrutura (excluída) ou a discutir (lista suspensa). Status: A validar ou Validado. Comentário defasado?: Sim (o comentário não corresponde mais ao código) ou Não. Em Descartados: Manter descartado ou Reincluir.
A9: Alertas | B9: possível código desativado: o comentário parece uma instrução COBOL comentada. comentário curto: até 3 palavras. trecho truncado: o código do par passa do limite de linhas exibidas; a coluna Linhas do código mostra o intervalo completo e a classificação considerou todo o bloco. comentários adjacentes fundidos: o bloco seguinte de comentário foi unido porque o trecho entre eles não tinha código ativo. decisão no cabeçalho anterior ao comentário: o par foi retido pela linha IF/ELSE/WHEN/EVALUATE que precede o comentário (linhas indicadas; também no código da linha anterior da planilha). comentário delega lógica (PERFORM): o trecho só chama outro parágrafo; a regra pode estar no parágrafo executado. contém GO TO: há desvio incondicional no trecho. Qtd decisões (coluna N): total de IF, EVALUATE e WHEN do bloco inteiro (+1 quando o par foi retido pelo cabeçalho); é uma contagem, não a profundidade de aninhamento. comentário menciona condição (aba Descartados): o comentário descreve uma condição, mas o trecho seguinte é só ação; a decisão pode estar antes no fonte.
A10: Limitações | B10: A triagem é heurística e não substitui a revisão dupla. Comentários de cabeçalho (antes da PROCEDURE DIVISION) não entram. Regras sem comentário associado não geram par. Linhas de depuração (indicador D) aparecem com o prefixo [D]. O tipo (Decisão, Falha, Decisão e falha) é atribuído ao bloco inteiro, não ao comentário isolado. O cabeçalho IF/ELSE que precede um comentário continua também no código do par anterior (cada linha de código pertence a um único par, exceto o cabeçalho exibido como contexto).
A12: Rascunho (assistente) | B12: Colunas J, K e M preenchidas como rascunho em fonte azul; a Observação inicia por '[Rascunho]'. Status mantido em 'A validar'. Ao conferir uma linha no fonte, ajustar o texto, trocar a fonte para preta e atualizar o Status. Linhas com a categoria 'a discutir' ou 'infraestrutura (excluída)' sem regra em J são sugestões de classificação, não decisões.
A13: Reincluídas | B13: Blocos marcados como 'Reincluir' na aba Descartados são registrados ao final da aba Candidatos, com o mesmo ID, Tipo 'Reincluído' e Estruturas 'procedural'. Na aba Resumo, deixam de ser contados como descartados e passam a contar como candidatos retidos (a soma de Decisão, Falha e Decisão e falha fica menor que Candidatos retidos pelo número de reincluídas).
A14: Exemplo de regra atômica | B14: Ilustrativo, não faz parte do gabarito: "Se o valor solicitado for um débito e o saldo disponível for insuficiente, a solicitação é negada." (uma condição e uma consequência por regra)

Sheet Resumo
A1: Programa | B1: Blocos com texto | C1: Candidatos retidos | D1: Descartados | E1: Decisão | F1: Falha | G1: Decisão e falha | H1: Com alertas | I1: Regra de negócio | J1: Infraestrutura (excluída) | K1: A discutir | L1: Validados | M1: Pendentes | N1: Defasagem avaliada | O1: Comentário defasado (Sim)
A2: DBCRFUN | B2: =C2+D2 -> 33 | C2: =COUNTIF(Candidatos!$B:$B,$A2) -> 23 | D2: =COUNTIFS(Descartados!$B:$B,$A2,Descartados!$I:$I,"<>Reincluir") -> 10 | E2: =COUNTIFS(Candidatos!$B:$B,$A2,Candidatos!$G:$G,"Decisão") -> 8 | F2: =COUNTIFS(Candidatos!$B:$B,$A2,Candidatos!$G:$G,"Falha") -> 5 | G2: =COUNTIFS(Candidatos!$B:$B,$A2,Candidatos!$G:$G,"Decisão e falha") -> 8 | H2: =COUNTIFS(Candidatos!$B:$B,$A2,Candidatos!$I:$I,"<>") -> 7 | I2: =COUNTIFS(Candidatos!$B:$B,$A2,Candidatos!$K:$K,"regra de negócio") -> 9 | J2: =COUNTIFS(Candidatos!$B:$B,$A2,Candidatos!$K:$K,"infraestrutura (excluída)") -> 13 | K2: =COUNTIFS(Candidatos!$B:$B,$A2,Candidatos!$K:$K,"a discutir") -> 1 | L2: =COUNTIFS(Candidatos!$B:$B,$A2,Candidatos!$L:$L,"Validado") -> 20 | M2: =C2-L2 -> 3 | N2: =COUNTIFS(Candidatos!$B:$B,$A2,Candidatos!$P:$P,"Sim")+COUNTIFS(Candidatos!$B:$B,$A2,Candidatos!$P:$P,"Não") -> 0 | O2: =COUNTIFS(Candidatos!$B:$B,$A2,Candidatos!$P:$P,"Sim") -> 0
A3: XFRFUN | B3: =C3+D3 -> 70 | C3: =COUNTIF(Candidatos!$B:$B,$A3) -> 57 | D3: =COUNTIFS(Descartados!$B:$B,$A3,Descartados!$I:$I,"<>Reincluir") -> 13 | E3: =COUNTIFS(Candidatos!$B:$B,$A3,Candidatos!$G:$G,"Decisão") -> 11 | F3: =COUNTIFS(Candidatos!$B:$B,$A3,Candidatos!$G:$G,"Falha") -> 23 | G3: =COUNTIFS(Candidatos!$B:$B,$A3,Candidatos!$G:$G,"Decisão e falha") -> 20 | H3: =COUNTIFS(Candidatos!$B:$B,$A3,Candidatos!$I:$I,"<>") -> 20 | I3: =COUNTIFS(Candidatos!$B:$B,$A3,Candidatos!$K:$K,"regra de negócio") -> 9 | J3: =COUNTIFS(Candidatos!$B:$B,$A3,Candidatos!$K:$K,"infraestrutura (excluída)") -> 43 | K3: =COUNTIFS(Candidatos!$B:$B,$A3,Candidatos!$K:$K,"a discutir") -> 5 | L3: =COUNTIFS(Candidatos!$B:$B,$A3,Candidatos!$L:$L,"Validado") -> 45 | M3: =C3-L3 -> 12 | N3: =COUNTIFS(Candidatos!$B:$B,$A3,Candidatos!$P:$P,"Sim")+COUNTIFS(Candidatos!$B:$B,$A3,Candidatos!$P:$P,"Não") -> 0 | O3: =COUNTIFS(Candidatos!$B:$B,$A3,Candidatos!$P:$P,"Sim") -> 0
A4: BNK1CRA | B4: =C4+D4 -> 43 | C4: =COUNTIF(Candidatos!$B:$B,$A4) -> 31 | D4: =COUNTIFS(Descartados!$B:$B,$A4,Descartados!$I:$I,"<>Reincluir") -> 12 | E4: =COUNTIFS(Candidatos!$B:$B,$A4,Candidatos!$G:$G,"Decisão") -> 16 | F4: =COUNTIFS(Candidatos!$B:$B,$A4,Candidatos!$G:$G,"Falha") -> 7 | G4: =COUNTIFS(Candidatos!$B:$B,$A4,Candidatos!$G:$G,"Decisão e falha") -> 8 | H4: =COUNTIFS(Candidatos!$B:$B,$A4,Candidatos!$I:$I,"<>") -> 8 | I4: =COUNTIFS(Candidatos!$B:$B,$A4,Candidatos!$K:$K,"regra de negócio") -> 9 | J4: =COUNTIFS(Candidatos!$B:$B,$A4,Candidatos!$K:$K,"infraestrutura (excluída)") -> 15 | K4: =COUNTIFS(Candidatos!$B:$B,$A4,Candidatos!$K:$K,"a discutir") -> 7 | L4: =COUNTIFS(Candidatos!$B:$B,$A4,Candidatos!$L:$L,"Validado") -> 15 | M4: =C4-L4 -> 16 | N4: =COUNTIFS(Candidatos!$B:$B,$A4,Candidatos!$P:$P,"Sim")+COUNTIFS(Candidatos!$B:$B,$A4,Candidatos!$P:$P,"Não") -> 0 | O4: =COUNTIFS(Candidatos!$B:$B,$A4,Candidatos!$P:$P,"Sim") -> 0
A5: BNK1TFN | B5: =C5+D5 -> 49 | C5: =COUNTIF(Candidatos!$B:$B,$A5) -> 33 | D5: =COUNTIFS(Descartados!$B:$B,$A5,Descartados!$I:$I,"<>Reincluir") -> 16 | E5: =COUNTIFS(Candidatos!$B:$B,$A5,Candidatos!$G:$G,"Decisão") -> 18 | F5: =COUNTIFS(Candidatos!$B:$B,$A5,Candidatos!$G:$G,"Falha") -> 8 | G5: =COUNTIFS(Candidatos!$B:$B,$A5,Candidatos!$G:$G,"Decisão e falha") -> 7 | H5: =COUNTIFS(Candidatos!$B:$B,$A5,Candidatos!$I:$I,"<>") -> 12 | I5: =COUNTIFS(Candidatos!$B:$B,$A5,Candidatos!$K:$K,"regra de negócio") -> 11 | J5: =COUNTIFS(Candidatos!$B:$B,$A5,Candidatos!$K:$K,"infraestrutura (excluída)") -> 15 | K5: =COUNTIFS(Candidatos!$B:$B,$A5,Candidatos!$K:$K,"a discutir") -> 7 | L5: =COUNTIFS(Candidatos!$B:$B,$A5,Candidatos!$L:$L,"Validado") -> 15 | M5: =C5-L5 -> 18 | N5: =COUNTIFS(Candidatos!$B:$B,$A5,Candidatos!$P:$P,"Sim")+COUNTIFS(Candidatos!$B:$B,$A5,Candidatos!$P:$P,"Não") -> 0 | O5: =COUNTIFS(Candidatos!$B:$B,$A5,Candidatos!$P:$P,"Sim") -> 0
A6: TOTAL | B6: =SUM(B2:B5) -> 195 | C6: =SUM(C2:C5) -> 144 | D6: =SUM(D2:D5) -> 51 | E6: =SUM(E2:E5) -> 53 | F6: =SUM(F2:F5) -> 43 | G6: =SUM(G2:G5) -> 43 | H6: =SUM(H2:H5) -> 47 | I6: =SUM(I2:I5) -> 38 | ... O6: =SUM(O2:O5) -> 0
A8: Contagens por fórmula: atualizam conforme a revisão é preenchida na aba Candidatos.

Sheet Candidatos
A1: ID | B1: Programa | C1: Linhas do comentário | D1: Linhas do código | E1: Comentário | F1: Trecho de código | G1: Tipo | H1: Estruturas | I1: Alertas | J1: Regra de negócio extraída | K1: Categoria | L1: Status | M1: Observação | N1: Qtd decisões | O1: ID atômico (sub-regra) | P1: Comentário defasado?
A2: DBCRFUN-001 | B2: DBCRFUN | C2: 205 | D2: 207-212 | E2: Set up some Abend handling | F2: EXEC CICS HANDLE ABEND LABEL(ABEND-HANDLING) END-EXEC. MOVE SORTCODE TO COMM-SORTC. MOVE SORTCODE TO DESIRED-SORT-CODE. | G2: Falha | H2: falha | K2: infraestrutura (excluída) | L2: Validado | M2: Configuração do tratamento de ABEND (HANDLE ABEND) e cópia do código da agência (SORTCODE), sem decisão de negócio. | N2: 0
A3: DBCRFUN-005 | B3: DBCRFUN | C3: 276-277 | D3: 279-287 | E3: Check that select was successful. If it wasn't then deal with it | F3: IF SQLCODE NOT = 0 MOVE 'N' TO COMM-SUCCESS IF SQLCODE = +100 MOVE '1' TO COMM-FAIL-CODE ELSE MOVE '2' TO COMM-FAIL-CODE END-IF | G3: Decisão e falha | H3: IF, falha | J3: Se a conta solicitada não for encontrada (SQLCODE igual a +100), a operação é sinalizada como malsucedida com o código de falha '1'. | K3: regra de negócio | L3: Validado | M3: O código '1' tem semântica de domínio. O código '2' (SQLCODE diferente de zero e de +100) corresponde a falha técnica de DB2 e não integra a regra, pelo mesmo critério da DBCRFUN-013 (infraestrutura). O IF externo termina na DBCRFUN-006 (Descartados): PERFORM CHECK-FOR-STORM-DRAIN-DB2 e GO TO UAD999 (infraestrutura). | N3: 2
A4: DBCRFUN-007 | B4: DBCRFUN | C4: 301-304 | D4: 307 | E4: Is the amount being requested a debit or a credit? If it is a CREDIT (+) then we don't need to ensure that the available balance has sufficient funds, because this is money coming in. | F4: IF COMM-AMT < 0 | G4: Decisão | H4: IF | J4: Se o valor solicitado for crédito (não negativo), a suficiência do saldo disponível não é verificada. | K4: regra de negócio | L4: Validado | M4: O código contém só a condição (COMM-AMT < 0); as consequências do débito estão na DBCRFUN-008. Não há ELSE: crédito e valor zero não entram no bloco. A checagem de MORTGAGE/LOAN reaparece após o END-IF (DBCRFUN-009). | N4: 1
A5: DBCRFUN-008 | B5: DBCRFUN | C5: 309-328 | D5: 316-352 | E5: The amount being requested is a DEBIT/Payment (-) so we do need to check that the available balance is sufficient to cover the amount being asked for. If there are NOT sufficient funds the request is denied so remove the record LOCK and and finish. Check to see whether the Payment is being requested from a MORTGAGE or LOAN account. We only make this check for PAYMENTs (we don't make this check for requests via the Teller). How do we know it is a PAYMENT as opposed to a Teller, this is determined by the COMM-FACILTYPE(496 = NONE) If it is a PAYMENT being requested from a MORTGAGE or LOAN account then set an appropriate fail code (4) and finish up. | F5: [D] DISPLAY 'COMM-AMT IS negative' IF (HV-ACCOUNT-ACC-TYPE = 'MORTGAGE' AND COMM-FACILTYPE = 496) OR (HV-ACCOUNT-ACC-TYPE = 'LOAN ' AND COMM-FACILTYPE = 496) MOVE 'N' TO COMM-SUCCESS MOVE '4' TO COMM-FAIL-CODE GO TO UAD999 END-IF MOVE 0 TO WS-DIFFERENCE COMPUTE WS-DIFFERENCE = HV-ACCOUNT-AVAIL-BAL + COMM-AMT IF WS-DIFFERENCE < 0 AND COMM-FACILTYPE = 496 [D] DISPLAY 'insufficient funds!' MOVE 'N' TO COMM-SUCCESS MOVE '3' TO COMM-FAIL-CODE GO TO UAD999 END-IF END-IF. | G5: Decisão | H5: IF | I5: comentários adjacentes fundidos; contém GO TO (desvio incondicional) | J5: 1. Se o valor solicitado for um débito, a solicitação vier por pagamento (COMM-FACILTYPE igual a 496) e a conta for do tipo MORTGAGE ou LOAN, a solicitação é negada com o código de falha '4'. 2. Se o valor solicitado for um débito, a solicitação vier por pagamento (COMM-FACILTYPE igual a 496) e o saldo disponível após o débito for negativo, a solicitação é negada com o código de falha '3'. | K5: regra de negócio | L5: Validado | M5: Comentário e código divergem: o comentário diz que todo débito exige saldo suficiente, mas o código só nega por saldo insuficiente quando COMM-FACILTYPE = 496. Saldo zero após o débito é aceito (negação só se a diferença for menor que zero). A checagem MORTGAGE/LOAN vem antes da de saldo: conta MORTGAGE sem saldo resulta em '4', não '3'. O comentário cita 'remove the record LOCK', mas não há comando de liberação de lock no trecho. Comentários adjacentes fundidos; linhas [D] ignoradas (depuração). Linha vale por duas regras. | N5: 2
A6: DBCRFUN-009 | B6: DBCRFUN | C6: 356-366 | D6: 368-376 | E6: Check to see whether a Credit is being requested from a MORTGAGE or LOAN account. We only make this check for requests via the PAYMENT link (we don't make this check for requests via the Teller). How do we know it is a PAYMENT as opposed to a Teller, this is determined by the COMM-FACILTYPE(496 = NONE) If it is a PAYMENT credit being requested from a MORTGAGE or LOAN account then set an appropriate fail code (4), remove the record lock and finish up. | F6: IF (HV-ACCOUNT-ACC-TYPE = 'MORTGAGE' AND COMM-FACILTYPE = 496) OR (HV-ACCOUNT-ACC-TYPE = 'LOAN ' AND COMM-FACILTYPE = 496) MOVE 'N' TO COMM-SUCCESS MOVE '4' TO COMM-FAIL-CODE GO TO UAD999 END-IF. | G6: Decisão | H6: IF | I6: contém GO TO (desvio incondicional) | J6: Se a solicitação vier por pagamento (COMM-FACILTYPE igual a 496) e a conta for do tipo MORTGAGE ou LOAN, a solicitação é negada com o código de falha '4'. | K6: regra de negócio | L6: Validado | M6: Mesma condição da regra 1 da DBCRFUN-008, repetida fora do bloco de débito (após o END-IF). Como o débito já sai por GO TO UAD999 na 008, esta checagem só alcança créditos na prática, embora o código não teste o sinal do valor (o comentário fala em 'Credit'). O comentário cita 'remove the record lock', sem comando correspondente. Mantida como entrada separada (critério de não fundir duplicatas); conferir fonte, linhas 356-376. | N6: 1
A7: DBCRFUN-012 | B7: DBCRFUN | C7: 411-412 | D7: 414-419 | E7: If the rewrite was successful then we need to pass back the amended available balance and actual balance. | F7: MOVE SQLCODE TO SQLCODE-DISPLAY. MOVE HV-ACCOUNT-AVAIL-BAL TO COMM-AV-BAL. MOVE HV-ACCOUNT-ACTUAL-BAL TO COMM-ACT-BAL. | G7: Falha | H7: falha | K7: infraestrutura (excluída) | L7: Validado | M7: Sem estrutura de decisão (retido por conter 'SQLCODE'). O comentário diz 'if the rewrite was successful', mas os MOVE de saldos ocorrem sem condição, antes do IF SQLCODE NOT = 0 (DBCRFUN-013): os saldos são devolvidos mesmo se a atualização falhar. | N7: 0
A8: DBCRFUN-013 | B8: DBCRFUN | C8: 422-423 | D8: 425-427 | E8: If the RESP CODE was NOT OK then we need to set flags accordingly | F8: IF SQLCODE NOT = 0 MOVE 'N' TO COMM-SUCCESS MOVE '2' TO COMM-FAIL-CODE | G8: Decisão e falha | H8: IF, falha | K8: infraestrutura (excluída) | L8: Validado | M8: Falha técnica de DB2 na atualização, excluída como infraestrutura (mesmo critério aplicado ao código '2' da DBCRFUN-005). O código '2' chega ao usuário como 'unexpected error' (BNK1CRA-025). O trecho termina antes do tratamento de storm drain (DBCRFUN-014, Descartados). | N8: 1
A9: DBCRFUN-017 | B9: DBCRFUN | C9: 473 | D9: 475-493 | E9: Populate the current time and date | F9: EXEC CICS ASKTIME ABSTIME(WS-U-TIME) END-EXEC. EXEC CICS FORMATTIME ABSTIME(WS-U-TIME) DDMMYYYY(WS-ORIG-DATE) TIME(HV-PROCTRAN-TIME) DATESEP('.') END-EXEC. MOVE WS-ORIG-DATE TO WS-ORIG-DATE-GRP-X. MOVE WS-ORIG-DATE-GRP-X TO HV-PROCTRAN-DATE. MOVE SPACES TO HV-PROCTRAN-DESC. IF COMM-AMT < 0 MOVE 'DEB' TO HV-PROCTRAN-TYPE MOVE 'COUNTER WTHDRW' TO HV-PROCTRAN-DESC | G9: Decisão | H9: IF | J9: Se o valor solicitado for negativo (débito), a transação registrada recebe o tipo 'DEB' e a descrição 'COUNTER WTHDRW'. | K9: regra de negócio | L9: Validado | M9: O trecho inclui ASKTIME/FORMATTIME (data e hora da transação; procedural, fora da regra). O tipo 'DEB' é sobrescrito por 'PDR' quando a solicitação vem por pagamento (DBCRFUN-018). O ELSE de crédito ('CRE') também está na 018. A condição COMM-AMT < 0 repete a da DBCRFUN-007. | N9: 1
A10: DBCRFUN-018 | B10: DBCRFUN | C10: 496 | D10: 498-506 | E10: If it is a debit from a PAYMENT | F10: IF COMM-FACILTYPE = 496 MOVE 'PDR' TO HV-PROCTRAN-TYPE MOVE COMM-ORIGIN(1:14) TO HV-PROCTRAN-DESC END-IF ELSE MOVE 'CRE' TO HV-PROCTRAN-TYPE MOVE 'COUNTER RECVED' TO HV-PROCTRAN-DESC | G10: Decisão | H10: IF | J10: 1. Se o valor solicitado for um débito feito por pagamento (COMM-FACILTYPE igual a 496), o tipo da transação registrada passa a 'PDR' e a descrição recebe os 14 primeiros caracteres da origem (COMM-ORIGIN). 2. Se o valor solicitado for crédito (não negativo), a transação registrada recebe o tipo 'CRE' e a descrição 'COUNTER RECVED'. | K10: regra de negócio | L10: Validado | M10: O ELSE fecha o IF COMM-AMT < 0 aberto na DBCRFUN-017; o comentário cobre apenas a regra 1. Linha vale por duas regras. | N10: 1
A11: DBCRFUN-019 | B11: DBCRFUN | C11: 509 | D11: 511-519 | E11: If it is a credit from a PAYMENT | F11: IF COMM-FACILTYPE = 496 MOVE 'PCR' TO HV-PROCTRAN-TYPE MOVE COMM-ORIGIN(1:14) TO HV-PROCTRAN-DESC END-IF END-IF. MOVE COMM-AMT TO HV-PROCTRAN-AMOUNT. | G11: Decisão | H11: IF | J11: Se o valor solicitado for um crédito feito por pagamento (COMM-FACILTYPE igual a 496), o tipo da transação registrada passa a 'PCR' e a descrição recebe os 14 primeiros caracteres da origem (COMM-ORIGIN). | K11: regra de negócio | L11: Validado | M11: IF aninhado no ramo de crédito (ELSE da 018). O MOVE COMM-AMT TO HV-PROCTRAN-AMOUNT ao final é procedural e fica fora da regra. | N11: 1
A12: DBCRFUN-021 | B12: DBCRFUN | C12: 552 | D12: 554-559 | E12: Check the SQLCODE | F12: IF SQLCODE NOT = 0 MOVE SQLCODE TO SQLCODE-DISPLAY DISPLAY 'UNABLE TO WRITE TO PROCTRAN DB2 DATASTORE' ' SQLCODE=' SQLCODE-DISPLAY 'WITH THE FOLLOWING DATA:' HOST-PROCTRAN-ROW | G12: Decisão e falha | H12: IF, falha | I12: comentário curto | K12: infraestrutura (excluída) | L12: Validado | M12: Falha na gravação em PROCTRAN (DB2): exibe diagnóstico; o rollback (022) e o ABEND (023) completam o tratamento. Falha técnica, fora do escopo pelo critério de infraestrutura. O efeito (operação desfeita se o registro falhar) é regra de consistência. | N12: 1
A13: DBCRFUN-022 | B13: DBCRFUN | C13: 561-562 | D13: 564-569 | E13: You need to issue a ROLLBACK to get rid of the updated ACCOUNT record | F13: EXEC CICS SYNCPOINT ROLLBACK RESP(WS-CICS-RESP) RESP2(WS-CICS-RESP2) END-EXEC IF WS-CICS-RESP NOT = DFHRESP(NORMAL) | G13: Decisão e falha | H13: IF, falha | K13: infraestrutura (excluída) | L13: Validado | M13: Rollback da atualização da conta (SYNCPOINT ROLLBACK) e verificação do RESP; infraestrutura transacional. | N13: 1
A14: DBCRFUN-023 | B14: DBCRFUN | C14: 571-574 | D14: 576-578 | E14: Preserve the RESP and RESP2, then set up the standard ABEND info before getting the applid, date/time etc. and linking to the Abend Handler program. | F14: INITIALIZE ABNDINFO-REC MOVE EIBRESP TO ABND-RESPCODE MOVE EIBRESP2 TO ABND-RESP2CODE | G14: Falha | H14: falha | K14: infraestrutura (excluída) | L14: Validado | M14: Montagem padrão das informações de ABEND (INITIALIZE ABNDINFO-REC; MOVE EIBRESP/EIBRESP2); tratamento técnico sem semântica bancária. | N14: 0
A15: DBCRFUN-024 | B15: DBCRFUN | C15: 580 | D15: 582-637 | E15: Get supplemental information | F15: EXEC CICS ASSIGN APPLID(ABND-APPLID) END-EXEC MOVE EIBTASKN TO ABND-TASKNO-KEY MOVE EIBTRNID TO ABND-TRANID PERFORM POPULATE-TIME-DATE MOVE WS-ORIG-DATE TO ABND-DATE STRING WS-TIME-NOW-GRP-HH DELIMITED BY SIZE, ':' DELIMITED BY SIZE, WS-TIME-NOW-GRP-MM DELIMITED BY SIZE, ':' DELIMITED BY SIZE, WS-TIME-NOW-GRP-MM DELIMITED BY SIZE INTO ABND-TIME END-STRING MOVE WS-U-TIME TO ABND-UTIME-KEY MOVE 'HROL' TO ABND-CODE EXEC CICS ASSIGN PROGRAM(ABND-PROGRAM) END-EXEC MOVE ZEROS TO ABND-SQLCODE STRING 'WTPD010 - COULD NOT ROLL BACK, POSSIBLE DATA' DELIMITED BY SIZE, 'INTEGRITY ISSUE BETWEEN ACCOUNT AND PROCTRAN ' DELIMITED BY SIZE, 'FOR ROW:' DELIMITED BY SIZE, HOST-PROCTRAN-ROW DELIMITED BY SIZE, 'EIBRESP=' DELIMITED BY SIZE, ABND-RESPCODE DELIMITED BY SIZE, ' RESP2=' DELIMITED BY SIZE, ABND-RESP2CODE DELIMITED BY SIZE INTO ABND-FREEFORM END-STRING EXEC CICS LINK PROGRAM(WS-ABEND-PGM) COMMAREA(ABNDINFO-REC) END-EXEC DISPLAY ' COULD NOT ROLL BACK, POSSIBLE DATA ' 'INTEGRITY ISSUE BETWEEN ACCOUNT AND PROCTRAN ' 'FOR ROW:' HOST-PROCTRAN-ROW 'RESP CODE=' WS-CICS-RESP ' RESP2 CODE=' WS-CICS-RESP2 EXEC CICS ABEND ABCODE ('HROL') CANCEL END-EXEC END-IF MOVE 'N' TO COMM-SUCCESS MOVE '02' TO COMM-FAIL-CODE | G15: Falha | H15: falha | I15: comentário curto | K15: infraestrutura (excluída) | L15: Validado | M15: Coleta de informações complementares de ABEND (PERFORM POPULATE-TIME-DATE, LINK ao tratador de ABEND, ABEND); tratamento técnico sem semântica bancária. Estava como 'Manter descartado' na planilha anterior; o script agora o retém por conter ABEND (antes o trecho era cortado antes dele). | N15: 0
A16: DBCRFUN-026 | B16: DBCRFUN | C16: 647 | D16: 644; 649-669 | E16: If the WRITE to PROCTRAN worked then it was a success | F16: [cab.] ELSE MOVE 'Y' TO COMM-SUCCESS MOVE '0' TO COMM-FAIL-CODE END-IF. WTPD999. EXIT. GET-ME-OUT-OF-HERE SECTION. GMOOH010. EXEC CICS RETURN END-EXEC. GOBACK. GMOOH999. EXIT. CHECK-FOR-STORM-DRAIN-DB2 SECTION. CFSDD010. | G16: Decisão | H16: ELSE (cabeçalho) | I16: decisão no cabeçalho anterior ao comentário (linha 644) | J16: Se a gravação em PROCTRAN for bem-sucedida, a operação é sinalizada como bem-sucedida (COMM-SUCCESS igual a 'Y') com o código de falha '0'. | K16: regra de negócio | L16: A validar | M16: [Rascunho] Reincluída da aba Descartados (motivo do descarte: procedural, sem decisão nem tratamento de falha). Ramo ELSE do IF SQLCODE NOT = 0 da gravação em PROCTRAN (ramo de falha na DBCRFUN-021, classificado como infraestrutura). É o único ponto em que COMM-SUCCESS recebe 'Y': o sucesso da operação depende da gravação do registro. O trecho extraído inclui as seções seguintes (GET-ME-OUT-OF-HERE e CHECK-FOR-STORM-DRAIN-DB2), por corte do extrator; ficam fora da regra. | N16: 1
A17: DBCRFUN-027 | B17: DBCRFUN | C17: 671-672 | D17: 675-695 | E17: Check if the Sqclode that is returned one that will trigger Storm Drain is active in Workload | F17: EVALUATE SQLCODE WHEN 923 MOVE 'DB2 Connection lost ' TO STORM-DRAIN-CONDITION WHEN OTHER MOVE 'Not Storm Drain ' TO STORM-DRAIN-CONDITION END-EVALUATE. IF STORM-DRAIN-CONDITION NOT EQUAL 'Not Storm Drain ' DISPLAY 'DBCRFUN: Check-For-Storm-Drain-DB2: Storm ' 'Drain condition (' STORM-DRAIN-CONDITION ') ' 'has been met (' SQLCODE-DISPLAY ').' ELSE CONTINUE END-IF. CFSDD999. EXIT. | G17: Decisão e falha | H17: IF, EVALUATE, WHEN, falha | K17: infraestrutura (excluída) | L17: Validado | M17: Verificação de condição de storm drain do DB2 (EVALUATE SQLCODE, WHEN 923); infraestrutura. | N17: 4
A18: DBCRFUN-029 | B18: DBCRFUN | C18: 708-713 | D18: 716 | E18: Evaluate the Abend code that is returned - For DB2 AD2Z ... provide some diagnostics - For VSAM RLS abends: AFCR, AFCS and AFCT record the Abend as happening but do not abend ... leave this to CPSM WLM "Storm drain" (Abend probability) to handle If not a "storm drain" ... take the abend afterwards | F18: EVALUATE MY-ABEND-CODE | G18: Decisão | H18: EVALUATE | K18: infraestrutura (excluída) | L18: Validado | M18: Avaliação do código de ABEND (EVALUATE MY-ABEND-CODE) para diagnóstico e storm drain de DB2 e VSAM; infraestrutura. | N18: 1
A19: DBCRFUN-030 | B19: DBCRFUN | C19: 718 | D19: 720-735 | E19: DB2 AD2Z abend | F19: WHEN 'AD2Z' MOVE SQLCODE TO SQLCODE-DISPLAY DISPLAY 'DB2 DEADLOCK DETECTED IN DBCRFUN, SQLCODE=' SQLCODE-DISPLAY DISPLAY 'DB2 DEADLOCK FOR ACCOUNT ' HV-ACCOUNT-ACC-NO DISPLAY 'SQLSTATE=' SQLSTATE ',SQLERRMC=' SQLERRMC(1:SQLERRML) ',SQLERRD(1)=' SQLERRD(1) ',SQLERRD(2)=' SQLERRD(2) ',SQLERRD(3)=' SQLERRD(3) ',SQLERRD(4)=' SQLERRD(4) ',SQLERRD(5)=' SQLERRD(5) ',SQLERRD(6)=' SQLERRD(6) | G19: Decisão e falha | H19: WHEN, falha | I19: comentário curto | K19: infraestrutura (excluída) | L19: Validado | M19: Tratamento do ABEND AD2Z (deadlock DB2) com exibição de diagnósticos; infraestrutura. | N19: 1
A20: DBCRFUN-031 | B20: DBCRFUN | C20: 738-740 | D20: 742-756 | E20: VSAM RLS abends, subject to CPSM WLM Storm Drain check if handled (as here) and Workload Abend Thresholds are set. | F20: WHEN 'AFCR' WHEN 'AFCS' WHEN 'AFCT' MOVE 'Y' TO WS-STORM-DRAIN DISPLAY 'DBCRFUN: Check-For-Storm-Drain-VSAM: Storm ' 'Drain condition (Abend ' MY-ABEND-CODE ') ' 'has been met.' EXEC CICS SYNCPOINT ROLLBACK RESP(WS-CICS-RESP) RESP2(WS-CICS-RESP2) END-EXEC IF WS-CICS-RESP NOT = DFHRESP(NORMAL) | G20: Decisão e falha | H20: IF, WHEN, falha | K20: infraestrutura (excluída) | L20: Validado | M20: Tratamento dos ABEND AFCR, AFCS e AFCT (VSAM RLS, storm drain) com rollback; infraestrutura. | N20: 4
A21: DBCRFUN-032 | B21: DBCRFUN | C21: 758-761 | D21: 763-765 | E21: Preserve the RESP and RESP2, then set up the standard ABEND info before getting the applid, date/time etc. and linking to the Abend Handler program. | F21: INITIALIZE ABNDINFO-REC MOVE EIBRESP TO ABND-RESPCODE MOVE EIBRESP2 TO ABND-RESP2CODE | G21: Falha | H21: falha | K21: infraestrutura (excluída) | L21: Validado | M21: Montagem padrão das informações de ABEND (INITIALIZE ABNDINFO-REC; MOVE EIBRESP/EIBRESP2); tratamento técnico sem semântica bancária. | N21: 0
A22: DBCRFUN-033 | B22: DBCRFUN | C22: 767 | D22: 769-861 | E22: Get supplemental information | F22: EXEC CICS ASSIGN APPLID(ABND-APPLID) END-EXEC MOVE EIBTASKN TO ABND-TASKNO-KEY MOVE EIBTRNID TO ABND-TRANID PERFORM POPULATE-TIME-DATE MOVE WS-ORIG-DATE TO ABND-DATE STRING WS-TIME-NOW-GRP-HH DELIMITED BY SIZE, ':' DELIMITED BY SIZE, WS-TIME-NOW-GRP-MM DELIMITED BY SIZE, ':' DELIMITED BY SIZE, WS-TIME-NOW-GRP-MM DELIMITED BY SIZE INTO ABND-TIME END-STRING MOVE WS-U-TIME TO ABND-UTIME-KEY MOVE 'HROL' TO ABND-CODE EXEC CICS ASSIGN PROGRAM(ABND-PROGRAM) END-EXEC MOVE ZEROS TO ABND-SQLCODE STRING 'AH010 - Unable to perform Synpoint ' DELIMITED BY SIZE, 'Rollback.' DELIMITED BY SIZE, ' Possible Integrity issue following VSAM RLS ' DELIMITED BY SIZE, 'abend.' DELIMITED BY SIZE, 'EIBRESP=' DELIMITED BY SIZE, ABND-RESPCODE DELIMITED BY SIZE, ' RESP2=' DELIMITED BY SIZE, ABND-RESP2CODE DELIMITED BY SIZE INTO ABND-FREEFORM END-STRING EXEC CICS LINK PROGRAM(WS-ABEND-PGM) COMMAREA(ABNDINFO-REC) END-EXEC DISPLAY 'DBCRFUN: Unable to perform Synpoint ' 'Rollback.' ' Possible Integrity issue following VSAM RLS' ' abend' ' RESP CODE=' WS-CICS-RESP ' RESP2 CODE=' WS-CICS-RESP2 EXEC CICS ABEND ABCODE ('HROL') CANCEL END-EXEC END-IF MOVE 'N' TO COMM-SUCCESS MOVE '2' TO COMM-FAIL-CODE EXEC CICS RETURN END-EXEC END-EVALUATE. IF WS-STORM-DRAIN = 'N' | G22: Decisão e falha | H22: IF, falha | I22: comentário curto; trecho truncado (exibidas 50 de 71 linhas) | K22: infraestrutura (excluída) | L22: Validado | M22: Coleta de informações complementares de ABEND (PERFORM POPULATE-TIME-DATE, LINK ao tratador de ABEND, ABEND); tratamento técnico sem semântica bancária. Inclui a verificação de storm drain (IF WS-STORM-DRAIN = 'N' seguido de ABEND), que você definiu como infraestrutura. Exibidas 50 de 71 linhas: conferir no fonte o final do trecho (até a linha 861). Estava como 'Manter descartado' na planilha anterior. | N22: 1
A23: XFRFUN-001 | B23: XFRFUN | C23: 286-287 | D23: 289-296 | E23: If the amount being transferred is negative, then flag this as a failure and finish. | F23: IF COMM-AMT <= ZERO MOVE 'N' TO COMM-SUCCESS MOVE '4' TO COMM-FAIL-CODE PERFORM GET-ME-OUT-OF-HERE END-IF. PERFORM UPDATE-ACCOUNT-DB2 | G23: Decisão | H23: IF | J23: Se o valor a transferir for menor ou igual a zero, a transferência é negada e a operação é sinalizada como malsucedida com o código de falha '4'. | K23: regra de negócio | L23: A validar | M23: [Rascunho] Divergência: o comentário fala em valor negativo, mas o código testa <= ZERO, ou seja, zero também é recusado. O código '4' é traduzido na tela como 'Please supply an amount greater than zero.' (BNK1TFN-026). A consequência final (GET-ME-OUT-OF-HERE) encerra o programa; o PERFORM UPDATE-ACCOUNT-DB2 ao fim do trecho fica fora da regra. | N23: 1
A24: XFRFUN-003 | B24: XFRFUN | C24: 313-314 | D24: 316-317 | E24: Are we trying to transfer from and to the same account? We don't allow that. | F24: IF COMM-FACCNO = COMM-TACCNO AND COMM-FSCODE = COMM-TSCODE | G24: Decisão | H24: IF | J24: Se a conta de origem e a conta de destino forem a mesma (mesmo número e mesmo código de agência), a transferência não é permitida e o programa é encerrado com ABEND de código 'SAME'. | K24: regra de negócio | L24: A validar | M24: [Rascunho] Esta linha contém só a condição. A consequência (DISPLAY 'Cannot transfer to the same account' e ABEND 'SAME') está no bloco seguinte do fonte (linhas 318-379), fundido na XFRFUN-004 pelo extrator. A mesma restrição é validada na tela em BNK1TFN-019 (contas devem ser diferentes), com mensagem ao usuário. | N24: 1
A25: XFRFUN-004 | B25: XFRFUN | C25: 319-322 | D25: 324-326 | E25: Preserve the RESP and RESP2, then set up the standard ABEND info before getting the applid, date/time etc. and linking to the Abend Handler program. | F25: INITIALIZE ABNDINFO-REC MOVE EIBRESP TO ABND-RESPCODE MOVE EIBRESP2 TO ABND-RESP2CODE | G25: Falha | H25: falha | K25: infraestrutura (excluída) | L25: Validado | M25: Montagem de ABEND que compõe a consequência do IF de mesma conta (XFRFUN-003); a regra de negócio está registrada na 003. Montagem padrão das informações de ABEND (INITIALIZE ABNDINFO-REC; MOVE EIBRESP/EIBRESP2); tratamento técnico sem semântica bancária. | N25: 0
A26: XFRFUN-005 | B26: XFRFUN | C26: 328 | D26: 330-378 | E26: Get supplemental information | F26: EXEC CICS ASSIGN APPLID(ABND-APPLID) END-EXEC MOVE EIBTASKN TO ABND-TASKNO-KEY MOVE EIBTRNID TO ABND-TRANID PERFORM POPULATE-TIME-DATE MOVE WS-ORIG-DATE TO ABND-DATE STRING WS-TIME-NOW-GRP-HH DELIMITED BY SIZE, ':' DELIMITED BY SIZE, WS-TIME-NOW-GRP-MM DELIMITED BY SIZE, ':' DELIMITED BY SIZE, WS-TIME-NOW-GRP-MM DELIMITED BY SIZE INTO ABND-TIME END-STRING MOVE WS-U-TIME TO ABND-UTIME-KEY MOVE 'SAME' TO ABND-CODE EXEC CICS ASSIGN PROGRAM(ABND-PROGRAM) END-EXEC MOVE ZEROS TO ABND-SQLCODE STRING 'UAD010 - Cannot transfer to the same account ' DELIMITED BY SIZE, ' EIBRESP=' DELIMITED BY SIZE, ABND-RESPCODE DELIMITED BY SIZE, ' RESP2=' DELIMITED BY SIZE, ABND-RESP2CODE DELIMITED BY SIZE INTO ABND-FREEFORM END-STRING EXEC CICS LINK PROGRAM(WS-ABEND-PGM) COMMAREA(ABNDINFO-REC) END-EXEC DISPLAY 'Cannot transfer to the same account' EXEC CICS ABEND ABCODE('SAME') NODUMP CANCEL END-EXEC END-IF. IF COMM-FACCNO < COMM-TACCNO | G26: Decisão e falha | H26: IF, falha | I26: comentário curto | K26: infraestrutura (excluída) | L26: Validado | M26: Coleta de informações complementares de ABEND (PERFORM POPULATE-TIME-DATE, LINK ao tratador de ABEND, ABEND); tratamento técnico sem semântica bancária. O IF da linha 378, no fim do trecho, é o cabeçalho da regra de ordem de atualização (XFRFUN-006); o tipo 'Decisão e falha' vem dele. | N26: 1
A27: XFRFUN-006 | B27: XFRFUN | C27: 380-381 | D27: 378; 383-384 | E27: If the FROM account number is less than the TO account number | F27: [cab.] IF COMM-FACCNO < COMM-TACCNO MOVE COMM-FACCNO TO DESIRED-ACC-NO MOVE COMM-FSCODE TO DESIRED-SORT-CODE | G27: Decisão | H27: IF (cabeçalho) | I27: decisão no cabeçalho anterior ao comentário (linha 378) | J27: Se o número da conta de origem for menor que o número da conta de destino, a conta de origem é a primeira a ser atualizada. | K27: a discutir | L27: A validar | M27: [Rascunho] O IF da linha 378 vem antes do comentário e aparece como [cab.]. O comentário e o código só selecionam a conta de origem (MOVE para DESIRED-ACC-NO); a atualização está nas linhas seguintes (XFRFUN-007 e 008). Nenhum comentário do fonte explica por que a ordem depende do número da conta. O programa trata deadlock do DB2 com retentativas (DB2-DEADLOCK-RETRY), o que sugere controle de concorrência, mas isso é inferência. Decidir com o orientador se é regra de negócio ou infraestrutura. | N27: 1
A28: XFRFUN-008 | B28: XFRFUN | C28: 392 | D28: 394-398 | E28: If the update was successful, update the TO account | F28: IF COMM-SUCCESS = 'Y' MOVE COMM-TACCNO TO DESIRED-ACC-NO MOVE COMM-TSCODE TO DESIRED-SORT-CODE PERFORM UPDATE-ACCOUNT-DB2-TO | G28: Decisão | H28: IF | J28: Se a atualização da conta de origem for bem-sucedida, a conta de destino é atualizada. | K28: regra de negócio | L28: A validar | M28: [Rascunho] Ramo em que o número da conta de origem é menor que o da conta de destino (XFRFUN-006, Descartados). A ordem por número de conta é aspecto técnico e fica fora da regra. Estrutura espelhada na XFRFUN-019 (ordem inversa). Falhas seguem para rollback/ABEND (XFRFUN-009 a 015). | N28: 1
A29: XFRFUN-009 | B29: XFRFUN | C29: 401-402 | D29: 404-413 | E29: If the update to the TO account was unsuccessful then we need to flag it and roll it back | F29: IF COMM-SUCCESS = 'N' IF COMM-FAIL-CODE = '2' EXEC CICS SYNCPOINT ROLLBACK RESP(WS-CICS-RESP) RESP2(WS-CICS-RESP2) END-EXEC IF WS-CICS-RESP IS NOT EQUAL TO DFHRESP(NORMAL) | G29: Decisão e falha | H29: IF, falha | K29: infraestrutura (excluída) | L29: Validado | M29: Falha na atualização da conta de destino (COMM-SUCCESS = 'N') com código '2': rollback; se o rollback falhar, ABEND (010 e 011); com outro código, ABEND 'TO' (012). Fluxo de rollback/ABEND, tratado como infraestrutura. O efeito de negócio (transferência não efetivada pela metade) decorre do rollback: decidir se deve virar regra. | N29: 3
A30: XFRFUN-010 | B30: XFRFUN | C30: 415-418 | D30: 420-422 | E30: Preserve the RESP and RESP2, then set up the standard ABEND info before getting the applid, date/time etc. and linking to the Abend Handler program. | F30: INITIALIZE ABNDINFO-REC MOVE EIBRESP TO ABND-RESPCODE MOVE EIBRESP2 TO ABND-RESP2CODE | G30: Falha | H30: falha | K30: infraestrutura (excluída) | L30: Validado | M30: Montagem padrão das informações de ABEND (INITIALIZE ABNDINFO-REC; MOVE EIBRESP/EIBRESP2); tratamento técnico sem semântica bancária. | N30: 0
A31: XFRFUN-011 | B31: XFRFUN | C31: 424 | D31: 426-481 | E31: Get supplemental information | F31: EXEC CICS ASSIGN APPLID(ABND-APPLID) END-EXEC MOVE EIBTASKN TO ABND-TASKNO-KEY MOVE EIBTRNID TO ABND-TRANID PERFORM POPULATE-TIME-DATE MOVE WS-ORIG-DATE TO ABND-DATE STRING WS-TIME-NOW-GRP-HH DELIMITED BY SIZE, ':' DELIMITED BY SIZE, WS-TIME-NOW-GRP-MM DELIMITED BY SIZE, ':' DELIMITED BY SIZE, WS-TIME-NOW-GRP-MM DELIMITED BY SIZE INTO ABND-TIME END-STRING MOVE WS-U-TIME TO ABND-UTIME-KEY MOVE 'HROL' TO ABND-CODE EXEC CICS ASSIGN PROGRAM(ABND-PROGRAM) END-EXEC MOVE ZEROS TO ABND-SQLCODE STRING 'UAD010(2) - Error on SYNCPOINT' DELIMITED BY SIZE, ' ROLLBACK' DELIMITED BY SIZE, ' after UPDATING TO account ' DELIMITED BY SIZE, ' EIBRESP=' DELIMITED BY SIZE, ABND-RESPCODE DELIMITED BY SIZE, ' RESP2=' DELIMITED BY SIZE, ABND-RESP2CODE DELIMITED BY SIZE INTO ABND-FREEFORM END-STRING EXEC CICS LINK PROGRAM(WS-ABEND-PGM) COMMAREA(ABNDINFO-REC) END-EXEC DISPLAY 'XFRFUN error syncpoint rollback' ' after updating TO account ' ',RESP=' WS-CICS-RESP ',RESP2=' WS-CICS-RESP2 EXEC CICS ABEND ABCODE('HROL') NODUMP CANCEL END-EXEC END-IF GO TO UAD999 ELSE | G31: Falha | H31: falha | I31: comentário curto; contém GO TO (desvio incondicional) | K31: infraestrutura (excluída) | L31: Validado | M31: Coleta de informações complementares de ABEND (PERFORM POPULATE-TIME-DATE, LINK ao tratador de ABEND, ABEND); tratamento técnico sem semântica bancária. Termina com GO TO UAD999; o ELSE da linha 481 é o cabeçalho do comentário seguinte. | N31: 0
A32: XFRFUN-012 | B32: XFRFUN | C32: 483-484 | D32: 486-496 | E32: If the COMM-FLAG is anything else other than 2 then abend. | F32: DISPLAY 'Error updating TO account' EXEC CICS ABEND ABCODE('TO ') NODUMP END-EXEC END-IF END-IF ELSE | G32: Falha | H32: falha | K32: infraestrutura (excluída) | L32: Validado | M32: ABEND 'TO' quando o código de falha da conta de destino não é '2'. O comentário cita COMM-FLAG, mas o código testa COMM-FAIL-CODE. Tratamento de ABEND. | N32: 0
A33: XFRFUN-013 | B33: XFRFUN | C33: 498-499 | D33: 501-507 | E33: If the update to the FROM account was not successful rollback. | F33: IF COMM-FAIL-CODE = '1' EXEC CICS SYNCPOINT ROLLBACK RESP(WS-CICS-RESP) RESP2(WS-CICS-RESP2) END-EXEC | G33: Decisão | H33: IF | K33: infraestrutura (excluída) | L33: Validado | M33: Rollback quando a atualização da conta de origem falha com código '1'. O comentário diz apenas 'not successful', mas o código testa COMM-FAIL-CODE = '1'. Infraestrutura transacional. | N33: 1
A34: XFRFUN-014 | B34: XFRFUN | C34: 510 | D34: 512-526 | E34: If the ROLLback failed | F34: IF WS-CICS-RESP IS NOT EQUAL TO DFHRESP(NORMAL) DISPLAY 'XFRFUN error syncpoint ' ' rollback after ' 'updating FROM account ' ',RESP=' WS-CICS-RESP ',RESP2=' WS-CICS-RESP2 EXEC CICS ABEND ABCODE('HROL') NODUMP END-EXEC END-IF GO TO UAD999 ELSE | G34: Decisão e falha | H34: IF, falha | I34: contém GO TO (desvio incondicional) | K34: infraestrutura (excluída) | L34: Validado | M34: Falha do rollback após atualizar a conta de origem: DISPLAY e ABEND 'HROL'; infraestrutura. | N34: 1
A35: XFRFUN-015 | B35: XFRFUN | C35: 528-531 | D35: 533-535 | E35: Preserve the RESP and RESP2, then set up the standard ABEND info before getting the applid, date/time etc. and linking to the Abend Handler program. | F35: INITIALIZE ABNDINFO-REC MOVE EIBRESP TO ABND-RESPCODE MOVE EIBRESP2 TO ABND-RESP2CODE | G35: Falha | H35: falha | K35: infraestrutura (excluída) | L35: Validado | M35: Montagem padrão das informações de ABEND (INITIALIZE ABNDINFO-REC; MOVE EIBRESP/EIBRESP2); tratamento técnico sem semântica bancária. | N35: 0
A36: XFRFUN-016 | B36: XFRFUN | C36: 537 | D36: 539-589 | E36: Get supplemental information | F36: EXEC CICS ASSIGN APPLID(ABND-APPLID) END-EXEC MOVE EIBTASKN TO ABND-TASKNO-KEY MOVE EIBTRNID TO ABND-TRANID PERFORM POPULATE-TIME-DATE MOVE WS-ORIG-DATE TO ABND-DATE STRING WS-TIME-NOW-GRP-HH DELIMITED BY SIZE, ':' DELIMITED BY SIZE, WS-TIME-NOW-GRP-MM DELIMITED BY SIZE, ':' DELIMITED BY SIZE, WS-TIME-NOW-GRP-MM DELIMITED BY SIZE INTO ABND-TIME END-STRING MOVE WS-U-TIME TO ABND-UTIME-KEY MOVE 'FROM' TO ABND-CODE EXEC CICS ASSIGN PROGRAM(ABND-PROGRAM) END-EXEC MOVE ZEROS TO ABND-SQLCODE STRING 'UAD010(3) - Error updating FROM account ' DELIMITED BY SIZE, ' EIBRESP=' DELIMITED BY SIZE, ABND-RESPCODE DELIMITED BY SIZE, ' RESP2=' DELIMITED BY SIZE, ABND-RESP2CODE DELIMITED BY SIZE INTO ABND-FREEFORM END-STRING EXEC CICS LINK PROGRAM(WS-ABEND-PGM) COMMAREA(ABNDINFO-REC) END-EXEC DISPLAY 'Error updating FROM account' EXEC CICS ABEND ABCODE('FROM') NODUMP CANCEL END-EXEC END-IF END-IF ELSE | G36: Falha | H36: falha | I36: comentário curto | K36: infraestrutura (excluída) | L36: Validado | M36: Coleta de informações complementares de ABEND (PERFORM POPULATE-TIME-DATE, LINK ao tratador de ABEND, ABEND); tratamento técnico sem semântica bancária. O ELSE da linha 589, no fim do trecho, é o cabeçalho da XFRFUN-017. | N36: 0
A37: XFRFUN-017 | B37: XFRFUN | C37: 591-592 | D37: 589; 594-595 | E37: The FROM account number is greater than the TO account number | F37: [cab.] ELSE MOVE COMM-TACCNO TO DESIRED-ACC-NO MOVE COMM-TSCODE TO DESIRED-SORT-CODE | G37: Decisão | H37: ELSE (cabeçalho) | I37: decisão no cabeçalho anterior ao comentário (linha 589) | J37: Se o número da conta de origem for maior que o número da conta de destino, a conta de destino é a primeira a ser atualizada. | K37: a discutir | L37: A validar | M37: [Rascunho] O ELSE da linha 589 vem antes do comentário e aparece como [cab.]. O comentário diz 'maior que', mas o código é um ELSE de 'FROM < TO', que também cobre número de conta igual com sort code diferente (a checagem de contas iguais, linhas 316-317, usa número e sort code): possível divergência comentário x código para o anexo. Mesma dúvida de categoria da XFRFUN-006. | N37: 1
A38: XFRFUN-019 | B38: XFRFUN | C38: 603-604 | D38: 606-610 | E38: If the update to the TO account was successful then update the FROM account | F38: IF COMM-SUCCESS = 'Y' MOVE COMM-FACCNO TO DESIRED-ACC-NO MOVE COMM-FSCODE TO DESIRED-SORT-CODE PERFORM UPDATE-ACCOUNT-DB2-FROM | G38: Decisão | H38: IF | J38: Se a atualização da conta de destino for bem-sucedida, a conta de origem é atualizada. | K38: regra de negócio | L38: A validar | M38: [Rascunho] Ramo em que o número da conta de origem é maior que o da conta de destino (ordem inversa da XFRFUN-008). A ordem por número de conta é aspecto técnico e fica fora da regra. | N38: 1
A39: XFRFUN-020 | B39: XFRFUN | C39: 613 | D39: 615-617 | E39: Did the update to the FROM account work? | F39: IF COMM-SUCCESS = 'N' IF COMM-FAIL-CODE NOT = '1' | G39: Decisão | H39: IF | K39: infraestrutura (excluída) | L39: Validado | M39: Se a atualização da conta de origem falhar (COMM-SUCCESS = 'N') com código diferente de '1', ABEND 'FROM'; com código '1', rollback (XFRFUN-023, Descartados). Fluxo de ABEND/rollback. | N39: 2
A40: XFRFUN-021 | B40: XFRFUN | C40: 619-622 | D40: 624-626 | E40: Preserve the RESP and RESP2, then set up the standard ABEND info before getting the applid, date/time etc. and linking to the Abend Handler program. | F40: INITIALIZE ABNDINFO-REC MOVE EIBRESP TO ABND-RESPCODE MOVE EIBRESP2 TO ABND-RESP2CODE | G40: Falha | H40: falha | K40: infraestrutura (excluída) | L40: Validado | M40: Montagem padrão das informações de ABEND (INITIALIZE ABNDINFO-REC; MOVE EIBRESP/EIBRESP2); tratamento técnico sem semântica bancária. | N40: 0
A41: XFRFUN-022 | B41: XFRFUN | C41: 628 | D41: 630-675 | E41: Get supplemental information | F41: EXEC CICS ASSIGN APPLID(ABND-APPLID) END-EXEC MOVE EIBTASKN TO ABND-TASKNO-KEY MOVE EIBTRNID TO ABND-TRANID PERFORM POPULATE-TIME-DATE MOVE WS-ORIG-DATE TO ABND-DATE STRING WS-TIME-NOW-GRP-HH DELIMITED BY SIZE, ':' DELIMITED BY SIZE, WS-TIME-NOW-GRP-MM DELIMITED BY SIZE, ':' DELIMITED BY SIZE, WS-TIME-NOW-GRP-MM DELIMITED BY SIZE INTO ABND-TIME END-STRING MOVE WS-U-TIME TO ABND-UTIME-KEY MOVE 'FROM' TO ABND-CODE EXEC CICS ASSIGN PROGRAM(ABND-PROGRAM) END-EXEC MOVE ZEROS TO ABND-SQLCODE STRING 'UAD010(4) - Error updating FROM account ' DELIMITED BY SIZE, ' EIBRESP=' DELIMITED BY SIZE, ABND-RESPCODE DELIMITED BY SIZE, ' RESP2=' DELIMITED BY SIZE, ABND-RESP2CODE DELIMITED BY SIZE INTO ABND-FREEFORM END-STRING EXEC CICS LINK PROGRAM(WS-ABEND-PGM) COMMAREA(ABNDINFO-REC) END-EXEC DISPLAY 'Error updating FROM account' EXEC CICS ABEND ABCODE('FROM') NODUMP CANCEL END-EXEC ELSE | G41: Falha | H41: falha | I41: comentário curto | K41: infraestrutura (excluída) | L41: Validado | M41: Coleta de informações complementares de ABEND (PERFORM POPULATE-TIME-DATE, LINK ao tratador de ABEND, ABEND); tratamento técnico sem semântica bancária. O ELSE da linha 675, no fim do trecho, é o cabeçalho da XFRFUN-023. | N41: 0
A42: XFRFUN-023 | B42: XFRFUN | C42: 677 | D42: 675; 679-683 | E42: If the FAIL code is something else | F42: [cab.] ELSE EXEC CICS SYNCPOINT ROLLBACK RESP(WS-CICS-RESP) RESP2(WS-CICS-RESP2) END-EXEC | G42: Decisão | H42: ELSE (cabeçalho) | I42: decisão no cabeçalho anterior ao comentário (linha 675) | K42: infraestrutura (excluída) | L42: Validado | M42: O ELSE da linha 675 vem antes do comentário e aparece como [cab.]. Rollback da transação (EXEC CICS SYNCPOINT ROLLBACK) quando o código de falha é diferente do tratado no ramo anterior; infraestrutura, no mesmo critério do rollback do DBCRFUN-012 e 013. | N42: 1
A43: XFRFUN-024 | B43: XFRFUN | C43: 685 | D43: 687 | E43: If that rollback didn't work | F43: IF WS-CICS-RESP IS NOT EQUAL TO DFHRESP(NORMAL) | G43: Decisão e falha | H43: IF, falha | K43: infraestrutura (excluída) | L43: Validado | M43: Verificação do RESP do rollback executado após falha na conta de origem; infraestrutura transacional. | N43: 1
A44: XFRFUN-025 | B44: XFRFUN | C44: 689-692 | D44: 694-696 | E44: Preserve the RESP and RESP2, then set up the standard ABEND info before getting the applid, date/time etc. and linking to the Abend Handler program. | F44: INITIALIZE ABNDINFO-REC MOVE EIBRESP TO ABND-RESPCODE MOVE EIBRESP2 TO ABND-RESP2CODE | G44: Falha | H44: falha | K44: infraestrutura (excluída) | L44: Validado | M44: Montagem padrão das informações de ABEND (INITIALIZE ABNDINFO-REC; MOVE EIBRESP/EIBRESP2); tratamento técnico sem semântica bancária. | N44: 0
A45: XFRFUN-026 | B45: XFRFUN | C45: 698 | D45: 700-760 | E45: Get supplemental information | F45: EXEC CICS ASSIGN APPLID(ABND-APPLID) END-EXEC MOVE EIBTASKN TO ABND-TASKNO-KEY MOVE EIBTRNID TO ABND-TRANID PERFORM POPULATE-TIME-DATE MOVE WS-ORIG-DATE TO ABND-DATE STRING WS-TIME-NOW-GRP-HH DELIMITED BY SIZE, ':' DELIMITED BY SIZE, WS-TIME-NOW-GRP-MM DELIMITED BY SIZE, ':' DELIMITED BY SIZE, WS-TIME-NOW-GRP-MM DELIMITED BY SIZE INTO ABND-TIME END-STRING MOVE WS-U-TIME TO ABND-UTIME-KEY MOVE 'HROL' TO ABND-CODE EXEC CICS ASSIGN PROGRAM(ABND-PROGRAM) END-EXEC MOVE ZEROS TO ABND-SQLCODE STRING 'UAD010(5) - Error on SYNCPOINT ' DELIMITED BY SIZE, ' ROLLBACK ' DELIMITED BY SIZE, ' after UPDATING the FROM account' DELIMITED BY SIZE, ' EIBRESP=' DELIMITED BY SIZE, ABND-RESPCODE DELIMITED BY SIZE, ' RESP2=' DELIMITED BY SIZE, ABND-RESP2CODE DELIMITED BY SIZE INTO ABND-FREEFORM END-STRING EXEC CICS LINK PROGRAM(WS-ABEND-PGM) COMMAREA(ABNDINFO-REC) END-EXEC DISPLAY 'XFRFUN error syncpoint ' ' rollback after ' 'updating FROM account ' ',RESP=' WS-CICS-RESP ',RESP2=' WS-CICS-RESP2 EXEC CICS ABEND ABCODE('HROL') NODUMP CANCEL END-EXEC END-IF GO TO UAD999 END-IF END-IF ELSE | G45: Falha | H45: falha | I45: comentário curto; contém GO TO (desvio incondicional) | K45: infraestrutura (excluída) | L45: Validado | M45: Coleta de informações complementares de ABEND (PERFORM POPULATE-TIME-DATE, LINK ao tratador de ABEND, ABEND); tratamento técnico sem semântica bancária. Termina com GO TO UAD999; o ELSE da linha 760 é o cabeçalho do comentário seguinte. | N45: 0
A46: XFRFUN-027 | B46: XFRFUN | C46: 763-764 | D46: 766 | E46: If the update to the TO account was NOT successful & the fail code isn't = '2' | F46: IF COMM-FAIL-CODE NOT = '2' | G46: Decisão | H46: IF | K46: infraestrutura (excluída) | L46: Validado | M46: Se a atualização da conta de destino falhar com código diferente de '2', ABEND (XFRFUN-028 a 030); fluxo de ABEND. | N46: 1
A47: XFRFUN-028 | B47: XFRFUN | C47: 768-771 | D47: 773-775 | E47: Preserve the RESP and RESP2, then set up the standard ABEND info before getting the applid, date/time etc. and linking to the Abend Handler program. | F47: INITIALIZE ABNDINFO-REC MOVE EIBRESP TO ABND-RESPCODE MOVE EIBRESP2 TO ABND-RESP2CODE | G47: Falha | H47: falha | K47: infraestrutura (excluída) | L47: Validado | M47: Montagem padrão das informações de ABEND (INITIALIZE ABNDINFO-REC; MOVE EIBRESP/EIBRESP2); tratamento técnico sem semântica bancária. | N47: 0
A48: XFRFUN-029 | B48: XFRFUN | C48: 777 | D48: 779-832 | E48: Get supplemental information | F48: EXEC CICS ASSIGN APPLID(ABND-APPLID) END-EXEC MOVE EIBTASKN TO ABND-TASKNO-KEY MOVE EIBTRNID TO ABND-TRANID PERFORM POPULATE-TIME-DATE MOVE WS-ORIG-DATE TO ABND-DATE STRING WS-TIME-NOW-GRP-HH DELIMITED BY SIZE, ':' DELIMITED BY SIZE, WS-TIME-NOW-GRP-MM DELIMITED BY SIZE, ':' DELIMITED BY SIZE, WS-TIME-NOW-GRP-MM DELIMITED BY SIZE INTO ABND-TIME END-STRING MOVE WS-U-TIME TO ABND-UTIME-KEY MOVE 'TO ' TO ABND-CODE EXEC CICS ASSIGN PROGRAM(ABND-PROGRAM) END-EXEC MOVE ZEROS TO ABND-SQLCODE STRING 'UAD010(6) - Error updating TO account ' DELIMITED BY SIZE, ' EIBRESP=' DELIMITED BY SIZE, ABND-RESPCODE DELIMITED BY SIZE, ' RESP2=' DELIMITED BY SIZE, ABND-RESP2CODE DELIMITED BY SIZE INTO ABND-FREEFORM END-STRING EXEC CICS LINK PROGRAM(WS-ABEND-PGM) COMMAREA(ABNDINFO-REC) END-EXEC DISPLAY 'Error updating TO account' EXEC CICS ABEND ABCODE('TO ') CANCEL NODUMP END-EXEC ELSE EXEC CICS SYNCPOINT ROLLBACK RESP(WS-CICS-RESP) RESP2(WS-CICS-RESP2) END-EXEC IF WS-CICS-RESP IS NOT EQUAL TO DFHRESP(NORMAL) | G48: Decisão e falha | H48: IF, falha | I48: comentário curto | K48: infraestrutura (excluída) | L48: Validado | M48: Coleta de informações complementares de ABEND (PERFORM POPULATE-TIME-DATE, LINK ao tratador de ABEND, ABEND); tratamento técnico sem semântica bancária. Inclui SYNCPOINT ROLLBACK (linhas 826-827). O IF da linha 832, no fim do trecho, é cabeçalho do comentário seguinte e é ele que dá o tipo 'Decisão e falha'. | N48: 1
A49: XFRFUN-030 | B49: XFRFUN | C49: 834-837 | D49: 839-841 | E49: Preserve the RESP and RESP2, then set up the standard ABEND info before getting the applid, date/time etc. and linking to the Abend Handler program. | F49: INITIALIZE ABNDINFO-REC MOVE EIBRESP TO ABND-RESPCODE MOVE EIBRESP2 TO ABND-RESP2CODE | G49: Falha | H49: falha | K49: infraestrutura (excluída) | L49: Validado | M49: Montagem padrão das informações de ABEND (INITIALIZE ABNDINFO-REC; MOVE EIBRESP/EIBRESP2); tratamento técnico sem semântica bancária. | N49: 0
A50: XFRFUN-031 | B50: XFRFUN | C50: 843 | D50: 845-904 | E50: Get supplemental information | F50: EXEC CICS ASSIGN APPLID(ABND-APPLID) END-EXEC MOVE EIBTASKN TO ABND-TASKNO-KEY MOVE EIBTRNID TO ABND-TRANID PERFORM POPULATE-TIME-DATE MOVE WS-ORIG-DATE TO ABND-DATE STRING WS-TIME-NOW-GRP-HH DELIMITED BY SIZE, ':' DELIMITED BY SIZE, WS-TIME-NOW-GRP-MM DELIMITED BY SIZE, ':' DELIMITED BY SIZE, WS-TIME-NOW-GRP-MM DELIMITED BY SIZE INTO ABND-TIME END-STRING MOVE WS-U-TIME TO ABND-UTIME-KEY MOVE 'HROL' TO ABND-CODE EXEC CICS ASSIGN PROGRAM(ABND-PROGRAM) END-EXEC MOVE ZEROS TO ABND-SQLCODE STRING 'UAD010(7) - Error on SYNCPOINT ROLLBACK' DELIMITED BY SIZE, ' after UPDATING the TO account' DELIMITED BY SIZE, ' EIBRESP=' DELIMITED BY SIZE, ABND-RESPCODE DELIMITED BY SIZE, ' RESP2=' DELIMITED BY SIZE, ABND-RESP2CODE DELIMITED BY SIZE INTO ABND-FREEFORM END-STRING EXEC CICS LINK PROGRAM(WS-ABEND-PGM) COMMAREA(ABNDINFO-REC) END-EXEC DISPLAY 'XFRFUN error syncpoint rollback after ' 'updating TO account ' ',RESP=' WS-CICS-RESP ',RESP2=' WS-CICS-RESP2 EXEC CICS ABEND ABCODE('HROL') NODUMP CANCEL END-EXEC END-IF GO TO UAD999 END-IF END-IF END-IF. | G50: Falha | H50: falha | I50: comentário curto; contém GO TO (desvio incondicional) | K50: infraestrutura (excluída) | L50: Validado | M50: Coleta de informações complementares de ABEND (PERFORM POPULATE-TIME-DATE, LINK ao tratador de ABEND, ABEND); tratamento técnico sem semântica bancária. Contém GO TO UAD999 (linha 898). | N50: 0
A51: XFRFUN-034 | B51: XFRFUN | C51: 961-962 | D51: 964-971 | E51: Check that select was successful. If it wasn't then set the COMMAREA return flags accordingly. | F51: IF SQLCODE NOT = 0 MOVE 'N' TO COMM-SUCCESS IF SQLCODE = +100 MOVE '1' TO COMM-FAIL-CODE ELSE MOVE '3' TO COMM-FAIL-CODE END-IF | G51: Decisão e falha | H51: IF, falha | J51: 1. Se a conta de origem não for encontrada (SQLCODE igual a +100), a operação é sinalizada como malsucedida com o código de falha '1'. 2. Se a leitura da conta de origem falhar por motivo diferente de conta não encontrada, a operação é sinalizada como malsucedida com o código de falha '3'. | K51: regra de negócio | L51: A validar | M51: [Rascunho] Mesmo desenho da DBCRFUN-005. O código '1' vira mensagem 'FROM ACCOUNT no was not found' (BNK1TFN-026); o '3' é falha técnica ('unexpected error'): a regra 2 pode ser 'a discutir'. O trecho termina antes do storm drain (XFRFUN-035, Descartados). | N51: 2
A52: XFRFUN-037 | B52: XFRFUN | C52: 1011-1012 | D52: 1014-1017 | E52: If the RESP CODE was NOT OK then we need to indicate a failure | F52: IF SQLCODE NOT = 0 MOVE 'N' TO COMM-SUCCESS MOVE '3' TO COMM-FAIL-CODE | G52: Decisão e falha | H52: IF, falha | J52: Se a atualização da conta de origem falhar (SQLCODE diferente de zero), a operação é sinalizada como malsucedida com o código de falha '3'. | K52: a discutir | L52: A validar | M52: [Rascunho] Falha técnica de DB2 na atualização, tratada em conjunto com o código '3' da XFRFUN-034. O trecho termina antes do storm drain (XFRFUN-038, Descartados). | N52: 1
A53: XFRFUN-041 | B53: XFRFUN | C53: 1088-1089 | D53: 1091-1092 | E53: Check that SELECT was successful. If it wasn't then set the return flags accordingly. | F53: IF SQLCODE NOT = 0 MOVE 'N' TO COMM-SUCCESS | G53: Decisão e falha | H53: IF, falha | J53: Se a leitura da conta de destino não for bem-sucedida (SQLCODE diferente de zero), a operação é sinalizada como malsucedida. | K53: regra de negócio | L53: A validar | M53: [Rascunho] As consequências específicas estão nas XFRFUN-043 (código '2') e 046 (código '3'); esta regra pode ser absorvida por elas para evitar redundância (decisão do revisor). | N53: 1
A54: XFRFUN-043 | B54: XFRFUN | C54: 1100 | D54: 1102-1116 | E54: If the TO account was not found | F54: IF SQLCODE = +100 MOVE '2' TO COMM-FAIL-CODE MOVE SQLCODE TO SQLCODE-DISPLAY DISPLAY 'UPDATE UNABLE TO READ TO ACC' HV-ACCOUNT-SORTCODE '/' HV-ACCOUNT-ACC-NO ' ROLLBACK TO AVOID DATA INCONSISTENCY.' 'SQLCODE=' SQLCODE-DISPLAY EXEC CICS SYNCPOINT ROLLBACK RESP(WS-CICS-RESP) RESP2(WS-CICS-RESP2) END-EXEC IF WS-CICS-RESP IS NOT EQUAL TO DFHRESP(NORMAL) | G54: Decisão e falha | H54: IF, falha | J54: Se a conta de destino não for encontrada (SQLCODE igual a +100), a operação é sinalizada como malsucedida com o código de falha '2'. | K54: regra de negócio | L54: A validar | M54: [Rascunho] O trecho inclui DISPLAY e rollback ('to avoid data inconsistency'), tratados como infraestrutura e fora da regra. O código '2' vira a mensagem 'TO ACCOUNT no was not found' (BNK1TFN-026). | N54: 2
A55: XFRFUN-044 | B55: XFRFUN | C55: 1118-1121 | D55: 1123-1125 | E55: Preserve the RESP and RESP2, then set up the standard ABEND info before getting the applid, date/time etc. and linking to the Abend Handler program. | F55: INITIALIZE ABNDINFO-REC MOVE EIBRESP TO ABND-RESPCODE MOVE EIBRESP2 TO ABND-RESP2CODE | G55: Falha | H55: falha | K55: infraestrutura (excluída) | L55: Validado | M55: Montagem padrão das informações de ABEND (INITIALIZE ABNDINFO-REC; MOVE EIBRESP/EIBRESP2); tratamento técnico sem semântica bancária. | N55: 0
A56: XFRFUN-045 | B56: XFRFUN | C56: 1127 | D56: 1129-1183 | E56: Get supplemental information | F56: EXEC CICS ASSIGN APPLID(ABND-APPLID) END-EXEC MOVE EIBTASKN TO ABND-TASKNO-KEY MOVE EIBTRNID TO ABND-TRANID PERFORM POPULATE-TIME-DATE MOVE WS-ORIG-DATE TO ABND-DATE STRING WS-TIME-NOW-GRP-HH DELIMITED BY SIZE, ':' DELIMITED BY SIZE, WS-TIME-NOW-GRP-MM DELIMITED BY SIZE, ':' DELIMITED BY SIZE, WS-TIME-NOW-GRP-MM DELIMITED BY SIZE INTO ABND-TIME END-STRING MOVE WS-U-TIME TO ABND-UTIME-KEY MOVE 'HROL' TO ABND-CODE EXEC CICS ASSIGN PROGRAM(ABND-PROGRAM) END-EXEC MOVE ZEROS TO ABND-SQLCODE STRING 'UAD010-TO - Error on SYNCPOINT ROLLBACK ' DELIMITED BY SIZE, 'after failing to read TO account' DELIMITED BY SIZE, ' EIBRESP=' DELIMITED BY SIZE, ABND-RESPCODE DELIMITED BY SIZE, ' RESP2=' DELIMITED BY SIZE, ABND-RESP2CODE DELIMITED BY SIZE INTO ABND-FREEFORM END-STRING EXEC CICS LINK PROGRAM(WS-ABEND-PGM) COMMAREA(ABNDINFO-REC) END-EXEC DISPLAY 'XFRFUN error syncpoint rollback after ' 'failing to read TO account ' ',RESP=' WS-CICS-RESP ',RESP2=' WS-CICS-RESP2 EXEC CICS ABEND ABCODE('HROL') NODUMP CANCEL END-EXEC END-IF GO TO UADT999 ELSE | G56: Falha | H56: falha | I56: comentário curto; contém GO TO (desvio incondicional) | K56: infraestrutura (excluída) | L56: Validado | M56: Coleta de informações complementares de ABEND (PERFORM POPULATE-TIME-DATE, LINK ao tratador de ABEND, ABEND); tratamento técnico sem semântica bancária. Contém GO TO UADT999 (linha 1181); o ELSE da linha 1183 é o cabeçalho do comentário seguinte. | N56: 0
A57: XFRFUN-046 | B57: XFRFUN | C57: 1185-1186 | D57: 1188-1211 | E57: If the failure isn't down to the row NOT being found (it failed for some other reason) | F57: MOVE '3' TO COMM-FAIL-CODE MOVE SQLCODE TO SQLCODE-DISPLAY DISPLAY 'UPDATE UNABLE TO READ TO ACC' HV-ACCOUNT-SORTCODE HV-ACCOUNT-ACC-NO ' ABENDING TO AVOID DATA INCONSISTENCY. SQLCODE=' SQLCODE-DISPLAY ' SQLERRD(3) IS ' SQLERRD(3) IF SQLCODE = -911 IF SQLERRD(3) = 13172872 DISPLAY 'DEADLOCK DETECTED!' ADD 1 TO DB2-DEADLOCK-RETRY IF DB2-DEADLOCK-RETRY < 6 EXEC CICS SYNCPOINT ROLLBACK RESP(WS-CICS-RESP) RESP2(WS-CICS-RESP2) END-EXEC IF WS-CICS-RESP IS NOT EQUAL TO DFHRESP(NORMAL) | G57: Decisão e falha | H57: IF, falha | J57: Se a leitura da conta de destino falhar por motivo diferente de conta não encontrada, a operação é sinalizada como malsucedida com o código de falha '3'. | K57: a discutir | L57: A validar | M57: [Rascunho] Falha técnica de DB2. O restante do trecho (tratamento de deadlock -911 com nova tentativa, rollback e ABEND) é infraestrutura. Trecho com 24 linhas: conferir o final no fonte. | N57: 4
A58: XFRFUN-047 | B58: XFRFUN | C58: 1214-1217 | D58: 1219-1221 | E58: Preserve the RESP and RESP2, then set up the standard ABEND info before getting the applid, date/time etc. and link to the Abend Handler program. | F58: INITIALIZE ABNDINFO-REC MOVE EIBRESP TO ABND-RESPCODE MOVE EIBRESP2 TO ABND-RESP2CODE | G58: Falha | H58: falha | K58: infraestrutura (excluída) | L58: Validado | M58: Montagem padrão das informações de ABEND (INITIALIZE ABNDINFO-REC; MOVE EIBRESP/EIBRESP2); tratamento técnico sem semântica bancária. | N58: 0
A59: XFRFUN-048 | B59: XFRFUN | C59: 1223 | D59: 1225-1290 | E59: Get supplemental information | F59: EXEC CICS ASSIGN APPLID(ABND-APPLID) END-EXEC MOVE EIBTASKN TO ABND-TASKNO-KEY MOVE EIBTRNID TO ABND-TRANID PERFORM POPULATE-TIME-DATE MOVE WS-ORIG-DATE TO ABND-DATE STRING WS-TIME-NOW-GRP-HH DELIMITED BY SIZE, ':' DELIMITED BY SIZE, WS-TIME-NOW-GRP-MM DELIMITED BY SIZE, ':' DELIMITED BY SIZE, WS-TIME-NOW-GRP-MM DELIMITED BY SIZE INTO ABND-TIME END-STRING MOVE WS-U-TIME TO ABND-UTIME-KEY MOVE 'HROL' TO ABND-CODE EXEC CICS ASSIGN PROGRAM(ABND-PROGRAM) END-EXEC MOVE ZEROS TO ABND-SQLCODE STRING 'UAD010-TO(2) - Error on SYNCPOINT' DELIMITED BY SIZE, ' ROLLBACK after updating TO account' DELIMITED BY SIZE, ' EIBRESP=' DELIMITED BY SIZE, ABND-RESPCODE DELIMITED BY SIZE, ' RESP2=' DELIMITED BY SIZE, ABND-RESP2CODE DELIMITED BY SIZE INTO ABND-FREEFORM END-STRING EXEC CICS LINK PROGRAM(WS-ABEND-PGM) COMMAREA(ABNDINFO-REC) END-EXEC DISPLAY 'XFRFUN error syncpoint rollback' ' after updating TO account ' ',RESP=' WS-CICS-RESP ',RESP2=' WS-CICS-RESP2 EXEC CICS ABEND ABCODE('HROL') NODUMP CANCEL END-EXEC END-IF EXEC CICS DELAY FOR SECONDS(1) END-EXEC GO TO UPDATE-ACCOUNT-DB2 END-IF END-IF IF SQLERRD(3) = 13172894 DISPLAY 'TIMEOUT DETECTED!' END-IF | G59: Decisão e falha | H59: IF, falha | I59: comentário curto; contém GO TO (desvio incondicional) | K59: infraestrutura (excluída) | L59: Validado | M59: Coleta de informações complementares de ABEND (PERFORM POPULATE-TIME-DATE, LINK ao tratador de ABEND, ABEND); tratamento técnico sem semântica bancária. Inclui, após o rollback, ABEND com código 'HROL' se ele falhar, espera de 1 segundo e GO TO UPDATE-ACCOUNT-DB2 (retentativa), além do IF SQLERRD(3) = 13172894 com DISPLAY 'TIMEOUT DETECTED!' (linha 1288): tratamento técnico de deadlock e timeout do DB2. | N59: 1
A60: XFRFUN-049 | B60: XFRFUN | C60: 1293-1296 | D60: 1298-1300 | E60: Preserve the RESP and RESP2, then set up the standard ABEND info before getting the applid, date/time etc. and linking to the Abend Handler program. | F60: INITIALIZE ABNDINFO-REC MOVE EIBRESP TO ABND-RESPCODE MOVE EIBRESP2 TO ABND-RESP2CODE | G60: Falha | H60: falha | K60: infraestrutura (excluída) | L60: Validado | M60: Montagem padrão das informações de ABEND (INITIALIZE ABNDINFO-REC; MOVE EIBRESP/EIBRESP2); tratamento técnico sem semântica bancária. | N60: 0
A61: XFRFUN-050 | B61: XFRFUN | C61: 1302 | D61: 1304-1350 | E61: Get supplemental information | F61: EXEC CICS ASSIGN APPLID(ABND-APPLID) END-EXEC MOVE EIBTASKN TO ABND-TASKNO-KEY MOVE EIBTRNID TO ABND-TRANID PERFORM POPULATE-TIME-DATE MOVE WS-ORIG-DATE TO ABND-DATE STRING WS-TIME-NOW-GRP-HH DELIMITED BY SIZE, ':' DELIMITED BY SIZE, WS-TIME-NOW-GRP-MM DELIMITED BY SIZE, ':' DELIMITED BY SIZE, WS-TIME-NOW-GRP-MM DELIMITED BY SIZE INTO ABND-TIME END-STRING MOVE WS-U-TIME TO ABND-UTIME-KEY MOVE 'RUF2' TO ABND-CODE EXEC CICS ASSIGN PROGRAM(ABND-PROGRAM) END-EXEC MOVE ZEROS TO ABND-SQLCODE IF SQLERRD(3) = 13172894 STRING 'UAD010-TO(3) - timeout detected ' DELIMITED BY SIZE, ' EIBRESP=' DELIMITED BY SIZE, ABND-RESPCODE DELIMITED BY SIZE, 'RESP2=' DELIMITED BY SIZE, ABND-RESP2CODE DELIMITED BY SIZE INTO ABND-FREEFORM END-STRING END-IF EXEC CICS LINK PROGRAM(WS-ABEND-PGM) COMMAREA(ABNDINFO-REC) END-EXEC EXEC CICS ABEND ABCODE('RUF2') END-EXEC END-IF END-IF. | G61: Decisão e falha | H61: IF, falha | I61: comentário curto | K61: infraestrutura (excluída) | L61: Validado | M61: Coleta de informações complementares de ABEND (ASSIGN APPLID, data e hora, LINK ao tratador de ABEND); tratamento técnico sem semântica bancária. Inclui IF sobre SQLERRD(3) para mensagem de timeout. | N61: 1
A62: XFRFUN-052 | B62: XFRFUN | C62: 1382 | D62: 1384-1389 | E62: If the RESP CODE was NOT OK then we need to abend | F62: IF SQLCODE NOT = 0 MOVE SQLCODE TO SQLCODE-DISPLAY DISPLAY 'UNABLE TO UPDATE TO ACCOUNT.' HV-ACCOUNT-SORTCODE HV-ACCOUNT-ACC-NO 'THE SQLCODE=' SQLCODE-DISPLAY ' SQLERRD(3) ' SQLERRD(3) | G62: Decisão e falha | H62: IF, falha | K62: infraestrutura (excluída) | L62: Validado | M62: Falha na atualização da conta de destino (SQLCODE diferente de zero): exibe diagnóstico e leva a ABEND; tratamento técnico de DB2. | N62: 1
A63: XFRFUN-053 | B63: XFRFUN | C63: 1392-1393 | D63: 1395-1409 | E63: Check if SQLCODE indicates that Storm Drain processing is applicable in a workload if activated | F63: PERFORM CHECK-FOR-STORM-DRAIN-DB2 IF SQLCODE = -911 IF SQLERRD(3) = 13172872 DISPLAY 'DEADLOCK DETECTED!' ADD 1 TO DB2-DEADLOCK-RETRY IF DB2-DEADLOCK-RETRY < 6 EXEC CICS SYNCPOINT ROLLBACK RESP(WS-CICS-RESP) RESP2(WS-CICS-RESP2) END-EXEC IF WS-CICS-RESP IS NOT EQUAL TO DFHRESP(NORMAL) | G63: Decisão e falha | H63: IF, falha | K63: infraestrutura (excluída) | L63: Validado | M63: Detecção de deadlock (SQLCODE -911) com nova tentativa limitada (DB2-DEADLOCK-RETRY < 6) e rollback; verificação de storm drain. Política de reexecução técnica; infraestrutura. | N63: 4
A64: XFRFUN-054 | B64: XFRFUN | C64: 1412-1415 | D64: 1417-1419 | E64: Preserve the RESP and RESP2, then set up the standard ABEND info before getting the applid, date/time etc. and linking to the Abend Handler program. | F64: INITIALIZE ABNDINFO-REC MOVE EIBRESP TO ABND-RESPCODE MOVE EIBRESP2 TO ABND-RESP2CODE | G64: Falha | H64: falha | K64: infraestrutura (excluída) | L64: Validado | M64: Montagem padrão das informações de ABEND (INITIALIZE ABNDINFO-REC; MOVE EIBRESP/EIBRESP2); tratamento técnico sem semântica bancária. | N64: 0
A65: XFRFUN-055 | B65: XFRFUN | C65: 1421 | D65: 1423-1490 | E65: Get supplemental information | F65: EXEC CICS ASSIGN APPLID(ABND-APPLID) END-EXEC MOVE EIBTASKN TO ABND-TASKNO-KEY MOVE EIBTRNID TO ABND-TRANID PERFORM POPULATE-TIME-DATE MOVE WS-ORIG-DATE TO ABND-DATE STRING WS-TIME-NOW-GRP-HH DELIMITED BY SIZE, ':' DELIMITED BY SIZE, WS-TIME-NOW-GRP-MM DELIMITED BY SIZE, ':' DELIMITED BY SIZE, WS-TIME-NOW-GRP-MM DELIMITED BY SIZE INTO ABND-TIME END-STRING MOVE WS-U-TIME TO ABND-UTIME-KEY MOVE 'HROL' TO ABND-CODE EXEC CICS ASSIGN PROGRAM(ABND-PROGRAM) END-EXEC MOVE ZEROS TO ABND-SQLCODE STRING 'UAD010-TO(4) - Error on SYNCPOINT ' DELIMITED BY SIZE, 'ROLLBACK after Updating TO account' DELIMITED BY SIZE, ' EIBRESP=' DELIMITED BY SIZE, ABND-RESPCODE DELIMITED BY SIZE, ' RESP2=' DELIMITED BY SIZE, ABND-RESP2CODE DELIMITED BY SIZE INTO ABND-FREEFORM END-STRING EXEC CICS LINK PROGRAM(WS-ABEND-PGM) COMMAREA(ABNDINFO-REC) END-EXEC DISPLAY 'XFRFUN error syncpoint rollback ' ' after updating TO account ' ',RESP=' WS-CICS-RESP ',RESP2=' WS-CICS-RESP2 EXEC CICS ABEND ABCODE('HROL') NODUMP CANCEL END-EXEC END-IF EXEC CICS DELAY FOR SECONDS(1) END-EXEC GO TO UPDATE-ACCOUNT-DB2 END-IF END-IF IF SQLERRD(3) = 13172872 DISPLAY 'TIMEOUT DETECTED!' END-IF END-IF | G65: Decisão e falha | H65: IF, falha | I65: comentário curto; contém GO TO (desvio incondicional) | K65: infraestrutura (excluída) | L65: Validado | M65: Coleta de informações complementares de ABEND (PERFORM POPULATE-TIME-DATE, LINK ao tratador de ABEND, ABEND); tratamento técnico sem semântica bancária. Mesmo padrão da XFRFUN-048: retentativa do UPDATE (GO TO UPDATE-ACCOUNT-DB2, linha 1479) e IF SQLERRD(3) = 13172872 (linha 1485); tratamento técnico de deadlock e timeout do DB2. | N65: 1
A66: XFRFUN-056 | B66: XFRFUN | C66: 1493-1496 | D66: 1498-1500 | E66: Preserve the RESP and RESP2, then set up the standard ABEND info before getting the applid, date/time etc. and linking to the Abend Handler program. | F66: INITIALIZE ABNDINFO-REC MOVE EIBRESP TO ABND-RESPCODE MOVE EIBRESP2 TO ABND-RESP2CODE | G66: Falha | H66: falha | K66: infraestrutura (excluída) | L66: Validado | M66: Montagem padrão das informações de ABEND (INITIALIZE ABNDINFO-REC; MOVE EIBRESP/EIBRESP2); tratamento técnico sem semântica bancária. | N66: 0
A67: XFRFUN-057 | B67: XFRFUN | C67: 1502 | D67: 1504-1549 | E67: Get supplemental information | F67: EXEC CICS ASSIGN APPLID(ABND-APPLID) END-EXEC MOVE EIBTASKN TO ABND-TASKNO-KEY MOVE EIBTRNID TO ABND-TRANID PERFORM POPULATE-TIME-DATE MOVE WS-ORIG-DATE TO ABND-DATE STRING WS-TIME-NOW-GRP-HH DELIMITED BY SIZE, ':' DELIMITED BY SIZE, WS-TIME-NOW-GRP-MM DELIMITED BY SIZE, ':' DELIMITED BY SIZE, WS-TIME-NOW-GRP-MM DELIMITED BY SIZE INTO ABND-TIME END-STRING MOVE WS-U-TIME TO ABND-UTIME-KEY MOVE 'RUF2' TO ABND-CODE EXEC CICS ASSIGN PROGRAM(ABND-PROGRAM) END-EXEC MOVE ZEROS TO ABND-SQLCODE IF SQLERRD(3) = 13172872 STRING 'UAD010-TO(5) - timeout detected ' DELIMITED BY SIZE, ' EIBRESP=' DELIMITED BY SIZE, ABND-RESPCODE DELIMITED BY SIZE, ' RESP2=' DELIMITED BY SIZE, ABND-RESP2CODE DELIMITED BY SIZE INTO ABND-FREEFORM END-STRING END-IF EXEC CICS LINK PROGRAM(WS-ABEND-PGM) COMMAREA(ABNDINFO-REC) END-EXEC EXEC CICS ABEND ABCODE ('RUF3') END-EXEC END-IF. | G67: Decisão e falha | H67: IF, falha | I67: comentário curto | K67: infraestrutura (excluída) | L67: Validado | M67: Coleta de informações complementares de ABEND (ASSIGN APPLID, data e hora, LINK ao tratador de ABEND); tratamento técnico sem semântica bancária. Inclui IF sobre SQLERRD(3) para mensagem de timeout. | N67: 1
A68: XFRFUN-061 | B68: XFRFUN | C68: 1644 | D68: 1646-1648 | E68: Check the SQLCODE | F68: IF SQLCODE NOT = 0 MOVE SQLCODE TO WS-SQLCODE-DISP | G68: Decisão e falha | H68: IF, falha | I68: comentário curto | K68: infraestrutura (excluída) | L68: Validado | M68: Falha na gravação em PROCTRAN (SQLCODE diferente de zero): converte SQLCODE para exibição; segue para storm drain e ABEND 'WPCD' (XFRFUN-064). Tratamento técnico. | N68: 1
A69: XFRFUN-062 | B69: XFRFUN | C69: 1650-1653 | D69: 1655-1657 | E69: Preserve the RESP and RESP2, then set up the standard ABEND info before getting the applid, date/time etc. and linking to the Abend Handler program. | F69: INITIALIZE ABNDINFO-REC MOVE EIBRESP TO ABND-RESPCODE MOVE EIBRESP2 TO ABND-RESP2CODE | G69: Falha | H69: falha | K69: infraestrutura (excluída) | L69: Validado | M69: Montagem padrão das informações de ABEND (INITIALIZE ABNDINFO-REC; MOVE EIBRESP/EIBRESP2); tratamento técnico sem semântica bancária. | N69: 0
A70: XFRFUN-063 | B70: XFRFUN | C70: 1659 | D70: 1661-1708 | E70: Get supplemental information | F70: EXEC CICS ASSIGN APPLID(ABND-APPLID) END-EXEC MOVE EIBTASKN TO ABND-TASKNO-KEY MOVE EIBTRNID TO ABND-TRANID PERFORM POPULATE-TIME-DATE MOVE WS-ORIG-DATE TO ABND-DATE STRING WS-TIME-NOW-GRP-HH DELIMITED BY SIZE, ':' DELIMITED BY SIZE, WS-TIME-NOW-GRP-MM DELIMITED BY SIZE, ':' DELIMITED BY SIZE, WS-TIME-NOW-GRP-MM DELIMITED BY SIZE INTO ABND-TIME END-STRING MOVE WS-U-TIME TO ABND-UTIME-KEY MOVE 'WPCD' TO ABND-CODE EXEC CICS ASSIGN PROGRAM(ABND-PROGRAM) END-EXEC MOVE WS-SQLCODE-DISP TO ABND-SQLCODE STRING 'WTPD010 - Unable to WRITE to PROCTRAN DB2 ' DELIMITED BY SIZE, 'datastore. Data=' DELIMITED BY SIZE, HOST-PROCTRAN-ROW DELIMITED BY SIZE, '.Data inconsistency, data UPDATED on ACCOUNT file' DELIMITED BY SIZE, ' EIBRESP=' DELIMITED BY SIZE, ABND-RESPCODE DELIMITED BY SIZE, ' RESP2=' DELIMITED BY SIZE, ABND-RESP2CODE DELIMITED BY SIZE INTO ABND-FREEFORM END-STRING EXEC CICS LINK PROGRAM(WS-ABEND-PGM) COMMAREA(ABNDINFO-REC) END-EXEC DISPLAY 'UNABLE TO WRITE TO PROCTRAN DB2 DATASTORE' ' SQLCODE=' SQLCODE 'WITH THE FOLLOWING DATA:' HOST-PROCTRAN-ROW DISPLAY 'DATA INCONSISTENCY, DATA UPDATED ON ACCOUNT' | G70: Falha | H70: falha | I70: comentário curto | K70: infraestrutura (excluída) | L70: Validado | M70: Coleta de informações complementares de ABEND (PERFORM POPULATE-TIME-DATE, LINK ao tratador de ABEND, ABEND); tratamento técnico sem semântica bancária. SQLCODE aparece apenas na mensagem de ABEND. | N70: 0
A71: XFRFUN-064 | B71: XFRFUN | C71: 1711-1712 | D71: 1714-1738 | E71: Check if SQLCODE indicates that Storm Drain processing is applicable in a workload if activated | F71: PERFORM CHECK-FOR-STORM-DRAIN-DB2 EXEC CICS ABEND ABCODE('WPCD') END-EXEC END-IF. WTPD999. EXIT. GET-ME-OUT-OF-HERE SECTION. GMOOH010. EXEC CICS RETURN END-EXEC. GOBACK. GMOOH999. EXIT. CHECK-FOR-STORM-DRAIN-DB2 SECTION. CFSDD010. | G71: Falha | H71: falha | K71: infraestrutura (excluída) | L71: Validado | M71: Verificação de storm drain e ABEND 'WPCD' após falha na gravação em PROCTRAN. O trecho atravessa seções (WRITE-TO-PROCTRAN-DB2, GET-ME-OUT-OF-HERE, CHECK-FOR-STORM-DRAIN-DB2): efeito de corte do extrator. Infraestrutura. | N71: 0
A72: XFRFUN-065 | B72: XFRFUN | C72: 1741-1742 | D72: 1744-1770 | E72: Check if the Sqlcode that is returned one that will trigger Storm Drain is active in Workload | F72: EVALUATE SQLCODE WHEN 923 MOVE 'DB2 Connection lost ' TO STORM-DRAIN-CONDITION WHEN OTHER MOVE 'Not Storm Drain ' TO STORM-DRAIN-CONDITION END-EVALUATE. IF STORM-DRAIN-CONDITION NOT EQUAL 'Not Storm Drain ' DISPLAY 'XFRFUN: Check-For-Storm-Drain-DB2: Storm ' 'Drain condition (' STORM-DRAIN-CONDITION ') ' 'has been met (' SQLCODE-DISPLAY ').' ELSE CONTINUE END-IF. CFSDD999. EXIT. ABEND-HANDLING SECTION. AH010. | G72: Decisão e falha | H72: IF, EVALUATE, WHEN, falha | K72: infraestrutura (excluída) | L72: Validado | M72: Verificação de condição de storm drain do DB2 (EVALUATE SQLCODE, WHEN 923); infraestrutura. | N72: 4
A73: XFRFUN-067 | B73: XFRFUN | C73: 1779-1784 | D73: 1786 | E73: Evaluate the Abend code that is returned - For DB2 AD2Z ... provide some diagnostics - For VSAM RLS abends: AFCR, AFCS and AFCT record the Abend as happening but do not abend ... leave this to CPSM WLM "Storm drain" (Abend probability) to handle If not a "storm drain" ... take the abend afterwards | F73: EVALUATE MY-ABEND-CODE | G73: Decisão | H73: EVALUATE | K73: infraestrutura (excluída) | L73: Validado | M73: Avaliação do código de ABEND (EVALUATE MY-ABEND-CODE) para diagnóstico e storm drain de DB2 e VSAM; infraestrutura. | N73: 1
A74: XFRFUN-068 | B74: XFRFUN | C74: 1789 | D74: 1791-1821 | E74: DB2 AD2Z abend | F74: WHEN 'AD2Z' MOVE SQLCODE TO SQLCODE-DISPLAY DISPLAY 'DB2 DEADLOCK DETECTED IN XFRFUN, SQLCODE=' SQLCODE-DISPLAY DISPLAY 'DB2 DEADLOCK FOR ACCOUNT ' HV-ACCOUNT-ACC-NO DISPLAY 'SQLSTATE=' SQLSTATE ',SQLERRMC=' SQLERRMC(1:SQLERRML) ',SQLERRD(1)=' SQLERRD(1) ',SQLERRD(2)=' SQLERRD(2) ',SQLERRD(3)=' SQLERRD(3) ',SQLERRD(4)=' SQLERRD(4) ',SQLERRD(5)=' SQLERRD(5) ',SQLERRD(6)=' SQLERRD(6) WHEN 'AFCR' WHEN 'AFCS' WHEN 'AFCT' MOVE 'Y' TO WS-STORM-DRAIN DISPLAY 'XFRFUN: Check-For-Storm-Drain-VSAM: Storm ' 'Drain condition (Abend ' MY-ABEND-CODE ') ' 'has been met.' EXEC CICS SYNCPOINT ROLLBACK RESP(WS-CICS-RESP) RESP2(WS-CICS-RESP2) END-EXEC IF WS-CICS-RESP NOT = DFHRESP(NORMAL) | G74: Decisão e falha | H74: IF, WHEN, falha | I74: comentário curto | K74: infraestrutura (excluída) | L74: Validado | M74: Tratamento dos ABEND AD2Z (deadlock DB2) e AFCR/AFCS/AFCT (VSAM RLS, storm drain) com rollback; infraestrutura. | N74: 5
A75: XFRFUN-069 | B75: XFRFUN | C75: 1823-1826 | D75: 1828-1830 | E75: Preserve the RESP and RESP2, then set up the standard ABEND info before getting the applid, date/time etc. and linking to the Abend Handler program. | F75: INITIALIZE ABNDINFO-REC MOVE EIBRESP TO ABND-RESPCODE MOVE EIBRESP2 TO ABND-RESP2CODE | G75: Falha | H75: falha | K75: infraestrutura (excluída) | L75: Validado | M75: Montagem padrão das informações de ABEND (INITIALIZE ABNDINFO-REC; MOVE EIBRESP/EIBRESP2); tratamento técnico sem semântica bancária. | N75: 0
A76: XFRFUN-070 | B76: XFRFUN | C76: 1832 | D76: 1834-1924 | E76: Get supplemental information | F76: EXEC CICS ASSIGN APPLID(ABND-APPLID) END-EXEC MOVE EIBTASKN TO ABND-TASKNO-KEY MOVE EIBTRNID TO ABND-TRANID PERFORM POPULATE-TIME-DATE MOVE WS-ORIG-DATE TO ABND-DATE STRING WS-TIME-NOW-GRP-HH DELIMITED BY SIZE, ':' DELIMITED BY SIZE, WS-TIME-NOW-GRP-MM DELIMITED BY SIZE, ':' DELIMITED BY SIZE, WS-TIME-NOW-GRP-MM DELIMITED BY SIZE INTO ABND-TIME END-STRING MOVE WS-U-TIME TO ABND-UTIME-KEY MOVE 'HROL' TO ABND-CODE EXEC CICS ASSIGN PROGRAM(ABND-PROGRAM) END-EXEC MOVE ZEROS TO ABND-SQLCODE STRING 'AH010 - Unable to perform SYNCPOINT ' DELIMITED BY SIZE, 'ROLLBACK.' DELIMITED BY SIZE, ' Possible integrity issue following VSAM RLS ' DELIMITED BY SIZE, 'abend.' DELIMITED BY SIZE, ' EIBRESP=' DELIMITED BY SIZE, ABND-RESPCODE DELIMITED BY SIZE, ' RESP2=' DELIMITED BY SIZE, ABND-RESP2CODE DELIMITED BY SIZE INTO ABND-FREEFORM END-STRING EXEC CICS LINK PROGRAM(WS-ABEND-PGM) COMMAREA(ABNDINFO-REC) END-EXEC DISPLAY 'XFRFUN: Unable to perform Syncpoint ' 'Rollback. Possible Integrity issue following ' ' VSAM RLS abend RESP CODE=' WS-CICS-RESP ' RESP2 CODE=' WS-CICS-RESP2 EXEC CICS ABEND ABCODE ('HROL') END-EXEC END-IF MOVE 'N' TO COMM-SUCCESS MOVE '2' TO COMM-FAIL-CODE EXEC CICS RETURN END-EXEC END-EVALUATE. IF WS-STORM-DRAIN = 'N' EXEC CICS ABEND ABCODE( MY-ABEND-CODE) | G76: Decisão e falha | H76: IF, falha | I76: comentário curto; trecho truncado (exibidas 50 de 68 linhas) | K76: infraestrutura (excluída) | L76: Validado | M76: Coleta de informações complementares de ABEND (PERFORM POPULATE-TIME-DATE, LINK ao tratador de ABEND, ABEND); tratamento técnico sem semântica bancária. O trecho vai até o fim do programa e termina com IF WS-STORM-DRAIN = 'N' (linha 1897) seguido de ABEND com MY-ABEND-CODE: verificação de storm drain, infraestrutura pelo seu critério. | N76: 1
A77: BNK1CRA-001 | B77: BNK1CRA | C77: 182-183 | D77: 185-189 | E77: Is it the first time through? If so, send the map with erased (empty) data fields. | F77: WHEN EIBCALEN = ZERO MOVE LOW-VALUE TO BNK1CDO MOVE -1 TO ACCNOL SET SEND-ERASE TO TRUE PERFORM SEND-MAP | G77: Decisão | H77: WHEN | J77: Se for a primeira execução da transação (EIBCALEN igual a zero), a tela é enviada com os campos vazios. | K77: a discutir | L77: A validar | M77: [Rascunho] Regra de interface (fluxo de teclas e telas), não de domínio bancário; decidir a categoria com o orientador junto com as demais teclas de função (BNK1CRA-001 a 007 e BNK1TFN-001 a 007). | N77: 1
A78: BNK1CRA-002 | B78: BNK1CRA | C78: 192 | D78: 194-195 | E78: If a PA key is pressed, just carry on | F78: WHEN EIBAID = DFHPA1 OR DFHPA2 OR DFHPA3 CONTINUE | G78: Decisão | H78: WHEN | J78: Se uma tecla PA for pressionada (PA1, PA2 ou PA3), nenhuma ação é executada. | K78: a discutir | L78: A validar | M78: [Rascunho] Regra de interface (fluxo de teclas e telas), não de domínio bancário; decidir a categoria com o orientador junto com as demais teclas de função (BNK1CRA-001 a 007 e BNK1TFN-001 a 007). | N78: 1
A79: BNK1CRA-003 | B79: BNK1CRA | C79: 198 | D79: 200-206 | E79: When Pf3 is pressed, return to the main menu | F79: WHEN EIBAID = DFHPF3 EXEC CICS RETURN TRANSID('OMEN') IMMEDIATE RESP(WS-CICS-RESP) RESP2(WS-CICS-RESP2) END-EXEC | G79: Decisão | H79: WHEN | J79: Se a tecla PF3 for pressionada, o usuário retorna ao menu principal (transação OMEN). | K79: a discutir | L79: A validar | M79: [Rascunho] Regra de interface (fluxo de teclas e telas), não de domínio bancário; decidir a categoria com o orientador junto com as demais teclas de função (BNK1CRA-001 a 007 e BNK1TFN-001 a 007). | N79: 1
A80: BNK1CRA-004 | B80: BNK1CRA | C80: 209-210 | D80: 212-217 | E80: If the aid or Pf12 is pressed, then send a termination message. | F80: WHEN EIBAID = DFHAID OR DFHPF12 PERFORM SEND-TERMINATION-MSG EXEC CICS RETURN END-EXEC | G80: Decisão | H80: WHEN | J80: Se a tecla PF12 for pressionada, é enviada a mensagem de encerramento e a transação termina. | K80: a discutir | L80: A validar | M80: [Rascunho] Regra de interface (fluxo de teclas e telas), não de domínio bancário; decidir a categoria com o orientador junto com as demais teclas de função (BNK1CRA-001 a 007 e BNK1TFN-001 a 007). O código testa DFHAID ou DFHPF12; o comentário fala em 'the aid' ou PF12. Conferir o sentido de DFHAID no fonte (linhas 209-217). | N80: 1
A81: BNK1CRA-005 | B81: BNK1CRA | C81: 220 | D81: 222-229 | E81: When CLEAR is pressed | F81: WHEN EIBAID = DFHCLEAR EXEC CICS SEND CONTROL ERASE FREEKB END-EXEC EXEC CICS RETURN END-EXEC | G81: Decisão | H81: WHEN | J81: Se a tecla CLEAR for pressionada, a tela é limpa e a transação termina. | K81: a discutir | L81: A validar | M81: [Rascunho] Regra de interface (fluxo de teclas e telas), não de domínio bancário; decidir a categoria com o orientador junto com as demais teclas de função (BNK1CRA-001 a 007 e BNK1TFN-001 a 007). | N81: 1
A82: BNK1CRA-006 | B82: BNK1CRA | C82: 232 | D82: 234-235 | E82: When enter is pressed then process the content | F82: WHEN EIBAID = DFHENTER PERFORM PROCESS-MAP | G82: Decisão | H82: WHEN | J82: Se a tecla ENTER for pressionada, os dados informados são processados (PROCESS-MAP). | K82: a discutir | L82: A validar | M82: [Rascunho] Regra de interface (fluxo de teclas e telas), não de domínio bancário; decidir a categoria com o orientador junto com as demais teclas de função (BNK1CRA-001 a 007 e BNK1TFN-001 a 007). É o gatilho do processamento de negócio; a regra em si está na BNK1CRA-013. | N82: 1
A83: BNK1CRA-007 | B83: BNK1CRA | C83: 238 | D83: 240-247 | E83: When anything else happens, send the invalid key message | F83: WHEN OTHER MOVE LOW-VALUES TO BNK1CDO MOVE 'Invalid key pressed.' TO MESSAGEO MOVE 8 TO ACCNOL SET SEND-DATAONLY-ALARM TO TRUE PERFORM SEND-MAP END-EVALUATE. | G83: Decisão | H83: WHEN | J83: Se qualquer outra tecla for pressionada, é exibida a mensagem 'Invalid key pressed.' com alarme sonoro. | K83: a discutir | L83: A validar | M83: [Rascunho] Regra de interface (fluxo de teclas e telas), não de domínio bancário; decidir a categoria com o orientador junto com as demais teclas de função (BNK1CRA-001 a 007 e BNK1TFN-001 a 007). O trecho termina em END-EVALUATE. | N83: 1
A84: BNK1CRA-008 | B84: BNK1CRA | C84: 250-253 | D84: 255-271 | E84: Provided that we have been around this way before (i.e. it is NOT the first time through, put the data returned from the sub program into the area that we use as the COMMAREA on the RETURN. | F84: IF EIBCALEN NOT = ZERO MOVE COMM-ACCNO TO WS-COMM-ACCNO MOVE COMM-SIGN TO WS-COMM-SIGN MOVE COMM-AMT TO WS-COMM-AMT END-IF. EXEC CICS RETURN TRANSID('OCRA') COMMAREA(WS-COMM-AREA) LENGTH(21) RESP(WS-CICS-RESP) RESP2(WS-CICS-RESP2) END-EXEC. IF WS-CICS-RESP NOT = DFHRESP(NORMAL) | G84: Decisão e falha | H84: IF, falha | K84: infraestrutura (excluída) | L84: Validado | M84: Retorno pseudo-conversacional (RETURN TRANSID com COMMAREA) e verificação do RESP; controle de transação. A cópia dos dados para a COMMAREA só ocorre quando EIBCALEN é diferente de zero. | N84: 2
A85: BNK1CRA-009 | B85: BNK1CRA | C85: 273-276 | D85: 278-280 | E85: Preserve the RESP and RESP2, then set up the standard ABEND info before getting the applid, date/time etc. and linking to the Abend Handler program. | F85: INITIALIZE ABNDINFO-REC MOVE EIBRESP TO ABND-RESPCODE MOVE EIBRESP2 TO ABND-RESP2CODE | G85: Falha | H85: falha | K85: infraestrutura (excluída) | L85: Validado | M85: Montagem padrão das informações de ABEND (INITIALIZE ABNDINFO-REC; MOVE EIBRESP/EIBRESP2); tratamento técnico sem semântica bancária. | N85: 0
A86: BNK1CRA-013 | B86: BNK1CRA | C86: 347-348 | D86: 350-354 | E86: If the data passes validation go on to apply the debit or credit. | F86: IF VALID-DATA PERFORM UPD-CRED-DATA END-IF. SET SEND-DATAONLY-ALARM TO TRUE. | G86: Decisão | H86: IF | J86: Se os dados informados passarem na validação (VALID-DATA), o débito ou crédito é aplicado à conta (UPD-CRED-DATA). | K86: regra de negócio | L86: A validar | M86: [Rascunho] O SET SEND-DATAONLY-ALARM executado em seguida é procedural e fica fora da regra. | N86: 1
A87: BNK1CRA-015 | B87: BNK1CRA | C87: 368 | D87: 370-378 | E87: Retrieve the data | F87: EXEC CICS RECEIVE MAP('BNK1CD') MAPSET('BNK1CDM') INTO(BNK1CDI) RESP(WS-CICS-RESP) RESP2(WS-CICS-RESP2) END-EXEC. IF WS-CICS-RESP NOT = DFHRESP(NORMAL) | G87: Decisão e falha | H87: IF, falha | I87: comentário curto | K87: infraestrutura (excluída) | L87: Validado | M87: Recebimento dos dados da tela (RECEIVE MAP) e verificação do RESP; infraestrutura de interface. | N87: 1
A88: BNK1CRA-016 | B88: BNK1CRA | C88: 380-383 | D88: 385-387 | E88: Preserve the RESP and RESP2, then set up the standard ABEND info before getting the applid, date/time etc. and linking to the Abend Handler program. | F88: INITIALIZE ABNDINFO-REC MOVE EIBRESP TO ABND-RESPCODE MOVE EIBRESP2 TO ABND-RESP2CODE | G88: Falha | H88: falha | K88: infraestrutura (excluída) | L88: Validado | M88: Montagem padrão das informações de ABEND (INITIALIZE ABNDINFO-REC; MOVE EIBRESP/EIBRESP2); tratamento técnico sem semântica bancária. | N88: 0
A89: BNK1CRA-018 | B89: BNK1CRA | C89: 444 | D89: 446-469 | E89: Perform validation on the incoming fields | F89: EXEC CICS BIF DEEDIT FIELD(ACCNOI) END-EXEC. IF ACCNOI NOT NUMERIC MOVE 'Please enter an account number. ' TO MESSAGEO MOVE 'N' TO VALID-DATA-SW GO TO ED999 END-IF. IF ACCNOI = ZERO MOVE 'Please enter a non zero account number. ' TO MESSAGEO MOVE 'N' TO VALID-DATA-SW GO TO ED999 END-IF. IF SIGNI NOT = '+' AND SIGNI NOT = '-' AND SIGNL = 1 MOVE 'Please enter + or - preceding the amount ' TO MESSAGEO MOVE 'N' TO VALID-DATA-SW GO TO ED999 END-IF. | G89: Decisão | H89: IF | I89: contém GO TO (desvio incondicional) | J89: 1. Se o número da conta informado não for numérico, a entrada é considerada inválida e é exibida a mensagem 'Please enter an account number.' 2. Se o número da conta informado for zero, a entrada é considerada inválida e é exibida a mensagem 'Please enter a non zero account number.' 3. Se um sinal for informado e não for '+' nem '-', a entrada é considerada inválida e é exibida a mensagem 'Please enter + or - preceding the amount.' | K89: regra de negócio | L89: A validar | M89: [Rascunho] Linha vale por três regras. A condição do sinal é SIGNI diferente de '+' e de '-' com SIGNL = 1 (campo de sinal preenchido): conferir no fonte (linhas 440-469). | N89: 3
A90: BNK1CRA-021 | B90: BNK1CRA | C90: 492 | D90: 494-498 | E90: Provide the correct Amount | F90: IF SIGNI = '-' COMPUTE WS-AMOUNT-AS-FLOAT = WS-AMOUNT-AS-FLOAT * -1 END-IF. MOVE WS-AMOUNT-AS-FLOAT TO SUBPGM-AMT. | G90: Decisão | H90: IF | J90: Se o sinal informado for '-', o valor da operação é convertido para negativo (débito). | K90: regra de negócio | L90: A validar | M90: [Rascunho] Sem ELSE: sinal '+' mantém o valor positivo (crédito). O valor convertido segue para o DBCRFUN (SUBPGM-AMT). | N90: 1
A91: BNK1CRA-022 | B91: BNK1CRA | C91: 501 | D91: 503-519 | E91: Get the ORIGIN data | F91: EXEC CICS INQUIRE ASSOCIATION(EIBTASKN) ODAPPLID(SUBPGM-APPLID) ODUSERID(SUBPGM-USERID) ODFACILNAME(SUBPGM-FACILITY-NAME) ODNETWORKID(SUBPGM-NETWRK-ID) ODFACILTYPE(SUBPGM-FACILTYPE) END-EXEC. EXEC CICS LINK PROGRAM('DBCRFUN') COMMAREA(SUBPGM-PARMS) RESP(WS-CICS-RESP) RESP2(WS-CICS-RESP2) SYNCONRETURN END-EXEC. IF WS-CICS-RESP NOT = DFHRESP(NORMAL) | G91: Decisão e falha | H91: IF, falha | K91: infraestrutura (excluída) | L91: Validado | M91: Obtenção dos dados de origem (INQUIRE ASSOCIATION) e LINK ao DBCRFUN com verificação do RESP. O COMM-FACILTYPE obtido aqui alimenta a regra de pagamento (496) do DBCRFUN-008. | N91: 1
A92: BNK1CRA-023 | B92: BNK1CRA | C92: 521-524 | D92: 526-528 | E92: Preserve the RESP and RESP2, then set up the standard ABEND info before getting the applid, date/time etc. and linking to the Abend Handler program. | F92: INITIALIZE ABNDINFO-REC MOVE EIBRESP TO ABND-RESPCODE MOVE EIBRESP2 TO ABND-RESP2CODE | G92: Falha | H92: falha | K92: infraestrutura (excluída) | L92: Validado | M92: Montagem padrão das informações de ABEND (INITIALIZE ABNDINFO-REC; MOVE EIBRESP/EIBRESP2); tratamento técnico sem semântica bancária. | N92: 0
A93: BNK1CRA-025 | B93: BNK1CRA | C93: 579 | D93: 581-626 | E93: Check to see if the debit or credit was successful | F93: IF SUBPGM-SUCCESS = 'N' MOVE 'N' TO VALID-DATA-SW EVALUATE SUBPGM-FAIL-CODE WHEN '1' MOVE SPACES TO MESSAGEO STRING 'Sorry but the ACCOUNT no was not found' ' for SORTCODE ' SUBPGM-SORTC ' . Amount not applied. ' DELIMITED BY SIZE INTO MESSAGEO GO TO UCD999 WHEN '2' MOVE SPACES TO MESSAGEO STRING 'Sorry but the AMOUNT could not be applied' ' due to an unexpected error.' DELIMITED BY SIZE INTO MESSAGEO GO TO UCD999 WHEN '3' MOVE SPACES TO MESSAGEO STRING 'Sorry insufficient funds available to pro' 'cess the request. ' DELIMITED BY SIZE INTO MESSAGEO GO TO UCD999 WHEN OTHER MOVE SPACES TO MESSAGEO STRING 'Sorry but the AMOUNT could not be applied' ' due to an unexpected error. ' SUBPGM-FAIL-CODE DELIMITED BY SIZE INTO MESSAGEO GO TO UCD999 END-EVALUATE ELSE MOVE SPACES TO MESSAGEO MOVE 'Amount successfully applied to the account.' TO MESSAGEO END-IF. | G93: Decisão | H93: IF, EVALUATE, WHEN | I93: contém GO TO (desvio incondicional) | J93: 1. Se o débito ou crédito não for bem-sucedido e o código de falha for '1', é exibida a mensagem de conta não encontrada e valor não aplicado. 2. Se o débito ou crédito não for bem-sucedido e o código de falha for '2', é exibida a mensagem de erro inesperado. 3. Se o débito ou crédito não for bem-sucedido e o código de falha for '3', é exibida a mensagem de saldo insuficiente. 4. Se o débito ou crédito não for bem-sucedido e o código de falha for outro, é exibida a mensagem de erro inesperado acompanhada do código. 5. Se o débito ou crédito for bem-sucedido, é exibida a mensagem 'Amount successfully applied to the account.' | K93: regra de negócio | L93: A validar | M93: [Rascunho] Não há WHEN '4': a negação de pagamento em conta MORTGAGE/LOAN (DBCRFUN, código '4') cai em WHEN OTHER e aparece ao usuário como erro inesperado com o código. A regra 5 vem do ELSE, que agora aparece no fim do trecho. Linha vale por cinco regras; avaliar se divide em entradas. | N93: 6
A94: BNK1CRA-027 | B94: BNK1CRA | C94: 646 | D94: 648-657 | E94: If the map needs to have its data erased | F94: IF SEND-ERASE EXEC CICS SEND MAP('BNK1CD') MAPSET('BNK1CDM') FROM(BNK1CDO) ERASE RESP(WS-CICS-RESP) RESP2(WS-CICS-RESP2) END-EXEC IF WS-CICS-RESP NOT = DFHRESP(NORMAL) | G94: Decisão e falha | H94: IF, falha | K94: infraestrutura (excluída) | L94: Validado | M94: Envio da tela com apagamento (SEND MAP ... ERASE) e verificação do RESP; infraestrutura de interface. | N94: 2
A95: BNK1CRA-028 | B95: BNK1CRA | C95: 659-662 | D95: 664-666 | E95: Preserve the RESP and RESP2, then set up the standard ABEND info before getting the applid, date/time etc. and linking to the Abend Handler program. | F95: INITIALIZE ABNDINFO-REC MOVE EIBRESP TO ABND-RESPCODE MOVE EIBRESP2 TO ABND-RESP2CODE | G95: Falha | H95: falha | K95: infraestrutura (excluída) | L95: Validado | M95: Montagem padrão das informações de ABEND (INITIALIZE ABNDINFO-REC; MOVE EIBRESP/EIBRESP2); tratamento técnico sem semântica bancária. | N95: 0
A96: BNK1CRA-030 | B96: BNK1CRA | C96: 720 | D96: 722-731 | E96: If the map just needs a resend of only the data | F96: IF SEND-DATAONLY EXEC CICS SEND MAP('BNK1CD') MAPSET('BNK1CDM') FROM(BNK1CDO) DATAONLY RESP(WS-CICS-RESP) RESP2(WS-CICS-RESP2) END-EXEC IF WS-CICS-RESP NOT = DFHRESP(NORMAL) | G96: Decisão e falha | H96: IF, falha | K96: infraestrutura (excluída) | L96: Validado | M96: Reenvio apenas dos dados da tela (SEND MAP ... DATAONLY) e verificação do RESP; infraestrutura de interface. | N96: 2
A97: BNK1CRA-031 | B97: BNK1CRA | C97: 733-736 | D97: 738-740 | E97: Preserve the RESP and RESP2, then set up the standard ABEND info before getting the applid, date/time etc. and linking to the Abend Handler program. | F97: INITIALIZE ABNDINFO-REC MOVE EIBRESP TO ABND-RESPCODE MOVE EIBRESP2 TO ABND-RESP2CODE | G97: Falha | H97: falha | K97: infraestrutura (excluída) | L97: Validado | M97: Montagem padrão das informações de ABEND (INITIALIZE ABNDINFO-REC; MOVE EIBRESP/EIBRESP2); tratamento técnico sem semântica bancária. | N97: 0
A98: BNK1CRA-033 | B98: BNK1CRA | C98: 794 | D98: 796-806 | E98: If we have elected to send the map and a beep | F98: IF SEND-DATAONLY-ALARM EXEC CICS SEND MAP('BNK1CD') MAPSET('BNK1CDM') FROM(BNK1CDO) DATAONLY ALARM RESP(WS-CICS-RESP) RESP2(WS-CICS-RESP2) END-EXEC IF WS-CICS-RESP NOT = DFHRESP(NORMAL) | G98: Decisão e falha | H98: IF, falha | K98: infraestrutura (excluída) | L98: Validado | M98: Envio da tela com alarme sonoro (SEND MAP ... ALARM) e verificação do RESP; infraestrutura de interface. | N98: 2
A99: BNK1CRA-034 | B99: BNK1CRA | C99: 808-811 | D99: 813-815 | E99: Preserve the RESP and RESP2, then set up the standard ABEND info before getting the applid, date/time etc. and linking to the Abend Handler program. | F99: INITIALIZE ABNDINFO-REC MOVE EIBRESP TO ABND-RESPCODE MOVE EIBRESP2 TO ABND-RESP2CODE | G99: Falha | H99: falha | K99: infraestrutura (excluída) | L99: Validado | M99: Montagem padrão das informações de ABEND (INITIALIZE ABNDINFO-REC; MOVE EIBRESP/EIBRESP2); tratamento técnico sem semântica bancária. | N99: 0
A100: BNK1CRA-036 | B100: BNK1CRA | C100: 874 | D100: 876-884 | E100: Send the termination message | F100: EXEC CICS SEND TEXT FROM(END-OF-SESSION-MESSAGE) ERASE FREEKB RESP(WS-CICS-RESP) RESP2(WS-CICS-RESP2) END-EXEC. IF WS-CICS-RESP NOT = DFHRESP(NORMAL) | G100: Decisão e falha | H100: IF, falha | K100: infraestrutura (excluída) | L100: Validado | M100: Envio da mensagem de encerramento (SEND TEXT) e verificação do RESP; infraestrutura de interface. | N100: 1
...

Sheet Descartados
A1: ID | B1: Programa | C1: Linhas do comentário | D1: Linhas do código | E1: Comentário | F1: Trecho de código | G1: Motivo do descarte | H1: Alertas | I1: Reavaliação
A2: DBCRFUN-002 | B2: DBCRFUN | C2: 215-221 | D2: 223 | E2: Determine what kind of ACCOUNT datastore we should be accessing Go and update the ACCOUNT record | F2: PERFORM UPDATE-ACCOUNT-DB2. | G2: Procedural (sem decisão nem tratamento de falha) | H2: comentário delega lógica (PERFORM); comentário menciona condição: reavaliar | I2: Manter descartado
A3: DBCRFUN-003 | B3: DBCRFUN | C3: 225-226 | D3: 229-240 | E3: The COMMAREA values have now been set so all we need to do is finish | F3: PERFORM GET-ME-OUT-OF-HERE. A999. EXIT. UPDATE-ACCOUNT-DB2 SECTION. UAD010. MOVE COMM-ACCNO TO DESIRED-ACC-NO. MOVE DESIRED-SORT-CODE TO HV-ACCOUNT-SORTCODE. MOVE DESIRED-ACC-NO TO HV-ACCOUNT-ACC-NO. | G3: Procedural (sem decisão nem tratamento de falha) | H3: comentário delega lógica (PERFORM) | I3: Manter descartado
A4: DBCRFUN-004 | B4: DBCRFUN | C4: 243 | D4: 245-273 | E4: Retrieve the account information | F4: EXEC SQL SELECT ACCOUNT_EYECATCHER, ACCOUNT_CUSTOMER_NUMBER, ACCOUNT_SORTCODE, ACCOUNT_NUMBER, ACCOUNT_TYPE, ACCOUNT_INTEREST_RATE, ACCOUNT_OPENED, ACCOUNT_OVERDRAFT_LIMIT, ACCOUNT_LAST_STATEMENT, ACCOUNT_NEXT_STATEMENT, ACCOUNT_AVAILABLE_BALANCE, ACCOUNT_ACTUAL_BALANCE INTO :HV-ACCOUNT-EYECATCHER, :HV-ACCOUNT-CUST-NO, :HV-ACCOUNT-SORTCODE, :HV-ACCOUNT-ACC-NO, :HV-ACCOUNT-ACC-TYPE, :HV-ACCOUNT-INT-RATE, :HV-ACCOUNT-OPENED, :HV-ACCOUNT-OVERDRAFT-LIM, :HV-ACCOUNT-LAST-STMT, :HV-ACCOUNT-NEXT-STMT, :HV-ACCOUNT-AVAIL-BAL, :HV-ACCOUNT-ACTUAL-BAL FROM ACCOUNT WHERE (ACCOUNT_SORTCODE = :HV-ACCOUNT-SORTCODE AND ACCOUNT_NUMBER = :HV-ACCOUNT-ACC-NO) END-EXEC. | G4: Procedural (sem decisão nem tratamento de falha) | I4: Manter descartado
A5: DBCRFUN-006 | B5: DBCRFUN | C5: 290-291 | D5: 293-297 | E5: Check if SQLCODE indicates that Storm Drain processing is applicable in a workload if activated | F5: PERFORM CHECK-FOR-STORM-DRAIN-DB2 GO TO UAD999 END-IF. | G5: Procedural (sem decisão nem tratamento de falha) | H5: comentário delega lógica (PERFORM); contém GO TO (desvio incondicional); comentário menciona condição: reavaliar | I5: Manter descartado
A6: DBCRFUN-010 | B6: DBCRFUN | C6: 380-382 | D6: 384-387 | E6: If the SQLCODE from the SELECT is OK then update the record and update the details on the PROCTRAN (Processed transaction) datastore. | F6: COMPUTE HV-ACCOUNT-AVAIL-BAL = HV-ACCOUNT-AVAIL-BAL + COMM-AMT. COMPUTE HV-ACCOUNT-ACTUAL-BAL = HV-ACCOUNT-ACTUAL-BAL + COMM-AMT. | G6: Procedural (sem decisão nem tratamento de falha) | H6: comentário menciona condição: reavaliar | I6: Reincluir
A7: DBCRFUN-011 | B7: DBCRFUN | C7: 390 | D7: 392-408 | E7: Update the account record | F7: EXEC SQL UPDATE ACCOUNT SET ACCOUNT_EYECATCHER = :HV-ACCOUNT-EYECATCHER, ACCOUNT_CUSTOMER_NUMBER = :HV-ACCOUNT-CUST-NO, ACCOUNT_SORTCODE = :HV-ACCOUNT-SORTCODE, ACCOUNT_NUMBER = :HV-ACCOUNT-ACC-NO, ACCOUNT_TYPE = :HV-ACCOUNT-ACC-TYPE, ACCOUNT_INTEREST_RATE = :HV-ACCOUNT-INT-RATE, ACCOUNT_OPENED = :HV-ACCOUNT-OPENED, ACCOUNT_OVERDRAFT_LIMIT = :HV-ACCOUNT-OVERDRAFT-LIM, ACCOUNT_LAST_STATEMENT = :HV-ACCOUNT-LAST-STMT, ACCOUNT_NEXT_STATEMENT = :HV-ACCOUNT-NEXT-STMT, ACCOUNT_AVAILABLE_BALANCE = :HV-ACCOUNT-AVAIL-BAL, ACCOUNT_ACTUAL_BALANCE = :HV-ACCOUNT-ACTUAL-BAL WHERE (ACCOUNT_SORTCODE = :HV-ACCOUNT-SORTCODE AND ACCOUNT_NUMBER = :HV-ACCOUNT-ACC-NO) END-EXEC. | G7: Procedural (sem decisão nem tratamento de falha) | I7: Manter descartado
A8: DBCRFUN-014 | B8: DBCRFUN | C8: 429-430 | D8: 432-435 | E8: Check if SQLCODE indicates that Storm Drain processing is applicable in a workload if activated | F8: PERFORM CHECK-FOR-STORM-DRAIN-DB2 GO TO UAD999 END-IF. | G8: Procedural (sem decisão nem tratamento de falha) | H8: comentário delega lógica (PERFORM); contém GO TO (desvio incondicional); comentário menciona condição: reavaliar | I8: Manter descartado
A9: DBCRFUN-015 | B9: DBCRFUN | C9: 438-439 | D9: 441-448 | E9: If the RESP CODE was normal then we need to write to the PROCTRAN (processed transaction) datastore. | F9: PERFORM WRITE-TO-PROCTRAN. UAD999. EXIT. WRITE-TO-PROCTRAN SECTION. WTP010. | G9: Procedural (sem decisão nem tratamento de falha) | H9: comentário delega lógica (PERFORM); comentário menciona condição: reavaliar | I9: Reincluir
A10: DBCRFUN-016 | B10: DBCRFUN | C10: 451-452 | D10: 454-470 | E10: Write to the PROCTRAN datastore deatils regarding the successfully applied transaction. | F10: PERFORM WRITE-TO-PROCTRAN-DB2. WTP999. EXIT. WRITE-TO-PROCTRAN-DB2 SECTION. WTPD010. INITIALIZE HOST-PROCTRAN-ROW. INITIALIZE WS-EIBTASKN12. MOVE 'PRTR' TO HV-PROCTRAN-EYECATCHER. MOVE COMM-SORTC TO HV-PROCTRAN-SORT-CODE. MOVE COMM-ACCNO TO HV-PROCTRAN-ACC-NUMBER. MOVE EIBTASKN TO WS-EIBTASKN12. MOVE WS-EIBTASKN12 TO HV-PROCTRAN-REF. | G10: Procedural (sem decisão nem tratamento de falha) | H10: comentário delega lógica (PERFORM) | I10: Manter descartado
A11: DBCRFUN-020 | B11: DBCRFUN | C11: 522 | D11: 524-549 | E11: Write a record to PROCTRAN | F11: EXEC SQL INSERT INTO PROCTRAN ( PROCTRAN_EYECATCHER, PROCTRAN_SORTCODE, PROCTRAN_NUMBER, PROCTRAN_DATE, PROCTRAN_TIME, PROCTRAN_REF, PROCTRAN_TYPE, PROCTRAN_DESC, PROCTRAN_AMOUNT ) VALUES ( :HV-PROCTRAN-EYECATCHER, :HV-PROCTRAN-SORT-CODE, :HV-PROCTRAN-ACC-NUMBER, :HV-PROCTRAN-DATE, :HV-PROCTRAN-TIME, :HV-PROCTRAN-REF, :HV-PROCTRAN-TYPE, :HV-PROCTRAN-DESC, :HV-PROCTRAN-AMOUNT ) END-EXEC. | G11: Procedural (sem decisão nem tratamento de falha) | I11: Manter descartado
A12: DBCRFUN-025 | B12: DBCRFUN | C12: 639-640 | D12: 642-644 | E12: Check if SQLCODE indicates that Storm Drain processing is applicable in a workload if activated | F12: PERFORM CHECK-FOR-STORM-DRAIN-DB2 ELSE | G12: Procedural (sem decisão nem tratamento de falha) | H12: comentário delega lógica (PERFORM); comentário menciona condição: reavaliar | I12: Manter descartado
A13: DBCRFUN-028 | B13: DBCRFUN | C13: 699 | D13: 701-705 | E13: How ABENDs are dealt with | F13: ABEND-HANDLING SECTION. AH010. EXEC CICS ASSIGN ABCODE(MY-ABEND-CODE) END-EXEC. | G13: Procedural (sem decisão nem tratamento de falha) | I13: Manter descartado
A14: XFRFUN-002 | B14: XFRFUN | C14: 299-300 | D14: 302-311 | E14: The COMMAREA values have now been set so all we need to do is finish | F14: PERFORM GET-ME-OUT-OF-HERE. A999. EXIT. UPDATE-ACCOUNT-DB2 SECTION. UAD010. MOVE 'N' TO COMM-SUCCESS. | G14: Procedural (sem decisão nem tratamento de falha) | H14: comentário delega lógica (PERFORM) | I14: Manter descartado
A15: XFRFUN-007 | B15: XFRFUN | C15: 387 | D15: 389 | E15: Update the FROM account | F15: PERFORM UPDATE-ACCOUNT-DB2-FROM | G15: Procedural (sem decisão nem tratamento de falha) | H15: comentário delega lógica (PERFORM) | I15: Manter descartado
A16: XFRFUN-018 | B16: XFRFUN | C16: 598 | D16: 600 | E16: Update the TO account number | F16: PERFORM UPDATE-ACCOUNT-DB2-TO | G16: Procedural (sem decisão nem tratamento de falha) | H16: comentário delega lógica (PERFORM) | I16: Manter descartado
A17: XFRFUN-032 | B17: XFRFUN | C17: 907-909 | D17: 911-920 | E17: If the updates to the TO and FROM accounts were successful then we need to write to PROCTRAN (processed transaction) to record the successful transfer. | F17: PERFORM WRITE-TO-PROCTRAN. MOVE 'Y' TO COMM-SUCCESS. UAD999. EXIT. UPDATE-ACCOUNT-DB2-FROM SECTION. UADF010. | G17: Procedural (sem decisão nem tratamento de falha) | H17: comentário delega lógica (PERFORM); comentário menciona condição: reavaliar | I17: Reincluir
A18: XFRFUN-033 | B18: XFRFUN | C18: 922 | D18: 924-958 | E18: Position ourself at the matching FROM account record | F18: MOVE COMM-FACCNO TO DESIRED-ACC-NO. MOVE COMM-FSCODE TO DESIRED-SORT-CODE. MOVE DESIRED-SORT-CODE TO HV-ACCOUNT-SORTCODE. MOVE DESIRED-ACC-NO TO HV-ACCOUNT-ACC-NO. EXEC SQL SELECT ACCOUNT_EYECATCHER, ACCOUNT_CUSTOMER_NUMBER, ACCOUNT_SORTCODE, ACCOUNT_NUMBER, ACCOUNT_TYPE, ACCOUNT_INTEREST_RATE, ACCOUNT_OPENED, ACCOUNT_OVERDRAFT_LIMIT, ACCOUNT_LAST_STATEMENT, ACCOUNT_NEXT_STATEMENT, ACCOUNT_AVAILABLE_BALANCE, ACCOUNT_ACTUAL_BALANCE INTO :HV-ACCOUNT-EYECATCHER, :HV-ACCOUNT-CUST-NO, :HV-ACCOUNT-SORTCODE, :HV-ACCOUNT-ACC-NO, :HV-ACCOUNT-ACC-TYPE, :HV-ACCOUNT-INT-RATE, :HV-ACCOUNT-OPENED, :HV-ACCOUNT-OVERDRAFT-LIM, :HV-ACCOUNT-LAST-STMT, :HV-ACCOUNT-NEXT-STMT, :HV-ACCOUNT-AVAIL-BAL, :HV-ACCOUNT-ACTUAL-BAL FROM ACCOUNT WHERE (ACCOUNT_SORTCODE = :HV-ACCOUNT-SORTCODE AND ACCOUNT_NUMBER = :HV-ACCOUNT-ACC-NO) END-EXEC. | G18: Procedural (sem decisão nem tratamento de falha) | I18: Manter descartado
A19: XFRFUN-035 | B19: XFRFUN | C19: 973-974 | D19: 976-980 | E19: Check if SQLCODE indicates that Storm Drain processing is applicable in a workload if activated | F19: PERFORM CHECK-FOR-STORM-DRAIN-DB2 GO TO UADF999 END-IF. | G19: Procedural (sem decisão nem tratamento de falha) | H19: comentário delega lógica (PERFORM); contém GO TO (desvio incondicional); comentário menciona condição: reavaliar | I19: Manter descartado
A20: XFRFUN-036 | B20: XFRFUN | C20: 983-984 | D20: 986-1008 | E20: If the SQLCODE is OK then update the row on ACCOUNT for the FROM account. | F20: COMPUTE HV-ACCOUNT-AVAIL-BAL = HV-ACCOUNT-AVAIL-BAL - COMM-AMT. COMPUTE HV-ACCOUNT-ACTUAL-BAL = HV-ACCOUNT-ACTUAL-BAL - COMM-AMT. EXEC SQL UPDATE ACCOUNT SET ACCOUNT_EYECATCHER = :HV-ACCOUNT-EYECATCHER, ACCOUNT_CUSTOMER_NUMBER = :HV-ACCOUNT-CUST-NO, ACCOUNT_SORTCODE = :HV-ACCOUNT-SORTCODE, ACCOUNT_NUMBER = :HV-ACCOUNT-ACC-NO, ACCOUNT_TYPE = :HV-ACCOUNT-ACC-TYPE, ACCOUNT_INTEREST_RATE = :HV-ACCOUNT-INT-RATE, ACCOUNT_OPENED = :HV-ACCOUNT-OPENED, ACCOUNT_OVERDRAFT_LIMIT = :HV-ACCOUNT-OVERDRAFT-LIM, ACCOUNT_LAST_STATEMENT = :HV-ACCOUNT-LAST-STMT, ACCOUNT_NEXT_STATEMENT = :HV-ACCOUNT-NEXT-STMT, ACCOUNT_AVAILABLE_BALANCE = :HV-ACCOUNT-AVAIL-BAL, ACCOUNT_ACTUAL_BALANCE = :HV-ACCOUNT-ACTUAL-BAL WHERE (ACCOUNT_SORTCODE = :HV-ACCOUNT-SORTCODE AND ACCOUNT_NUMBER = :HV-ACCOUNT-ACC-NO) END-EXEC. | G20: Procedural (sem decisão nem tratamento de falha) | H20: comentário menciona condição: reavaliar | I20: Reincluir
A21: XFRFUN-038 | B21: XFRFUN | C21: 1020-1021 | D21: 1023-1027 | E21: Check if SQLCODE indicates that Storm Drain processing is applicable in a workload if activated | F21: PERFORM CHECK-FOR-STORM-DRAIN-DB2 GO TO UADF999 END-IF. | G21: Procedural (sem decisão nem tratamento de falha) | H21: comentário delega lógica (PERFORM); contém GO TO (desvio incondicional); comentário menciona condição: reavaliar | I21: Manter descartado
A22: XFRFUN-039 | B22: XFRFUN | C22: 1030-1031 | D22: 1033-1044 | E22: If the update to the FROM account was OK store the updated balances away. | F22: MOVE HV-ACCOUNT-AVAIL-BAL TO COMM-FAVBAL. MOVE HV-ACCOUNT-ACTUAL-BAL TO COMM-FACTBAL. MOVE 'Y' TO COMM-SUCCESS. UADF999. EXIT. UPDATE-ACCOUNT-DB2-TO SECTION. UADT010. MOVE 'N' TO COMM-SUCCESS. | G22: Procedural (sem decisão nem tratamento de falha) | H22: comentário menciona condição: reavaliar | I22: Manter descartado
A23: XFRFUN-040 | B23: XFRFUN | C23: 1046-1047 | D23: 1049-1085 | E23: Position ourself at the matching account record for the TO account | F23: INITIALIZE HOST-ACCOUNT-ROW. MOVE COMM-TACCNO TO DESIRED-ACC-NO. MOVE COMM-TSCODE TO DESIRED-SORT-CODE. MOVE DESIRED-SORT-CODE TO HV-ACCOUNT-SORTCODE. MOVE DESIRED-ACC-NO TO HV-ACCOUNT-ACC-NO. EXEC SQL SELECT ACCOUNT_EYECATCHER, ACCOUNT_CUSTOMER_NUMBER, ACCOUNT_SORTCODE, ACCOUNT_NUMBER, ACCOUNT_TYPE, ACCOUNT_INTEREST_RATE, ACCOUNT_OPENED, ACCOUNT_OVERDRAFT_LIMIT, ACCOUNT_LAST_STATEMENT, ACCOUNT_NEXT_STATEMENT, ACCOUNT_AVAILABLE_BALANCE, ACCOUNT_ACTUAL_BALANCE INTO :HV-ACCOUNT-EYECATCHER, :HV-ACCOUNT-CUST-NO, :HV-ACCOUNT-SORTCODE, :HV-ACCOUNT-ACC-NO, :HV-ACCOUNT-ACC-TYPE, :HV-ACCOUNT-INT-RATE, :HV-ACCOUNT-OPENED, :HV-ACCOUNT-OVERDRAFT-LIM, :HV-ACCOUNT-LAST-STMT, :HV-ACCOUNT-NEXT-STMT, :HV-ACCOUNT-AVAIL-BAL, :HV-ACCOUNT-ACTUAL-BAL FROM ACCOUNT WHERE (ACCOUNT_SORTCODE = :HV-ACCOUNT-SORTCODE AND ACCOUNT_NUMBER = :HV-ACCOUNT-ACC-NO) END-EXEC. | G23: Procedural (sem decisão nem tratamento de falha) | I23: Manter descartado
A24: XFRFUN-042 | B24: XFRFUN | C24: 1094-1095 | D24: 1097 | E24: Check if SQLCODE indicates that Storm Drain processing is applicable in a workload if activated | F24: PERFORM CHECK-FOR-STORM-DRAIN-DB2 | G24: Procedural (sem decisão nem tratamento de falha) | H24: comentário delega lógica (PERFORM); comentário menciona condição: reavaliar | I24: Manter descartado
A25: XFRFUN-051 | B25: XFRFUN | C25: 1354-1355 | D25: 1357-1378 | E25: If the SELECT was successful, then amend the account balances and UPDATE the row back onto the ACCOUNT table. | F25: COMPUTE HV-ACCOUNT-AVAIL-BAL = HV-ACCOUNT-AVAIL-BAL + COMM-AMT. COMPUTE HV-ACCOUNT-ACTUAL-BAL = HV-ACCOUNT-ACTUAL-BAL + COMM-AMT. EXEC SQL UPDATE ACCOUNT SET ACCOUNT_EYECATCHER = :HV-ACCOUNT-EYECATCHER, ACCOUNT_CUSTOMER_NUMBER = :HV-ACCOUNT-CUST-NO, ACCOUNT_SORTCODE = :HV-ACCOUNT-SORTCODE, ACCOUNT_NUMBER = :HV-ACCOUNT-ACC-NO, ACCOUNT_TYPE = :HV-ACCOUNT-ACC-TYPE, ACCOUNT_INTEREST_RATE = :HV-ACCOUNT-INT-RATE, ACCOUNT_OPENED = :HV-ACCOUNT-OPENED, ACCOUNT_OVERDRAFT_LIMIT = :HV-ACCOUNT-OVERDRAFT-LIM, ACCOUNT_LAST_STATEMENT = :HV-ACCOUNT-LAST-STMT, ACCOUNT_NEXT_STATEMENT = :HV-ACCOUNT-NEXT-STMT, ACCOUNT_AVAILABLE_BALANCE = :HV-ACCOUNT-AVAIL-BAL, ACCOUNT_ACTUAL_BALANCE = :HV-ACCOUNT-ACTUAL-BAL WHERE (ACCOUNT_SORTCODE = :HV-ACCOUNT-SORTCODE AND ACCOUNT_NUMBER = :HV-ACCOUNT-ACC-NO) END-EXEC. | G25: Procedural (sem decisão nem tratamento de falha) | H25: comentário menciona condição: reavaliar | I25: Reincluir
A26: XFRFUN-058 | B26: XFRFUN | C26: 1552 | D26: 1554-1572 | E26: Store the data away | F26: MOVE HV-ACCOUNT-AVAIL-BAL TO COMM-TAVBAL. MOVE HV-ACCOUNT-ACTUAL-BAL TO COMM-TACTBAL. MOVE 'Y' TO COMM-SUCCESS. UADT999. EXIT. WRITE-TO-PROCTRAN SECTION. WTP010. PERFORM WRITE-TO-PROCTRAN-DB2. WTP999. EXIT. WRITE-TO-PROCTRAN-DB2 SECTION. WTPD010. | G26: Procedural (sem decisão nem tratamento de falha) | H26: comentário delega lógica (PERFORM) | I26: Manter descartado
A27: XFRFUN-059 | B27: XFRFUN | C27: 1574-1575 | D27: 1577-1584 | E27: Writes details of the successful transfer to the PROCTRAN (Processed Transaction) datastore. | F27: INITIALIZE HOST-PROCTRAN-ROW. INITIALIZE WS-EIBTASKN12. MOVE 'PRTR' TO HV-PROCTRAN-EYECATCHER. MOVE COMM-FSCODE TO HV-PROCTRAN-SORT-CODE. MOVE COMM-FACCNO TO HV-PROCTRAN-ACC-NUMBER. MOVE EIBTASKN TO WS-EIBTASKN12. MOVE WS-EIBTASKN12 TO HV-PROCTRAN-REF. | G27: Procedural (sem decisão nem tratamento de falha) | H27: comentário menciona condição: reavaliar | I27: Manter descartado
A28: XFRFUN-060 | B28: XFRFUN | C28: 1587 | D28: 1589-1641 | E28: Populate the time and date | F28: EXEC CICS ASKTIME ABSTIME(WS-U-TIME) END-EXEC. EXEC CICS FORMATTIME ABSTIME(WS-U-TIME) DDMMYYYY(WS-ORIG-DATE) TIME(HV-PROCTRAN-TIME) DATESEP('.') END-EXEC. MOVE WS-ORIG-DATE TO WS-ORIG-DATE-GRP-X. MOVE WS-ORIG-DATE-GRP-X TO HV-PROCTRAN-DATE. SET PROC-TY-TRANSFER IN PROCTRAN-AREA TO TRUE MOVE PROC-TRAN-TYPE IN PROCTRAN-AREA TO HV-PROCTRAN-TYPE. MOVE COMM-AMT TO HV-PROCTRAN-AMOUNT. SET PROC-TRAN-DESC-XFR-FLAG IN PROCTRAN-AREA TO TRUE. MOVE COMM-TSCODE TO PROC-TRAN-DESC-XFR-SORTCODE IN PROCTRAN-AREA. MOVE COMM-TACCNO TO PROC-TRAN-DESC-XFR-ACCOUNT IN PROCTRAN-AREA. MOVE PROC-TRAN-DESC IN PROCTRAN-AREA TO HV-PROCTRAN-DESC. EXEC SQL INSERT INTO PROCTRAN ( PROCTRAN_EYECATCHER, PROCTRAN_SORTCODE, PROCTRAN_NUMBER, PROCTRAN_DATE, PROCTRAN_TIME, PROCTRAN_REF, PROCTRAN_TYPE, PROCTRAN_DESC, PROCTRAN_AMOUNT ) VALUES ( :HV-PROCTRAN-EYECATCHER, :HV-PROCTRAN-SORT-CODE, :HV-PROCTRAN-ACC-NUMBER, :HV-PROCTRAN-DATE, :HV-PROCTRAN-TIME, :HV-PROCTRAN-REF, :HV-PROCTRAN-TYPE, :HV-PROCTRAN-DESC, :HV-PROCTRAN-AMOUNT ) END-EXEC. | G28: Procedural (sem decisão nem tratamento de falha) | I28: Manter descartado
A29: XFRFUN-066 | B29: XFRFUN | C29: 1772 | D29: 1774-1776 | E29: Deal with any abends | F29: EXEC CICS ASSIGN ABCODE(MY-ABEND-CODE) END-EXEC. | G29: Procedural (sem decisão nem tratamento de falha) | I29: Manter descartado
A30: BNK1CRA-010 | B30: BNK1CRA | C30: 282 | D30: 284-335 | E30: Get supplemental information | F30: EXEC CICS ASSIGN APPLID(ABND-APPLID) END-EXEC MOVE EIBTASKN TO ABND-TASKNO-KEY MOVE EIBTRNID TO ABND-TRANID PERFORM POPULATE-TIME-DATE MOVE WS-ORIG-DATE TO ABND-DATE STRING WS-TIME-NOW-GRP-HH DELIMITED BY SIZE, ':' DELIMITED BY SIZE, WS-TIME-NOW-GRP-MM DELIMITED BY SIZE, ':' DELIMITED BY SIZE, WS-TIME-NOW-GRP-MM DELIMITED BY SIZE INTO ABND-TIME END-STRING MOVE WS-U-TIME TO ABND-UTIME-KEY MOVE 'HBNK' TO ABND-CODE EXEC CICS ASSIGN PROGRAM(ABND-PROGRAM) END-EXEC MOVE ZEROS TO ABND-SQLCODE STRING 'A010 - RETURN TRANSID(OCRA) FAIL.' DELIMITED BY SIZE, 'EIBRESP=' DELIMITED BY SIZE, ABND-RESPCODE DELIMITED BY SIZE, ' RESP2=' DELIMITED BY SIZE, ABND-RESP2CODE DELIMITED BY SIZE INTO ABND-FREEFORM END-STRING EXEC CICS LINK PROGRAM(WS-ABEND-PGM) COMMAREA(ABNDINFO-REC) END-EXEC INITIALIZE WS-FAIL-INFO MOVE 'BNK1CRA - A010 - RETURN TRANSID(OCRA) FAIL' TO WS-CICS-FAIL-MSG MOVE WS-CICS-RESP TO WS-CICS-RESP-DISP MOVE WS-CICS-RESP2 TO WS-CICS-RESP2-DISP PERFORM ABEND-THIS-TASK END-IF. A999. EXIT. PROCESS-MAP SECTION. PM010. | G30: Procedural (sem decisão nem tratamento de falha) | H30: comentário curto; comentário delega lógica (PERFORM) | I30: Manter descartado
A31: BNK1CRA-011 | B31: BNK1CRA | C31: 337 | D31: 339 | E31: Retrieve the data from the map | F31: PERFORM RECEIVE-MAP. | G31: Procedural (sem decisão nem tratamento de falha) | H31: comentário delega lógica (PERFORM) | I31: Manter descartado
A32: BNK1CRA-012 | B32: BNK1CRA | C32: 342 | D32: 344 | E32: Validate the received data | F32: PERFORM EDIT-DATA. | G32: Procedural (sem decisão nem tratamento de falha) | H32: comentário delega lógica (PERFORM) | I32: Manter descartado
A33: BNK1CRA-014 | B33: BNK1CRA | C33: 357 | D33: 359-366 | E33: Output the data to the screen | F33: PERFORM SEND-MAP. PM999. EXIT. RECEIVE-MAP SECTION. RM010. | G33: Procedural (sem decisão nem tratamento de falha) | H33: comentário delega lógica (PERFORM) | I33: Manter descartado
A34: BNK1CRA-017 | B34: BNK1CRA | C34: 389 | D34: 391-442 | E34: Get supplemental information | F34: EXEC CICS ASSIGN APPLID(ABND-APPLID) END-EXEC MOVE EIBTASKN TO ABND-TASKNO-KEY MOVE EIBTRNID TO ABND-TRANID PERFORM POPULATE-TIME-DATE MOVE WS-ORIG-DATE TO ABND-DATE STRING WS-TIME-NOW-GRP-HH DELIMITED BY SIZE, ':' DELIMITED BY SIZE, WS-TIME-NOW-GRP-MM DELIMITED BY SIZE, ':' DELIMITED BY SIZE, WS-TIME-NOW-GRP-MM DELIMITED BY SIZE INTO ABND-TIME END-STRING MOVE WS-U-TIME TO ABND-UTIME-KEY MOVE 'HBNK' TO ABND-CODE EXEC CICS ASSIGN PROGRAM(ABND-PROGRAM) END-EXEC MOVE ZEROS TO ABND-SQLCODE STRING 'RM010 - RECEIVE MAP FAIL.' DELIMITED BY SIZE, 'EIBRESP=' DELIMITED BY SIZE, ABND-RESPCODE DELIMITED BY SIZE, ' RESP2=' DELIMITED BY SIZE, ABND-RESP2CODE DELIMITED BY SIZE INTO ABND-FREEFORM END-STRING EXEC CICS LINK PROGRAM(WS-ABEND-PGM) COMMAREA(ABNDINFO-REC) END-EXEC INITIALIZE WS-FAIL-INFO MOVE 'BNKMENU - RM010 - RECEIVE MAP FAIL ' TO WS-CICS-FAIL-MSG MOVE WS-CICS-RESP TO WS-CICS-RESP-DISP MOVE WS-CICS-RESP2 TO WS-CICS-RESP2-DISP PERFORM ABEND-THIS-TASK END-IF. RM999. EXIT. EDIT-DATA SECTION. ED010. | G34: Procedural (sem decisão nem tratamento de falha) | H34: comentário curto; comentário delega lógica (PERFORM) | I34: Manter descartado
A35: BNK1CRA-019 | B35: BNK1CRA | C35: 472 | D35: 474-481 | E35: Validate the Amount entered | F35: PERFORM VALIDATE-AMOUNT. ED999. EXIT. UPD-CRED-DATA SECTION. UCD010. | G35: Procedural (sem decisão nem tratamento de falha) | H35: comentário delega lógica (PERFORM) | I35: Manter descartado
A36: BNK1CRA-020 | B36: BNK1CRA | C36: 483-484 | D36: 486-489 | E36: Set up the COMMAREA fields required by DBCRFUN and then link to it. | F36: INITIALIZE SUBPGM-PARMS. MOVE ACCNOI TO SUBPGM-ACCNO. MOVE 0 TO SUBPGM-AMT. | G36: Procedural (sem decisão nem tratamento de falha) | I36: Manter descartado
A37: BNK1CRA-024 | B37: BNK1CRA | C37: 530 | D37: 532-576 | E37: Get supplemental information | F37: EXEC CICS ASSIGN APPLID(ABND-APPLID) END-EXEC MOVE EIBTASKN TO ABND-TASKNO-KEY MOVE EIBTRNID TO ABND-TRANID PERFORM POPULATE-TIME-DATE MOVE WS-ORIG-DATE TO ABND-DATE STRING WS-TIME-NOW-GRP-HH DELIMITED BY SIZE, ':' DELIMITED BY SIZE, WS-TIME-NOW-GRP-MM DELIMITED BY SIZE, ':' DELIMITED BY SIZE, WS-TIME-NOW-GRP-MM DELIMITED BY SIZE INTO ABND-TIME END-STRING MOVE WS-U-TIME TO ABND-UTIME-KEY MOVE 'HBNK' TO ABND-CODE EXEC CICS ASSIGN PROGRAM(ABND-PROGRAM) END-EXEC MOVE ZEROS TO ABND-SQLCODE STRING 'UCD010 - LINK DBCRFUN FAIL.' DELIMITED BY SIZE, 'EIBRESP=' DELIMITED BY SIZE, ABND-RESPCODE DELIMITED BY SIZE, ' RESP2=' DELIMITED BY SIZE, ABND-RESP2CODE DELIMITED BY SIZE INTO ABND-FREEFORM END-STRING EXEC CICS LINK PROGRAM(WS-ABEND-PGM) COMMAREA(ABNDINFO-REC) END-EXEC INITIALIZE WS-FAIL-INFO MOVE 'BNK1CRA - UCD010 - LINK DBCRFUN FAIL ' TO WS-CICS-FAIL-MSG MOVE WS-CICS-RESP TO WS-CICS-RESP-DISP MOVE WS-CICS-RESP2 TO WS-CICS-RESP2-DISP PERFORM ABEND-THIS-TASK END-IF. | G37: Procedural (sem decisão nem tratamento de falha) | H37: comentário curto; comentário delega lógica (PERFORM) | I37: Manter descartado
A38: BNK1CRA-026 | B38: BNK1CRA | C38: 629 | D38: 631-644 | E38: Set up the values on the map | F38: MOVE SUBPGM-ACCNO TO ACCNOO. MOVE SUBPGM-SORTC TO SORTCO. MOVE SUBPGM-ACT-BAL TO ACTUAL-BALANCE-DISPLAY. MOVE SUBPGM-AV-BAL TO AVAILABLE-BALANCE-DISPLAY. MOVE ACTUAL-BALANCE-DISPLAY TO ACTBALO. MOVE AVAILABLE-BALANCE-DISPLAY TO AVBALO. UCD999. EXIT. SEND-MAP SECTION. SM010. | G38: Procedural (sem decisão nem tratamento de falha) | I38: Manter descartado
A39: BNK1CRA-029 | B39: BNK1CRA | C39: 668 | D39: 670-717 | E39: Get supplemental information | F39: EXEC CICS ASSIGN APPLID(ABND-APPLID) END-EXEC MOVE EIBTASKN TO ABND-TASKNO-KEY MOVE EIBTRNID TO ABND-TRANID PERFORM POPULATE-TIME-DATE MOVE WS-ORIG-DATE TO ABND-DATE STRING WS-TIME-NOW-GRP-HH DELIMITED BY SIZE, ':' DELIMITED BY SIZE, WS-TIME-NOW-GRP-MM DELIMITED BY SIZE, ':' DELIMITED BY SIZE, WS-TIME-NOW-GRP-MM DELIMITED BY SIZE INTO ABND-TIME END-STRING MOVE WS-U-TIME TO ABND-UTIME-KEY MOVE 'HBNK' TO ABND-CODE EXEC CICS ASSIGN PROGRAM(ABND-PROGRAM) END-EXEC MOVE ZEROS TO ABND-SQLCODE STRING 'SM010 - SEND MAP ERASE FAIL.' DELIMITED BY SIZE, 'EIBRESP=' DELIMITED BY SIZE, ABND-RESPCODE DELIMITED BY SIZE, ' RESP2=' DELIMITED BY SIZE, ABND-RESP2CODE DELIMITED BY SIZE INTO ABND-FREEFORM END-STRING EXEC CICS LINK PROGRAM(WS-ABEND-PGM) COMMAREA(ABNDINFO-REC) END-EXEC INITIALIZE WS-FAIL-INFO MOVE 'BNK1CRA - SM010 - SEND MAP ERASE FAIL ' TO WS-CICS-FAIL-MSG MOVE WS-CICS-RESP TO WS-CICS-RESP-DISP MOVE WS-CICS-RESP2 TO WS-CICS-RESP2-DISP PERFORM ABEND-THIS-TASK END-IF GO TO SM999 END-IF. | G39: Procedural (sem decisão nem tratamento de falha) | H39: comentário curto; comentário delega lógica (PERFORM); contém GO TO (desvio incondicional) | I39: Manter descartado
A40: BNK1CRA-032 | B40: BNK1CRA | C40: 742 | D40: 744-791 | E40: Get supplemental information | F40: EXEC CICS ASSIGN APPLID(ABND-APPLID) END-EXEC MOVE EIBTASKN TO ABND-TASKNO-KEY MOVE EIBTRNID TO ABND-TRANID PERFORM POPULATE-TIME-DATE MOVE WS-ORIG-DATE TO ABND-DATE STRING WS-TIME-NOW-GRP-HH DELIMITED BY SIZE, ':' DELIMITED BY SIZE, WS-TIME-NOW-GRP-MM DELIMITED BY SIZE, ':' DELIMITED BY SIZE, WS-TIME-NOW-GRP-MM DELIMITED BY SIZE INTO ABND-TIME END-STRING MOVE WS-U-TIME TO ABND-UTIME-KEY MOVE 'HBNK' TO ABND-CODE EXEC CICS ASSIGN PROGRAM(ABND-PROGRAM) END-EXEC MOVE ZEROS TO ABND-SQLCODE STRING 'SM010 - SEND MAP DATAONLY FAIL.' DELIMITED BY SIZE, 'EIBRESP=' DELIMITED BY SIZE, ABND-RESPCODE DELIMITED BY SIZE, ' RESP2=' DELIMITED BY SIZE, ABND-RESP2CODE DELIMITED BY SIZE INTO ABND-FREEFORM END-STRING EXEC CICS LINK PROGRAM(WS-ABEND-PGM) COMMAREA(ABNDINFO-REC) END-EXEC INITIALIZE WS-FAIL-INFO MOVE 'BNK1CRA - SM010 - SEND MAP DATAONLY FAIL ' TO WS-CICS-FAIL-MSG MOVE WS-CICS-RESP TO WS-CICS-RESP-DISP MOVE WS-CICS-RESP2 TO WS-CICS-RESP2-DISP PERFORM ABEND-THIS-TASK END-IF GO TO SM999 END-IF. | G40: Procedural (sem decisão nem tratamento de falha) | H40: comentário curto; comentário delega lógica (PERFORM); contém GO TO (desvio incondicional) | I40: Manter descartado
A41: BNK1CRA-035 | B41: BNK1CRA | C41: 817 | D41: 819-872 | E41: Get supplemental information | F41: EXEC CICS ASSIGN APPLID(ABND-APPLID) END-EXEC MOVE EIBTASKN TO ABND-TASKNO-KEY MOVE EIBTRNID TO ABND-TRANID PERFORM POPULATE-TIME-DATE MOVE WS-ORIG-DATE TO ABND-DATE STRING WS-TIME-NOW-GRP-HH DELIMITED BY SIZE, ':' DELIMITED BY SIZE, WS-TIME-NOW-GRP-MM DELIMITED BY SIZE, ':' DELIMITED BY SIZE, WS-TIME-NOW-GRP-MM DELIMITED BY SIZE INTO ABND-TIME END-STRING MOVE WS-U-TIME TO ABND-UTIME-KEY MOVE 'HBNK' TO ABND-CODE EXEC CICS ASSIGN PROGRAM(ABND-PROGRAM) END-EXEC MOVE ZEROS TO ABND-SQLCODE STRING 'SM010 - SEND MAP DATAONLY ALARM FAIL.' DELIMITED BY SIZE, 'EIBRESP=' DELIMITED BY SIZE, ABND-RESPCODE DELIMITED BY SIZE, ' RESP2=' DELIMITED BY SIZE, ABND-RESP2CODE DELIMITED BY SIZE INTO ABND-FREEFORM END-STRING EXEC CICS LINK PROGRAM(WS-ABEND-PGM) COMMAREA(ABNDINFO-REC) END-EXEC INITIALIZE WS-FAIL-INFO MOVE 'BNK1CRA - SM010 - SEND MAP DATAONLY ALARM FAIL ' TO WS-CICS-FAIL-MSG MOVE WS-CICS-RESP TO WS-CICS-RESP-DISP MOVE WS-CICS-RESP2 TO WS-CICS-RESP2-DISP PERFORM ABEND-THIS-TASK END-IF END-IF. SM999. EXIT. SEND-TERMINATION-MSG SECTION. STM010. | G41: Procedural (sem decisão nem tratamento de falha) | H41: comentário curto; comentário delega lógica (PERFORM) | I41: Manter descartado
A42: BNK1TFN-008 | B42: BNK1TFN | C42: 238 | D42: 239-242 | E42: MOVE 10 TO CUSTNOL | F42: SET SEND-DATAONLY-ALARM TO TRUE PERFORM SEND-MAP END-EVALUATE. | G42: Procedural (sem decisão nem tratamento de falha) | H42: possível código desativado; comentário delega lógica (PERFORM) | I42: Manter descartado
A43: BNK1TFN-011 | B43: BNK1TFN | C43: 266 | D43: 268-320 | E43: Get supplemental information | F43: EXEC CICS ASSIGN APPLID(ABND-APPLID) END-EXEC MOVE EIBTASKN TO ABND-TASKNO-KEY MOVE EIBTRNID TO ABND-TRANID PERFORM POPULATE-TIME-DATE MOVE WS-ORIG-DATE TO ABND-DATE STRING WS-TIME-NOW-GRP-HH DELIMITED BY SIZE, ':' DELIMITED BY SIZE, WS-TIME-NOW-GRP-MM DELIMITED BY SIZE, ':' DELIMITED BY SIZE, WS-TIME-NOW-GRP-MM DELIMITED BY SIZE INTO ABND-TIME END-STRING MOVE WS-U-TIME TO ABND-UTIME-KEY MOVE 'HBNK' TO ABND-CODE EXEC CICS ASSIGN PROGRAM(ABND-PROGRAM) END-EXEC MOVE ZEROS TO ABND-SQLCODE STRING 'A010 - RETURN TRANSID(OCCS) FAIL.' DELIMITED BY SIZE, ' EIBRESP=' DELIMITED BY SIZE, ABND-RESPCODE DELIMITED BY SIZE, ' RESP2=' DELIMITED BY SIZE, ABND-RESP2CODE DELIMITED BY SIZE INTO ABND-FREEFORM END-STRING EXEC CICS LINK PROGRAM(WS-ABEND-PGM) COMMAREA(ABNDINFO-REC) END-EXEC INITIALIZE WS-FAIL-INFO MOVE 'BNK1TFN - A010 - RETURN TRANSID(OCCS) FAIL' TO WS-CICS-FAIL-MSG MOVE WS-CICS-RESP TO WS-CICS-RESP-DISP MOVE WS-CICS-RESP2 TO WS-CICS-RESP2-DISP PERFORM ABEND-THIS-TASK END-IF. A999. EXIT. PROCESS-MAP SECTION. PM010. | G43: Procedural (sem decisão nem tratamento de falha) | H43: comentário curto; comentário delega lógica (PERFORM) | I43: Manter descartado
A44: BNK1TFN-012 | B44: BNK1TFN | C44: 322 | D44: 325 | E44: Retrieve the data from the map | F44: PERFORM RECEIVE-MAP. | G44: Procedural (sem decisão nem tratamento de falha) | H44: comentário delega lógica (PERFORM) | I44: Manter descartado
A45: BNK1TFN-013 | B45: BNK1TFN | C45: 328 | D45: 330 | E45: Validate the received data | F45: PERFORM EDIT-DATA. | G45: Procedural (sem decisão nem tratamento de falha) | H45: comentário delega lógica (PERFORM) | I45: Manter descartado
A46: BNK1TFN-015 | B46: BNK1TFN | C46: 343 | D46: 345-352 | E46: Output the data to the screen | F46: PERFORM SEND-MAP. PM999. EXIT. RECEIVE-MAP SECTION. RM010. | G46: Procedural (sem decisão nem tratamento de falha) | H46: comentário delega lógica (PERFORM) | I46: Manter descartado
A47: BNK1TFN-018 | B47: BNK1TFN | C47: 375 | D47: 377-429 | E47: Get supplemental information | F47: EXEC CICS ASSIGN APPLID(ABND-APPLID) END-EXEC MOVE EIBTASKN TO ABND-TASKNO-KEY MOVE EIBTRNID TO ABND-TRANID PERFORM POPULATE-TIME-DATE MOVE WS-ORIG-DATE TO ABND-DATE STRING WS-TIME-NOW-GRP-HH DELIMITED BY SIZE, ':' DELIMITED BY SIZE, WS-TIME-NOW-GRP-MM DELIMITED BY SIZE, ':' DELIMITED BY SIZE, WS-TIME-NOW-GRP-MM DELIMITED BY SIZE INTO ABND-TIME END-STRING MOVE WS-U-TIME TO ABND-UTIME-KEY MOVE 'HBNK' TO ABND-CODE EXEC CICS ASSIGN PROGRAM(ABND-PROGRAM) END-EXEC MOVE ZEROS TO ABND-SQLCODE STRING 'RM010 - RECEIVE MAP FAIL.' DELIMITED BY SIZE, ' EIBRESP=' DELIMITED BY SIZE, ABND-RESPCODE DELIMITED BY SIZE, ' RESP2=' DELIMITED BY SIZE, ABND-RESP2CODE DELIMITED BY SIZE INTO ABND-FREEFORM END-STRING EXEC CICS LINK PROGRAM(WS-ABEND-PGM) COMMAREA(ABNDINFO-REC) END-EXEC INITIALIZE WS-FAIL-INFO MOVE 'BNK1TFN - RM010 - RECEIVE MAP FAIL ' TO WS-CICS-FAIL-MSG MOVE WS-CICS-RESP TO WS-CICS-RESP-DISP MOVE WS-CICS-RESP2 TO WS-CICS-RESP2-DISP PERFORM ABEND-THIS-TASK END-IF. RM999. EXIT. EDIT-DATA SECTION. ED010. | G47: Procedural (sem decisão nem tratamento de falha) | H47: comentário curto; comentário delega lógica (PERFORM) | I47: Manter descartado
A48: BNK1TFN-020 | B48: BNK1TFN | C48: 470 | D48: 472-479 | E48: Validate the Amount entered | F48: PERFORM VALIDATE-AMOUNT. ED999. EXIT. GET-ACC-DATA SECTION. GCD010. | G48: Procedural (sem decisão nem tratamento de falha) | H48: comentário delega lógica (PERFORM) | I48: Manter descartado
A49: BNK1TFN-021 | B49: BNK1TFN | C49: 481-483 | D49: 485-489 | E49: Set up the fields required by XFRFUN then link to it to get account information and perform the transfer, then check what gets returned. | F49: INITIALIZE SUBPGM-PARMS. MOVE FACCNOI TO SUBPGM-FACCNO. MOVE TACCNOI TO SUBPGM-TACCNO. MOVE 'N' TO SUBPGM-SUCCESS. | G49: Procedural (sem decisão nem tratamento de falha) | H49: comentário menciona condição: reavaliar | I49: Manter descartado
A50: BNK1TFN-024 | B50: BNK1TFN | C50: 515 | D50: 517-561 | E50: Get supplemental information | F50: EXEC CICS ASSIGN APPLID(ABND-APPLID) END-EXEC MOVE EIBTASKN TO ABND-TASKNO-KEY MOVE EIBTRNID TO ABND-TRANID PERFORM POPULATE-TIME-DATE MOVE WS-ORIG-DATE TO ABND-DATE STRING WS-TIME-NOW-GRP-HH DELIMITED BY SIZE, ':' DELIMITED BY SIZE, WS-TIME-NOW-GRP-MM DELIMITED BY SIZE, ':' DELIMITED BY SIZE, WS-TIME-NOW-GRP-MM DELIMITED BY SIZE INTO ABND-TIME END-STRING MOVE WS-U-TIME TO ABND-UTIME-KEY MOVE 'HBNK' TO ABND-CODE EXEC CICS ASSIGN PROGRAM(ABND-PROGRAM) END-EXEC MOVE ZEROS TO ABND-SQLCODE STRING 'GCD010 - LINK XFRFUN FAIL.' DELIMITED BY SIZE, ' EIBRESP=' DELIMITED BY SIZE, ABND-RESPCODE DELIMITED BY SIZE, ' RESP2=' DELIMITED BY SIZE, ABND-RESP2CODE DELIMITED BY SIZE INTO ABND-FREEFORM END-STRING EXEC CICS LINK PROGRAM(WS-ABEND-PGM) COMMAREA(ABNDINFO-REC) END-EXEC INITIALIZE WS-FAIL-INFO MOVE 'BNK1TFN - GCD010 - LINK XFRFUN FAIL ' TO WS-CICS-FAIL-MSG MOVE WS-CICS-RESP TO WS-CICS-RESP-DISP MOVE WS-CICS-RESP2 TO WS-CICS-RESP2-DISP PERFORM ABEND-THIS-TASK END-IF. | G50: Procedural (sem decisão nem tratamento de falha) | H50: comentário curto; comentário delega lógica (PERFORM) | I50: Manter descartado
A51: BNK1TFN-025 | B51: BNK1TFN | C51: 564 | D51: 566-577 | E51: Map the returned data to the screen output fields | F51: MOVE SUBPGM-FACCNO TO FACCNO2O MOVE SUBPGM-FSCODE TO FSORTCO MOVE SUBPGM-TACCNO TO TACCNO2O MOVE SUBPGM-TSCODE TO TSORTCO MOVE ZERO TO FROM-ACTUAL-BALANCE-DISPLAY MOVE ZERO TO FROM-AVAILABLE-BALANCE-DISPLAY MOVE ZERO TO TO-ACTUAL-BALANCE-DISPLAY MOVE ZERO TO TO-AVAILABLE-BALANCE-DISPLAY MOVE FROM-ACTUAL-BALANCE-DISPLAY TO FACTBALO MOVE FROM-AVAILABLE-BALANCE-DISPLAY TO FAVBALO MOVE TO-ACTUAL-BALANCE-DISPLAY TO TACTBALO MOVE TO-AVAILABLE-BALANCE-DISPLAY TO TAVBALO | G51: Procedural (sem decisão nem tratamento de falha) | I51: Manter descartado
A52: BNK1TFN-027 | B52: BNK1TFN | C52: 643 | D52: 645-663 | E52: Map the remaining fields | F52: MOVE SUBPGM-FACCNO TO FACCNO2O. MOVE SUBPGM-FSCODE TO FSORTCO. MOVE SUBPGM-TACCNO TO TACCNO2O. MOVE SUBPGM-TSCODE TO TSORTCO. MOVE SUBPGM-FACTBAL TO FROM-ACTUAL-BALANCE-DISPLAY. MOVE SUBPGM-FAVBAL TO FROM-AVAILABLE-BALANCE-DISPLAY. MOVE SUBPGM-TACTBAL TO TO-ACTUAL-BALANCE-DISPLAY. MOVE SUBPGM-TAVBAL TO TO-AVAILABLE-BALANCE-DISPLAY. MOVE FROM-ACTUAL-BALANCE-DISPLAY TO FACTBALO. MOVE FROM-AVAILABLE-BALANCE-DISPLAY TO FAVBALO. MOVE TO-ACTUAL-BALANCE-DISPLAY TO TACTBALO. MOVE TO-AVAILABLE-BALANCE-DISPLAY TO TAVBALO. GCD999. EXIT. SEND-MAP SECTION. SM010. | G52: Procedural (sem decisão nem tratamento de falha) | I52: Manter descartado
A53: BNK1TFN-030 | B53: BNK1TFN | C53: 691 | D53: 693-740 | E53: Get supplemental information | F53: EXEC CICS ASSIGN APPLID(ABND-APPLID) END-EXEC MOVE EIBTASKN TO ABND-TASKNO-KEY MOVE EIBTRNID TO ABND-TRANID PERFORM POPULATE-TIME-DATE MOVE WS-ORIG-DATE TO ABND-DATE STRING WS-TIME-NOW-GRP-HH DELIMITED BY SIZE, ':' DELIMITED BY SIZE, WS-TIME-NOW-GRP-MM DELIMITED BY SIZE, ':' DELIMITED BY SIZE, WS-TIME-NOW-GRP-MM DELIMITED BY SIZE INTO ABND-TIME END-STRING MOVE WS-U-TIME TO ABND-UTIME-KEY MOVE 'HBNK' TO ABND-CODE EXEC CICS ASSIGN PROGRAM(ABND-PROGRAM) END-EXEC MOVE ZEROS TO ABND-SQLCODE STRING 'SM010 - SEND MAP ERASE FAIL.' DELIMITED BY SIZE, ' EIBRESP=' DELIMITED BY SIZE, ABND-RESPCODE DELIMITED BY SIZE, ' RESP2=' DELIMITED BY SIZE, ABND-RESP2CODE DELIMITED BY SIZE INTO ABND-FREEFORM END-STRING EXEC CICS LINK PROGRAM(WS-ABEND-PGM) COMMAREA(ABNDINFO-REC) END-EXEC INITIALIZE WS-FAIL-INFO MOVE 'BNK1TFN - SM010 - SEND MAP ERASE FAIL ' TO WS-CICS-FAIL-MSG MOVE WS-CICS-RESP TO WS-CICS-RESP-DISP MOVE WS-CICS-RESP2 TO WS-CICS-RESP2-DISP PERFORM ABEND-THIS-TASK END-IF GO TO SM999 END-IF. | G53: Procedural (sem decisão nem tratamento de falha) | H53: comentário curto; comentário delega lógica (PERFORM); contém GO TO (desvio incondicional) | I53: Manter descartado
A54: BNK1TFN-033 | B54: BNK1TFN | C54: 765 | D54: 767-814 | E54: Get supplemental information | F54: EXEC CICS ASSIGN APPLID(ABND-APPLID) END-EXEC MOVE EIBTASKN TO ABND-TASKNO-KEY MOVE EIBTRNID TO ABND-TRANID PERFORM POPULATE-TIME-DATE MOVE WS-ORIG-DATE TO ABND-DATE STRING WS-TIME-NOW-GRP-HH DELIMITED BY SIZE, ':' DELIMITED BY SIZE, WS-TIME-NOW-GRP-MM DELIMITED BY SIZE, ':' DELIMITED BY SIZE, WS-TIME-NOW-GRP-MM DELIMITED BY SIZE INTO ABND-TIME END-STRING MOVE WS-U-TIME TO ABND-UTIME-KEY MOVE 'HBNK' TO ABND-CODE EXEC CICS ASSIGN PROGRAM(ABND-PROGRAM) END-EXEC MOVE ZEROS TO ABND-SQLCODE STRING 'SM010 - SEND MAP DATAONLY FAIL.' DELIMITED BY SIZE, ' EIBRESP=' DELIMITED BY SIZE, ABND-RESPCODE DELIMITED BY SIZE, ' RESP2=' DELIMITED BY SIZE, ABND-RESP2CODE DELIMITED BY SIZE INTO ABND-FREEFORM END-STRING EXEC CICS LINK PROGRAM(WS-ABEND-PGM) COMMAREA(ABNDINFO-REC) END-EXEC INITIALIZE WS-FAIL-INFO MOVE 'BNK1TFN - SM010 - SEND MAP DATAONLY FAIL ' TO WS-CICS-FAIL-MSG MOVE WS-CICS-RESP TO WS-CICS-RESP-DISP MOVE WS-CICS-RESP2 TO WS-CICS-RESP2-DISP PERFORM ABEND-THIS-TASK END-IF GO TO SM999 END-IF. | G54: Procedural (sem decisão nem tratamento de falha) | H54: comentário curto; comentário delega lógica (PERFORM); contém GO TO (desvio incondicional) | I54: Manter descartado
A55: BNK1TFN-036 | B55: BNK1TFN | C55: 840 | D55: 842-895 | E55: Get supplemental information | F55: EXEC CICS ASSIGN APPLID(ABND-APPLID) END-EXEC MOVE EIBTASKN TO ABND-TASKNO-KEY MOVE EIBTRNID TO ABND-TRANID PERFORM POPULATE-TIME-DATE MOVE WS-ORIG-DATE TO ABND-DATE STRING WS-TIME-NOW-GRP-HH DELIMITED BY SIZE, ':' DELIMITED BY SIZE, WS-TIME-NOW-GRP-MM DELIMITED BY SIZE, ':' DELIMITED BY SIZE, WS-TIME-NOW-GRP-MM DELIMITED BY SIZE INTO ABND-TIME END-STRING MOVE WS-U-TIME TO ABND-UTIME-KEY MOVE 'HBNK' TO ABND-CODE EXEC CICS ASSIGN PROGRAM(ABND-PROGRAM) END-EXEC MOVE ZEROS TO ABND-SQLCODE STRING 'SM010 - SEND MAP DATAONLY ALARM FAIL.' DELIMITED BY SIZE, ' EIBRESP=' DELIMITED BY SIZE, ABND-RESPCODE DELIMITED BY SIZE, ' RESP2=' DELIMITED BY SIZE, ABND-RESP2CODE DELIMITED BY SIZE INTO ABND-FREEFORM END-STRING EXEC CICS LINK PROGRAM(WS-ABEND-PGM) COMMAREA(ABNDINFO-REC) END-EXEC INITIALIZE WS-FAIL-INFO MOVE 'BNK1TFN - SM010 - SEND MAP DATAONLY ALARM FAIL ' TO WS-CICS-FAIL-MSG MOVE WS-CICS-RESP TO WS-CICS-RESP-DISP MOVE WS-CICS-RESP2 TO WS-CICS-RESP2-DISP PERFORM ABEND-THIS-TASK END-IF END-IF. SM999. EXIT. SEND-TERMINATION-MSG SECTION. STM010. | G55: Procedural (sem decisão nem tratamento de falha) | H55: comentário curto; comentário delega lógica (PERFORM) | I55: Manter descartado
A56: BNK1TFN-039 | B56: BNK1TFN | C56: 918 | D56: 920-971 | E56: Get supplemental information | F56: EXEC CICS ASSIGN APPLID(ABND-APPLID) END-EXEC MOVE EIBTASKN TO ABND-TASKNO-KEY MOVE EIBTRNID TO ABND-TRANID PERFORM POPULATE-TIME-DATE MOVE WS-ORIG-DATE TO ABND-DATE STRING WS-TIME-NOW-GRP-HH DELIMITED BY SIZE, ':' DELIMITED BY SIZE, WS-TIME-NOW-GRP-MM DELIMITED BY SIZE, ':' DELIMITED BY SIZE, WS-TIME-NOW-GRP-MM DELIMITED BY SIZE INTO ABND-TIME END-STRING MOVE WS-U-TIME TO ABND-UTIME-KEY MOVE 'HBNK' TO ABND-CODE EXEC CICS ASSIGN PROGRAM(ABND-PROGRAM) END-EXEC MOVE ZEROS TO ABND-SQLCODE STRING 'STM010 - SEND TEXT FAIL.' DELIMITED BY SIZE, ' EIBRESP=' DELIMITED BY SIZE, ABND-RESPCODE DELIMITED BY SIZE, ' RESP2=' DELIMITED BY SIZE, ABND-RESP2CODE DELIMITED BY SIZE INTO ABND-FREEFORM END-STRING EXEC CICS LINK PROGRAM(WS-ABEND-PGM) COMMAREA(ABNDINFO-REC) END-EXEC INITIALIZE WS-FAIL-INFO MOVE 'BNK1TFN - STM010 - SEND TEXT FAIL' TO WS-CICS-FAIL-MSG MOVE WS-CICS-RESP TO WS-CICS-RESP-DISP MOVE WS-CICS-RESP2 TO WS-CICS-RESP2-DISP PERFORM ABEND-THIS-TASK END-IF. STM999. EXIT. ABEND-THIS-TASK SECTION. ATT010. | G56: Procedural (sem decisão nem tratamento de falha) | H56: comentário curto; comentário delega lógica (PERFORM) | I56: Manter descartado
A57: BNK1TFN-049 | B57: BNK1TFN | C57: 1210 | D57: 1212-1224 | E57: Fomate the date and time | F57: EXEC CICS ASKTIME ABSTIME(WS-U-TIME) END-EXEC. EXEC CICS FORMATTIME ABSTIME(WS-U-TIME) DDMMYYYY(WS-ORIG-DATE) TIME(WS-TIME-NOW) DATESEP END-EXEC. PTD999. EXIT. | G57: Procedural (sem decisão nem tratamento de falha) | I57: Manter descartado
