Workbook

Sheet Legenda
A1: Gabarito (ground-truth): pares candidatos de comentário e código
A3: Origem | B3: Programas da CBSA na pasta ORIGINAL do repositório da base de dados (commit e22475691524ef72a92ee77f7040233e098ab1b9, ijmitch/cics-banking-sample-application-cbsa). Números de linha referem-se aos arquivos do ORIGINAL.
A4: Como foi gerado | B4: Extração automática (script extrair_pares_gabarito.py). Cada bloco de comentário da PROCEDURE DIVISION é pareado ao código que o segue, até o próximo comentário (limite de 30 linhas por trecho).
A5: Filtro (E4, seção 1.3) | B5: Retido: trecho com IF, EVALUATE ou WHEN, ou com tratamento de falha (ABEND, SQLCODE, HANDLE, DFHRESP, EIBRESP, EIBRCODE). Os demais ficam na aba Descartados, para que o critério seja auditável.
A6: O que preencher | B6: Aba Candidatos, colunas J a M (fundo amarelo): Revisão discente, Revisão orientador, Regra atômica (redação final) e Observações. Na aba Descartados, coluna I.
A7: Valores da revisão | B7: Manter, Descartar ou Ajustar (lista suspensa). Em Descartados: Manter descartado ou Reincluir.
A8: Alertas | B8: possível código desativado: o comentário parece uma instrução COBOL comentada. comentário curto: até 3 palavras. trecho truncado: o código do par passa do limite de linhas; conferir o restante no fonte. comentários adjacentes fundidos: o bloco seguinte de comentário foi unido porque o trecho entre eles não tinha código ativo. comentário menciona condição (aba Descartados): o comentário descreve uma condição, mas o trecho seguinte é só ação; a decisão pode estar antes no fonte.
A9: Limitações | B9: A triagem é heurística e não substitui a revisão dupla. Comentários de cabeçalho (antes da PROCEDURE DIVISION) não entram. Linhas de depuração (indicador D) aparecem com o prefixo [D]. O tipo (Decisão, Falha, Decisão e falha) é atribuído ao trecho inteiro, não ao comentário isolado.
A11: Exemplo de regra atômica | B11: Ilustrativo, não faz parte do gabarito: "Se o valor solicitado for um débito e o saldo disponível for insuficiente, a solicitação é negada." (uma condição e uma consequência por regra)

Sheet Resumo
A1: Programa | B1: Blocos com texto | C1: Candidatos retidos | D1: Descartados | E1: Decisão | F1: Falha | G1: Decisão e falha | H1: Com alertas | I1: Manter (discente) | J1: Descartar (discente) | K1: Ajustar (discente) | L1: Pendentes (discente)
A2: DBCRFUN | B2: =C2+D2 -> 33 | C2: =COUNTIF(Candidatos!$B:$B,$A2) -> 18 | D2: =COUNTIF(Descartados!$B:$B,$A2) -> 15 | E2: =COUNTIFS(Candidatos!$B:$B,$A2,Candidatos!$G:$G,"Decisão") -> 7 | F2: =COUNTIFS(Candidatos!$B:$B,$A2,Candidatos!$G:$G,"Falha") -> 4 | G2: =COUNTIFS(Candidatos!$B:$B,$A2,Candidatos!$G:$G,"Decisão e falha") -> 7 | H2: =COUNTIFS(Candidatos!$B:$B,$A2,Candidatos!$I:$I,"<>") -> 3 | I2: =COUNTIFS(Candidatos!$B:$B,$A2,Candidatos!$J:$J,"Manter") -> 0 | J2: =COUNTIFS(Candidatos!$B:$B,$A2,Candidatos!$J:$J,"Descartar") -> 0 | K2: =COUNTIFS(Candidatos!$B:$B,$A2,Candidatos!$J:$J,"Ajustar") -> 0 | L2: =C2-I2-J2-K2 -> 18
A3: XFRFUN | B3: =C3+D3 -> 70 | C3: =COUNTIF(Candidatos!$B:$B,$A3) -> 39 | D3: =COUNTIF(Descartados!$B:$B,$A3) -> 31 | E3: =COUNTIFS(Candidatos!$B:$B,$A3,Candidatos!$G:$G,"Decisão") -> 10 | F3: =COUNTIFS(Candidatos!$B:$B,$A3,Candidatos!$G:$G,"Falha") -> 16 | G3: =COUNTIFS(Candidatos!$B:$B,$A3,Candidatos!$G:$G,"Decisão e falha") -> 13 | H3: =COUNTIFS(Candidatos!$B:$B,$A3,Candidatos!$I:$I,"<>") -> 4 | I3: =COUNTIFS(Candidatos!$B:$B,$A3,Candidatos!$J:$J,"Manter") -> 0 | J3: =COUNTIFS(Candidatos!$B:$B,$A3,Candidatos!$J:$J,"Descartar") -> 0 | K3: =COUNTIFS(Candidatos!$B:$B,$A3,Candidatos!$J:$J,"Ajustar") -> 0 | L3: =C3-I3-J3-K3 -> 39
A4: BNK1CRA | B4: =C4+D4 -> 43 | C4: =COUNTIF(Candidatos!$B:$B,$A4) -> 30 | D4: =COUNTIF(Descartados!$B:$B,$A4) -> 13 | E4: =COUNTIFS(Candidatos!$B:$B,$A4,Candidatos!$G:$G,"Decisão") -> 16 | F4: =COUNTIFS(Candidatos!$B:$B,$A4,Candidatos!$G:$G,"Falha") -> 7 | G4: =COUNTIFS(Candidatos!$B:$B,$A4,Candidatos!$G:$G,"Decisão e falha") -> 7 | H4: =COUNTIFS(Candidatos!$B:$B,$A4,Candidatos!$I:$I,"<>") -> 4 | I4: =COUNTIFS(Candidatos!$B:$B,$A4,Candidatos!$J:$J,"Manter") -> 0 | J4: =COUNTIFS(Candidatos!$B:$B,$A4,Candidatos!$J:$J,"Descartar") -> 0 | K4: =COUNTIFS(Candidatos!$B:$B,$A4,Candidatos!$J:$J,"Ajustar") -> 0 | L4: =C4-I4-J4-K4 -> 30
A5: BNK1TFN | B5: =C5+D5 -> 49 | C5: =COUNTIF(Candidatos!$B:$B,$A5) -> 33 | D5: =COUNTIF(Descartados!$B:$B,$A5) -> 16 | E5: =COUNTIFS(Candidatos!$B:$B,$A5,Candidatos!$G:$G,"Decisão") -> 18 | F5: =COUNTIFS(Candidatos!$B:$B,$A5,Candidatos!$G:$G,"Falha") -> 8 | G5: =COUNTIFS(Candidatos!$B:$B,$A5,Candidatos!$G:$G,"Decisão e falha") -> 7 | H5: =COUNTIFS(Candidatos!$B:$B,$A5,Candidatos!$I:$I,"<>") -> 5 | I5: =COUNTIFS(Candidatos!$B:$B,$A5,Candidatos!$J:$J,"Manter") -> 0 | J5: =COUNTIFS(Candidatos!$B:$B,$A5,Candidatos!$J:$J,"Descartar") -> 0 | K5: =COUNTIFS(Candidatos!$B:$B,$A5,Candidatos!$J:$J,"Ajustar") -> 0 | L5: =C5-I5-J5-K5 -> 33
A6: TOTAL | B6: =SUM(B2:B5) -> 195 | C6: =SUM(C2:C5) -> 120 | D6: =SUM(D2:D5) -> 75 | E6: =SUM(E2:E5) -> 51 | F6: =SUM(F2:F5) -> 35 | G6: =SUM(G2:G5) -> 34 | H6: =SUM(H2:H5) -> 16 | I6: =SUM(I2:I5) -> 0 | ... L6: =SUM(L2:L5) -> 120
A8: Contagens por fórmula: atualizam conforme a revisão é preenchida na aba Candidatos.

Sheet Candidatos
A1: ID | B1: Programa | C1: Linhas do comentário | D1: Linhas do código | E1: Comentário | F1: Trecho de código | G1: Tipo | H1: Estruturas | I1: Alertas | J1: Revisão discente | K1: Revisão orientador | L1: Regra atômica (redação final) | M1: Observações
A2: DBCRFUN-001 | B2: DBCRFUN | C2: 205 | D2: 207-212 | E2: Set up some Abend handling | F2: EXEC CICS HANDLE ABEND LABEL(ABEND-HANDLING) END-EXEC. MOVE SORTCODE TO COMM-SORTC. MOVE SORTCODE TO DESIRED-SORT-CODE. | G2: Falha | H2: falha
A3: DBCRFUN-005 | B3: DBCRFUN | C3: 276-277 | D3: 279-287 | E3: Check that select was successful. If it wasn't then deal with it | F3: IF SQLCODE NOT = 0 MOVE 'N' TO COMM-SUCCESS IF SQLCODE = +100 MOVE '1' TO COMM-FAIL-CODE ELSE MOVE '2' TO COMM-FAIL-CODE END-IF | G3: Decisão e falha | H3: IF, falha
A4: DBCRFUN-007 | B4: DBCRFUN | C4: 301-304 | D4: 307 | E4: Is the amount being requested a debit or a credit? If it is a CREDIT (+) then we don't need to ensure that the available balance has sufficient funds, because this is money coming in. | F4: IF COMM-AMT < 0 | G4: Decisão | H4: IF
A5: DBCRFUN-008 | B5: DBCRFUN | C5: 309-328 | D5: 316-352 | E5: The amount being requested is a DEBIT/Payment (-) so we do need to check that the available balance is sufficient to cover the amount being asked for. If there are NOT sufficient funds the request is denied so remove the record LOCK and and finish. Check to see whether the Payment is being requested from a MORTGAGE or LOAN account. We only make this check for PAYMENTs (we don't make this check for requests via the Teller). How do we know it is a PAYMENT as opposed to a Teller, this is determined by the COMM-FACILTYPE(496 = NONE) If it is a PAYMENT being requested from a MORTGAGE or LOAN account then set an appropriate fail code (4) and finish up. | F5: [D] DISPLAY 'COMM-AMT IS negative' IF (HV-ACCOUNT-ACC-TYPE = 'MORTGAGE' AND COMM-FACILTYPE = 496) OR (HV-ACCOUNT-ACC-TYPE = 'LOAN ' AND COMM-FACILTYPE = 496) MOVE 'N' TO COMM-SUCCESS MOVE '4' TO COMM-FAIL-CODE GO TO UAD999 END-IF MOVE 0 TO WS-DIFFERENCE COMPUTE WS-DIFFERENCE = HV-ACCOUNT-AVAIL-BAL + COMM-AMT IF WS-DIFFERENCE < 0 AND COMM-FACILTYPE = 496 [D] DISPLAY 'insufficient funds!' MOVE 'N' TO COMM-SUCCESS MOVE '3' TO COMM-FAIL-CODE GO TO UAD999 END-IF END-IF. | G5: Decisão | H5: IF | I5: comentários adjacentes fundidos
A6: DBCRFUN-009 | B6: DBCRFUN | C6: 356-366 | D6: 368-376 | E6: Check to see whether a Credit is being requested from a MORTGAGE or LOAN account. We only make this check for requests via the PAYMENT link (we don't make this check for requests via the Teller). How do we know it is a PAYMENT as opposed to a Teller, this is determined by the COMM-FACILTYPE(496 = NONE) If it is a PAYMENT credit being requested from a MORTGAGE or LOAN account then set an appropriate fail code (4), remove the record lock and finish up. | F6: IF (HV-ACCOUNT-ACC-TYPE = 'MORTGAGE' AND COMM-FACILTYPE = 496) OR (HV-ACCOUNT-ACC-TYPE = 'LOAN ' AND COMM-FACILTYPE = 496) MOVE 'N' TO COMM-SUCCESS MOVE '4' TO COMM-FAIL-CODE GO TO UAD999 END-IF. | G6: Decisão | H6: IF
A7: DBCRFUN-012 | B7: DBCRFUN | C7: 411-412 | D7: 414-419 | E7: If the rewrite was successful then we need to pass back the amended available balance and actual balance. | F7: MOVE SQLCODE TO SQLCODE-DISPLAY. MOVE HV-ACCOUNT-AVAIL-BAL TO COMM-AV-BAL. MOVE HV-ACCOUNT-ACTUAL-BAL TO COMM-ACT-BAL. | G7: Falha | H7: falha
A8: DBCRFUN-013 | B8: DBCRFUN | C8: 422-423 | D8: 425-427 | E8: If the RESP CODE was NOT OK then we need to set flags accordingly | F8: IF SQLCODE NOT = 0 MOVE 'N' TO COMM-SUCCESS MOVE '2' TO COMM-FAIL-CODE | G8: Decisão e falha | H8: IF, falha
A9: DBCRFUN-017 | B9: DBCRFUN | C9: 473 | D9: 475-493 | E9: Populate the current time and date | F9: EXEC CICS ASKTIME ABSTIME(WS-U-TIME) END-EXEC. EXEC CICS FORMATTIME ABSTIME(WS-U-TIME) DDMMYYYY(WS-ORIG-DATE) TIME(HV-PROCTRAN-TIME) DATESEP('.') END-EXEC. MOVE WS-ORIG-DATE TO WS-ORIG-DATE-GRP-X. MOVE WS-ORIG-DATE-GRP-X TO HV-PROCTRAN-DATE. MOVE SPACES TO HV-PROCTRAN-DESC. IF COMM-AMT < 0 MOVE 'DEB' TO HV-PROCTRAN-TYPE MOVE 'COUNTER WTHDRW' TO HV-PROCTRAN-DESC | G9: Decisão | H9: IF
A10: DBCRFUN-018 | B10: DBCRFUN | C10: 496 | D10: 498-506 | E10: If it is a debit from a PAYMENT | F10: IF COMM-FACILTYPE = 496 MOVE 'PDR' TO HV-PROCTRAN-TYPE MOVE COMM-ORIGIN(1:14) TO HV-PROCTRAN-DESC END-IF ELSE MOVE 'CRE' TO HV-PROCTRAN-TYPE MOVE 'COUNTER RECVED' TO HV-PROCTRAN-DESC | G10: Decisão | H10: IF
A11: DBCRFUN-019 | B11: DBCRFUN | C11: 509 | D11: 511-519 | E11: If it is a credit from a PAYMENT | F11: IF COMM-FACILTYPE = 496 MOVE 'PCR' TO HV-PROCTRAN-TYPE MOVE COMM-ORIGIN(1:14) TO HV-PROCTRAN-DESC END-IF END-IF. MOVE COMM-AMT TO HV-PROCTRAN-AMOUNT. | G11: Decisão | H11: IF
A12: DBCRFUN-021 | B12: DBCRFUN | C12: 552 | D12: 554-559 | E12: Check the SQLCODE | F12: IF SQLCODE NOT = 0 MOVE SQLCODE TO SQLCODE-DISPLAY DISPLAY 'UNABLE TO WRITE TO PROCTRAN DB2 DATASTORE' ' SQLCODE=' SQLCODE-DISPLAY 'WITH THE FOLLOWING DATA:' HOST-PROCTRAN-ROW | G12: Decisão e falha | H12: IF, falha | I12: comentário curto
A13: DBCRFUN-022 | B13: DBCRFUN | C13: 561-562 | D13: 564-569 | E13: You need to issue a ROLLBACK to get rid of the updated ACCOUNT record | F13: EXEC CICS SYNCPOINT ROLLBACK RESP(WS-CICS-RESP) RESP2(WS-CICS-RESP2) END-EXEC IF WS-CICS-RESP NOT = DFHRESP(NORMAL) | G13: Decisão e falha | H13: IF, falha
A14: DBCRFUN-023 | B14: DBCRFUN | C14: 571-574 | D14: 576-578 | E14: Preserve the RESP and RESP2, then set up the standard ABEND info before getting the applid, date/time etc. and linking to the Abend Handler program. | F14: INITIALIZE ABNDINFO-REC MOVE EIBRESP TO ABND-RESPCODE MOVE EIBRESP2 TO ABND-RESP2CODE | G14: Falha | H14: falha
A15: DBCRFUN-027 | B15: DBCRFUN | C15: 671-672 | D15: 675-695 | E15: Check if the Sqclode that is returned one that will trigger Storm Drain is active in Workload | F15: EVALUATE SQLCODE WHEN 923 MOVE 'DB2 Connection lost ' TO STORM-DRAIN-CONDITION WHEN OTHER MOVE 'Not Storm Drain ' TO STORM-DRAIN-CONDITION END-EVALUATE. IF STORM-DRAIN-CONDITION NOT EQUAL 'Not Storm Drain ' DISPLAY 'DBCRFUN: Check-For-Storm-Drain-DB2: Storm ' 'Drain condition (' STORM-DRAIN-CONDITION ') ' 'has been met (' SQLCODE-DISPLAY ').' ELSE CONTINUE END-IF. CFSDD999. EXIT. | G15: Decisão e falha | H15: IF, EVALUATE, WHEN, falha
A16: DBCRFUN-029 | B16: DBCRFUN | C16: 708-713 | D16: 716 | E16: Evaluate the Abend code that is returned - For DB2 AD2Z ... provide some diagnostics - For VSAM RLS abends: AFCR, AFCS and AFCT record the Abend as happening but do not abend ... leave this to CPSM WLM "Storm drain" (Abend probability) to handle If not a "storm drain" ... take the abend afterwards | F16: EVALUATE MY-ABEND-CODE | G16: Decisão | H16: EVALUATE
A17: DBCRFUN-030 | B17: DBCRFUN | C17: 718 | D17: 720-735 | E17: DB2 AD2Z abend | F17: WHEN 'AD2Z' MOVE SQLCODE TO SQLCODE-DISPLAY DISPLAY 'DB2 DEADLOCK DETECTED IN DBCRFUN, SQLCODE=' SQLCODE-DISPLAY DISPLAY 'DB2 DEADLOCK FOR ACCOUNT ' HV-ACCOUNT-ACC-NO DISPLAY 'SQLSTATE=' SQLSTATE ',SQLERRMC=' SQLERRMC(1:SQLERRML) ',SQLERRD(1)=' SQLERRD(1) ',SQLERRD(2)=' SQLERRD(2) ',SQLERRD(3)=' SQLERRD(3) ',SQLERRD(4)=' SQLERRD(4) ',SQLERRD(5)=' SQLERRD(5) ',SQLERRD(6)=' SQLERRD(6) | G17: Decisão e falha | H17: WHEN, falha | I17: comentário curto
A18: DBCRFUN-031 | B18: DBCRFUN | C18: 738-740 | D18: 742-756 | E18: VSAM RLS abends, subject to CPSM WLM Storm Drain check if handled (as here) and Workload Abend Thresholds are set. | F18: WHEN 'AFCR' WHEN 'AFCS' WHEN 'AFCT' MOVE 'Y' TO WS-STORM-DRAIN DISPLAY 'DBCRFUN: Check-For-Storm-Drain-VSAM: Storm ' 'Drain condition (Abend ' MY-ABEND-CODE ') ' 'has been met.' EXEC CICS SYNCPOINT ROLLBACK RESP(WS-CICS-RESP) RESP2(WS-CICS-RESP2) END-EXEC IF WS-CICS-RESP NOT = DFHRESP(NORMAL) | G18: Decisão e falha | H18: IF, WHEN, falha
A19: DBCRFUN-032 | B19: DBCRFUN | C19: 758-761 | D19: 763-765 | E19: Preserve the RESP and RESP2, then set up the standard ABEND info before getting the applid, date/time etc. and linking to the Abend Handler program. | F19: INITIALIZE ABNDINFO-REC MOVE EIBRESP TO ABND-RESPCODE MOVE EIBRESP2 TO ABND-RESP2CODE | G19: Falha | H19: falha
A20: XFRFUN-001 | B20: XFRFUN | C20: 286-287 | D20: 289-296 | E20: If the amount being transferred is negative, then flag this as a failure and finish. | F20: IF COMM-AMT <= ZERO MOVE 'N' TO COMM-SUCCESS MOVE '4' TO COMM-FAIL-CODE PERFORM GET-ME-OUT-OF-HERE END-IF. PERFORM UPDATE-ACCOUNT-DB2 | G20: Decisão | H20: IF
A21: XFRFUN-003 | B21: XFRFUN | C21: 313-314 | D21: 316-317 | E21: Are we trying to transfer from and to the same account? We don't allow that. | F21: IF COMM-FACCNO = COMM-TACCNO AND COMM-FSCODE = COMM-TSCODE | G21: Decisão | H21: IF
A22: XFRFUN-004 | B22: XFRFUN | C22: 319-322 | D22: 324-326 | E22: Preserve the RESP and RESP2, then set up the standard ABEND info before getting the applid, date/time etc. and linking to the Abend Handler program. | F22: INITIALIZE ABNDINFO-REC MOVE EIBRESP TO ABND-RESPCODE MOVE EIBRESP2 TO ABND-RESP2CODE | G22: Falha | H22: falha
A23: XFRFUN-008 | B23: XFRFUN | C23: 392 | D23: 394-398 | E23: If the update was successful, update the TO account | F23: IF COMM-SUCCESS = 'Y' MOVE COMM-TACCNO TO DESIRED-ACC-NO MOVE COMM-TSCODE TO DESIRED-SORT-CODE PERFORM UPDATE-ACCOUNT-DB2-TO | G23: Decisão | H23: IF
A24: XFRFUN-009 | B24: XFRFUN | C24: 401-402 | D24: 404-413 | E24: If the update to the TO account was unsuccessful then we need to flag it and roll it back | F24: IF COMM-SUCCESS = 'N' IF COMM-FAIL-CODE = '2' EXEC CICS SYNCPOINT ROLLBACK RESP(WS-CICS-RESP) RESP2(WS-CICS-RESP2) END-EXEC IF WS-CICS-RESP IS NOT EQUAL TO DFHRESP(NORMAL) | G24: Decisão e falha | H24: IF, falha
A25: XFRFUN-010 | B25: XFRFUN | C25: 415-418 | D25: 420-422 | E25: Preserve the RESP and RESP2, then set up the standard ABEND info before getting the applid, date/time etc. and linking to the Abend Handler program. | F25: INITIALIZE ABNDINFO-REC MOVE EIBRESP TO ABND-RESPCODE MOVE EIBRESP2 TO ABND-RESP2CODE | G25: Falha | H25: falha
A26: XFRFUN-012 | B26: XFRFUN | C26: 483-484 | D26: 486-496 | E26: If the COMM-FLAG is anything else other than 2 then abend. | F26: DISPLAY 'Error updating TO account' EXEC CICS ABEND ABCODE('TO ') NODUMP END-EXEC END-IF END-IF ELSE | G26: Falha | H26: falha
A27: XFRFUN-013 | B27: XFRFUN | C27: 498-499 | D27: 501-507 | E27: If the update to the FROM account was not successful rollback. | F27: IF COMM-FAIL-CODE = '1' EXEC CICS SYNCPOINT ROLLBACK RESP(WS-CICS-RESP) RESP2(WS-CICS-RESP2) END-EXEC | G27: Decisão | H27: IF
A28: XFRFUN-014 | B28: XFRFUN | C28: 510 | D28: 512-526 | E28: If the ROLLback failed | F28: IF WS-CICS-RESP IS NOT EQUAL TO DFHRESP(NORMAL) DISPLAY 'XFRFUN error syncpoint ' ' rollback after ' 'updating FROM account ' ',RESP=' WS-CICS-RESP ',RESP2=' WS-CICS-RESP2 EXEC CICS ABEND ABCODE('HROL') NODUMP END-EXEC END-IF GO TO UAD999 ELSE | G28: Decisão e falha | H28: IF, falha
A29: XFRFUN-015 | B29: XFRFUN | C29: 528-531 | D29: 533-535 | E29: Preserve the RESP and RESP2, then set up the standard ABEND info before getting the applid, date/time etc. and linking to the Abend Handler program. | F29: INITIALIZE ABNDINFO-REC MOVE EIBRESP TO ABND-RESPCODE MOVE EIBRESP2 TO ABND-RESP2CODE | G29: Falha | H29: falha
... A45: XFRFUN-049 | B45: XFRFUN | C45: 1293-1296 | D45: 1298-1300 | E45: Preserve the RESP and RESP2, then set up the standard ABEND info before getting the applid, date/time etc. and linking to the Abend Handler program. | F45: INITIALIZE ABNDINFO-REC MOVE EIBRESP TO ABND-RESPCODE MOVE EIBRESP2 TO ABND-RESP2CODE | G45: Falha | H45: falha
A46: XFRFUN-050 | B46: XFRFUN | C46: 1302 | D46: 1304-1342 | E46: Get supplemental information | F46: EXEC CICS ASSIGN APPLID(ABND-APPLID) END-EXEC MOVE EIBTASKN TO ABND-TASKNO-KEY MOVE EIBTRNID TO ABND-TRANID PERFORM POPULATE-TIME-DATE MOVE WS-ORIG-DATE TO ABND-DATE STRING WS-TIME-NOW-GRP-HH DELIMITED BY SIZE, ':' DELIMITED BY SIZE, WS-TIME-NOW-GRP-MM DELIMITED BY SIZE, ':' DELIMITED BY SIZE, WS-TIME-NOW-GRP-MM DELIMITED BY SIZE INTO ABND-TIME END-STRING MOVE WS-U-TIME TO ABND-UTIME-KEY MOVE 'RUF2' TO ABND-CODE EXEC CICS ASSIGN PROGRAM(ABND-PROGRAM) END-EXEC MOVE ZEROS TO ABND-SQLCODE IF SQLERRD(3) = 13172894 STRING 'UAD010-TO(3) - timeout detected ' DELIMITED BY SIZE, ' EIBRESP=' DELIMITED BY SIZE, ABND-RESPCODE DELIMITED BY SIZE, 'RESP2=' DELIMITED BY SIZE, ABND-RESP2CODE DELIMITED BY SIZE INTO ABND-FREEFORM END-STRING END-IF EXEC CICS LINK PROGRAM(WS-ABEND-PGM) COMMAREA(ABNDINFO-REC) | G46: Decisão | H46: IF | I46: comentário curto; trecho truncado (30 linhas)
A47: XFRFUN-052 | B47: XFRFUN | C47: 1382 | D47: 1384-1389 | E47: If the RESP CODE was NOT OK then we need to abend | F47: IF SQLCODE NOT = 0 MOVE SQLCODE TO SQLCODE-DISPLAY DISPLAY 'UNABLE TO UPDATE TO ACCOUNT.' HV-ACCOUNT-SORTCODE HV-ACCOUNT-ACC-NO 'THE SQLCODE=' SQLCODE-DISPLAY ' SQLERRD(3) ' SQLERRD(3) | G47: Decisão e falha | H47: IF, falha
A48: XFRFUN-053 | B48: XFRFUN | C48: 1392-1393 | D48: 1395-1409 | E48: Check if SQLCODE indicates that Storm Drain processing is applicable in a workload if activated | F48: PERFORM CHECK-FOR-STORM-DRAIN-DB2 IF SQLCODE = -911 IF SQLERRD(3) = 13172872 DISPLAY 'DEADLOCK DETECTED!' ADD 1 TO DB2-DEADLOCK-RETRY IF DB2-DEADLOCK-RETRY < 6 EXEC CICS SYNCPOINT ROLLBACK RESP(WS-CICS-RESP) RESP2(WS-CICS-RESP2) END-EXEC IF WS-CICS-RESP IS NOT EQUAL TO DFHRESP(NORMAL) | G48: Decisão e falha | H48: IF, falha
A49: XFRFUN-054 | B49: XFRFUN | C49: 1412-1415 | D49: 1417-1419 | E49: Preserve the RESP and RESP2, then set up the standard ABEND info before getting the applid, date/time etc. and linking to the Abend Handler program. | F49: INITIALIZE ABNDINFO-REC MOVE EIBRESP TO ABND-RESPCODE MOVE EIBRESP2 TO ABND-RESP2CODE | G49: Falha | H49: falha
A50: XFRFUN-056 | B50: XFRFUN | C50: 1493-1496 | D50: 1498-1500 | E50: Preserve the RESP and RESP2, then set up the standard ABEND info before getting the applid, date/time etc. and linking to the Abend Handler program. | F50: INITIALIZE ABNDINFO-REC MOVE EIBRESP TO ABND-RESPCODE MOVE EIBRESP2 TO ABND-RESP2CODE | G50: Falha | H50: falha
A51: XFRFUN-057 | B51: XFRFUN | C51: 1502 | D51: 1504-1542 | E51: Get supplemental information | F51: EXEC CICS ASSIGN APPLID(ABND-APPLID) END-EXEC MOVE EIBTASKN TO ABND-TASKNO-KEY MOVE EIBTRNID TO ABND-TRANID PERFORM POPULATE-TIME-DATE MOVE WS-ORIG-DATE TO ABND-DATE STRING WS-TIME-NOW-GRP-HH DELIMITED BY SIZE, ':' DELIMITED BY SIZE, WS-TIME-NOW-GRP-MM DELIMITED BY SIZE, ':' DELIMITED BY SIZE, WS-TIME-NOW-GRP-MM DELIMITED BY SIZE INTO ABND-TIME END-STRING MOVE WS-U-TIME TO ABND-UTIME-KEY MOVE 'RUF2' TO ABND-CODE EXEC CICS ASSIGN PROGRAM(ABND-PROGRAM) END-EXEC MOVE ZEROS TO ABND-SQLCODE IF SQLERRD(3) = 13172872 STRING 'UAD010-TO(5) - timeout detected ' DELIMITED BY SIZE, ' EIBRESP=' DELIMITED BY SIZE, ABND-RESPCODE DELIMITED BY SIZE, ' RESP2=' DELIMITED BY SIZE, ABND-RESP2CODE DELIMITED BY SIZE INTO ABND-FREEFORM END-STRING END-IF EXEC CICS LINK PROGRAM(WS-ABEND-PGM) COMMAREA(ABNDINFO-REC) | G51: Decisão | H51: IF | I51: comentário curto; trecho truncado (30 linhas)
A52: XFRFUN-061 | B52: XFRFUN | C52: 1644 | D52: 1646-1648 | E52: Check the SQLCODE | F52: IF SQLCODE NOT = 0 MOVE SQLCODE TO WS-SQLCODE-DISP | G52: Decisão e falha | H52: IF, falha | I52: comentário curto
A53: XFRFUN-062 | B53: XFRFUN | C53: 1650-1653 | D53: 1655-1657 | E53: Preserve the RESP and RESP2, then set up the standard ABEND info before getting the applid, date/time etc. and linking to the Abend Handler program. | F53: INITIALIZE ABNDINFO-REC MOVE EIBRESP TO ABND-RESPCODE MOVE EIBRESP2 TO ABND-RESP2CODE | G53: Falha | H53: falha
A54: XFRFUN-064 | B54: XFRFUN | C54: 1711-1712 | D54: 1714-1738 | E54: Check if SQLCODE indicates that Storm Drain processing is applicable in a workload if activated | F54: PERFORM CHECK-FOR-STORM-DRAIN-DB2 EXEC CICS ABEND ABCODE('WPCD') END-EXEC END-IF. WTPD999. EXIT. GET-ME-OUT-OF-HERE SECTION. GMOOH010. EXEC CICS RETURN END-EXEC. GOBACK. GMOOH999. EXIT. CHECK-FOR-STORM-DRAIN-DB2 SECTION. CFSDD010. | G54: Falha | H54: falha
A55: XFRFUN-065 | B55: XFRFUN | C55: 1741-1742 | D55: 1744-1770 | E55: Check if the Sqlcode that is returned one that will trigger Storm Drain is active in Workload | F55: EVALUATE SQLCODE WHEN 923 MOVE 'DB2 Connection lost ' TO STORM-DRAIN-CONDITION WHEN OTHER MOVE 'Not Storm Drain ' TO STORM-DRAIN-CONDITION END-EVALUATE. IF STORM-DRAIN-CONDITION NOT EQUAL 'Not Storm Drain ' DISPLAY 'XFRFUN: Check-For-Storm-Drain-DB2: Storm ' 'Drain condition (' STORM-DRAIN-CONDITION ') ' 'has been met (' SQLCODE-DISPLAY ').' ELSE CONTINUE END-IF. CFSDD999. EXIT. ABEND-HANDLING SECTION. AH010. | G55: Decisão e falha | H55: IF, EVALUATE, WHEN, falha
A56: XFRFUN-067 | B56: XFRFUN | C56: 1779-1784 | D56: 1786 | E56: Evaluate the Abend code that is returned - For DB2 AD2Z ... provide some diagnostics - For VSAM RLS abends: AFCR, AFCS and AFCT record the Abend as happening but do not abend ... leave this to CPSM WLM "Storm drain" (Abend probability) to handle If not a "storm drain" ... take the abend afterwards | F56: EVALUATE MY-ABEND-CODE | G56: Decisão | H56: EVALUATE
A57: XFRFUN-068 | B57: XFRFUN | C57: 1789 | D57: 1791-1821 | E57: DB2 AD2Z abend | F57: WHEN 'AD2Z' MOVE SQLCODE TO SQLCODE-DISPLAY DISPLAY 'DB2 DEADLOCK DETECTED IN XFRFUN, SQLCODE=' SQLCODE-DISPLAY DISPLAY 'DB2 DEADLOCK FOR ACCOUNT ' HV-ACCOUNT-ACC-NO DISPLAY 'SQLSTATE=' SQLSTATE ',SQLERRMC=' SQLERRMC(1:SQLERRML) ',SQLERRD(1)=' SQLERRD(1) ',SQLERRD(2)=' SQLERRD(2) ',SQLERRD(3)=' SQLERRD(3) ',SQLERRD(4)=' SQLERRD(4) ',SQLERRD(5)=' SQLERRD(5) ',SQLERRD(6)=' SQLERRD(6) WHEN 'AFCR' WHEN 'AFCS' WHEN 'AFCT' MOVE 'Y' TO WS-STORM-DRAIN DISPLAY 'XFRFUN: Check-For-Storm-Drain-VSAM: Storm ' 'Drain condition (Abend ' MY-ABEND-CODE ') ' 'has been met.' EXEC CICS SYNCPOINT ROLLBACK RESP(WS-CICS-RESP) RESP2(WS-CICS-RESP2) END-EXEC IF WS-CICS-RESP NOT = DFHRESP(NORMAL) | G57: Decisão e falha | H57: IF, WHEN, falha | I57: comentário curto
A58: XFRFUN-069 | B58: XFRFUN | C58: 1823-1826 | D58: 1828-1830 | E58: Preserve the RESP and RESP2, then set up the standard ABEND info before getting the applid, date/time etc. and linking to the Abend Handler program. | F58: INITIALIZE ABNDINFO-REC MOVE EIBRESP TO ABND-RESPCODE MOVE EIBRESP2 TO ABND-RESP2CODE | G58: Falha | H58: falha
A59: BNK1CRA-001 | B59: BNK1CRA | C59: 182-183 | D59: 185-189 | E59: Is it the first time through? If so, send the map with erased (empty) data fields. | F59: WHEN EIBCALEN = ZERO MOVE LOW-VALUE TO BNK1CDO MOVE -1 TO ACCNOL SET SEND-ERASE TO TRUE PERFORM SEND-MAP | G59: Decisão | H59: WHEN
A60: BNK1CRA-002 | B60: BNK1CRA | C60: 192 | D60: 194-195 | E60: If a PA key is pressed, just carry on | F60: WHEN EIBAID = DFHPA1 OR DFHPA2 OR DFHPA3 CONTINUE | G60: Decisão | H60: WHEN
A61: BNK1CRA-003 | B61: BNK1CRA | C61: 198 | D61: 200-206 | E61: When Pf3 is pressed, return to the main menu | F61: WHEN EIBAID = DFHPF3 EXEC CICS RETURN TRANSID('OMEN') IMMEDIATE RESP(WS-CICS-RESP) RESP2(WS-CICS-RESP2) END-EXEC | G61: Decisão | H61: WHEN
A62: BNK1CRA-004 | B62: BNK1CRA | C62: 209-210 | D62: 212-217 | E62: If the aid or Pf12 is pressed, then send a termination message. | F62: WHEN EIBAID = DFHAID OR DFHPF12 PERFORM SEND-TERMINATION-MSG EXEC CICS RETURN END-EXEC | G62: Decisão | H62: WHEN
A63: BNK1CRA-005 | B63: BNK1CRA | C63: 220 | D63: 222-229 | E63: When CLEAR is pressed | F63: WHEN EIBAID = DFHCLEAR EXEC CICS SEND CONTROL ERASE FREEKB END-EXEC EXEC CICS RETURN END-EXEC | G63: Decisão | H63: WHEN
A64: BNK1CRA-006 | B64: BNK1CRA | C64: 232 | D64: 234-235 | E64: When enter is pressed then process the content | F64: WHEN EIBAID = DFHENTER PERFORM PROCESS-MAP | G64: Decisão | H64: WHEN
A65: BNK1CRA-007 | B65: BNK1CRA | C65: 238 | D65: 240-247 | E65: When anything else happens, send the invalid key message | F65: WHEN OTHER MOVE LOW-VALUES TO BNK1CDO MOVE 'Invalid key pressed.' TO MESSAGEO MOVE 8 TO ACCNOL SET SEND-DATAONLY-ALARM TO TRUE PERFORM SEND-MAP END-EVALUATE. | G65: Decisão | H65: WHEN
A66: BNK1CRA-008 | B66: BNK1CRA | C66: 250-253 | D66: 255-271 | E66: Provided that we have been around this way before (i.e. it is NOT the first time through, put the data returned from the sub program into the area that we use as the COMMAREA on the RETURN. | F66: IF EIBCALEN NOT = ZERO MOVE COMM-ACCNO TO WS-COMM-ACCNO MOVE COMM-SIGN TO WS-COMM-SIGN MOVE COMM-AMT TO WS-COMM-AMT END-IF. EXEC CICS RETURN TRANSID('OCRA') COMMAREA(WS-COMM-AREA) LENGTH(21) RESP(WS-CICS-RESP) RESP2(WS-CICS-RESP2) END-EXEC. IF WS-CICS-RESP NOT = DFHRESP(NORMAL) | G66: Decisão e falha | H66: IF, falha
A67: BNK1CRA-009 | B67: BNK1CRA | C67: 273-276 | D67: 278-280 | E67: Preserve the RESP and RESP2, then set up the standard ABEND info before getting the applid, date/time etc. and linking to the Abend Handler program. | F67: INITIALIZE ABNDINFO-REC MOVE EIBRESP TO ABND-RESPCODE MOVE EIBRESP2 TO ABND-RESP2CODE | G67: Falha | H67: falha
A68: BNK1CRA-013 | B68: BNK1CRA | C68: 347-348 | D68: 350-354 | E68: If the data passes validation go on to apply the debit or credit. | F68: IF VALID-DATA PERFORM UPD-CRED-DATA END-IF. SET SEND-DATAONLY-ALARM TO TRUE. | G68: Decisão | H68: IF
A69: BNK1CRA-015 | B69: BNK1CRA | C69: 368 | D69: 370-378 | E69: Retrieve the data | F69: EXEC CICS RECEIVE MAP('BNK1CD') MAPSET('BNK1CDM') INTO(BNK1CDI) RESP(WS-CICS-RESP) RESP2(WS-CICS-RESP2) END-EXEC. IF WS-CICS-RESP NOT = DFHRESP(NORMAL) | G69: Decisão e falha | H69: IF, falha | I69: comentário curto
A70: BNK1CRA-016 | B70: BNK1CRA | C70: 380-383 | D70: 385-387 | E70: Preserve the RESP and RESP2, then set up the standard ABEND info before getting the applid, date/time etc. and linking to the Abend Handler program. | F70: INITIALIZE ABNDINFO-REC MOVE EIBRESP TO ABND-RESPCODE MOVE EIBRESP2 TO ABND-RESP2CODE | G70: Falha | H70: falha
A71: BNK1CRA-018 | B71: BNK1CRA | C71: 444 | D71: 446-469 | E71: Perform validation on the incoming fields | F71: EXEC CICS BIF DEEDIT FIELD(ACCNOI) END-EXEC. IF ACCNOI NOT NUMERIC MOVE 'Please enter an account number. ' TO MESSAGEO MOVE 'N' TO VALID-DATA-SW GO TO ED999 END-IF. IF ACCNOI = ZERO MOVE 'Please enter a non zero account number. ' TO MESSAGEO MOVE 'N' TO VALID-DATA-SW GO TO ED999 END-IF. IF SIGNI NOT = '+' AND SIGNI NOT = '-' AND SIGNL = 1 MOVE 'Please enter + or - preceding the amount ' TO MESSAGEO MOVE 'N' TO VALID-DATA-SW GO TO ED999 END-IF. | G71: Decisão | H71: IF
A72: BNK1CRA-021 | B72: BNK1CRA | C72: 492 | D72: 494-498 | E72: Provide the correct Amount | F72: IF SIGNI = '-' COMPUTE WS-AMOUNT-AS-FLOAT = WS-AMOUNT-AS-FLOAT * -1 END-IF. MOVE WS-AMOUNT-AS-FLOAT TO SUBPGM-AMT. | G72: Decisão | H72: IF
A73: BNK1CRA-022 | B73: BNK1CRA | C73: 501 | D73: 503-519 | E73: Get the ORIGIN data | F73: EXEC CICS INQUIRE ASSOCIATION(EIBTASKN) ODAPPLID(SUBPGM-APPLID) ODUSERID(SUBPGM-USERID) ODFACILNAME(SUBPGM-FACILITY-NAME) ODNETWORKID(SUBPGM-NETWRK-ID) ODFACILTYPE(SUBPGM-FACILTYPE) END-EXEC. EXEC CICS LINK PROGRAM('DBCRFUN') COMMAREA(SUBPGM-PARMS) RESP(WS-CICS-RESP) RESP2(WS-CICS-RESP2) SYNCONRETURN END-EXEC. IF WS-CICS-RESP NOT = DFHRESP(NORMAL) | G73: Decisão e falha | H73: IF, falha
A74: BNK1CRA-023 | B74: BNK1CRA | C74: 521-524 | D74: 526-528 | E74: Preserve the RESP and RESP2, then set up the standard ABEND info before getting the applid, date/time etc. and linking to the Abend Handler program. | F74: INITIALIZE ABNDINFO-REC MOVE EIBRESP TO ABND-RESPCODE MOVE EIBRESP2 TO ABND-RESP2CODE | G74: Falha | H74: falha
A75: BNK1CRA-025 | B75: BNK1CRA | C75: 579 | D75: 581-615 | E75: Check to see if the debit or credit was successful | F75: IF SUBPGM-SUCCESS = 'N' MOVE 'N' TO VALID-DATA-SW EVALUATE SUBPGM-FAIL-CODE WHEN '1' MOVE SPACES TO MESSAGEO STRING 'Sorry but the ACCOUNT no was not found' ' for SORTCODE ' SUBPGM-SORTC ' . Amount not applied. ' DELIMITED BY SIZE INTO MESSAGEO GO TO UCD999 WHEN '2' MOVE SPACES TO MESSAGEO STRING 'Sorry but the AMOUNT could not be applied' ' due to an unexpected error.' DELIMITED BY SIZE INTO MESSAGEO GO TO UCD999 WHEN '3' MOVE SPACES TO MESSAGEO STRING 'Sorry insufficient funds available to pro' 'cess the request. ' DELIMITED BY SIZE INTO MESSAGEO GO TO UCD999 WHEN OTHER MOVE SPACES TO MESSAGEO STRING 'Sorry but the AMOUNT could not be applied' ' due to an unexpected error. ' | G75: Decisão | H75: IF, EVALUATE, WHEN | I75: trecho truncado (30 linhas)
A76: BNK1CRA-027 | B76: BNK1CRA | C76: 646 | D76: 648-657 | E76: If the map needs to have its data erased | F76: IF SEND-ERASE EXEC CICS SEND MAP('BNK1CD') MAPSET('BNK1CDM') FROM(BNK1CDO) ERASE RESP(WS-CICS-RESP) RESP2(WS-CICS-RESP2) END-EXEC IF WS-CICS-RESP NOT = DFHRESP(NORMAL) | G76: Decisão e falha | H76: IF, falha
A77: BNK1CRA-028 | B77: BNK1CRA | C77: 659-662 | D77: 664-666 | E77: Preserve the RESP and RESP2, then set up the standard ABEND info before getting the applid, date/time etc. and linking to the Abend Handler program. | F77: INITIALIZE ABNDINFO-REC MOVE EIBRESP TO ABND-RESPCODE MOVE EIBRESP2 TO ABND-RESP2CODE | G77: Falha | H77: falha
A78: BNK1CRA-030 | B78: BNK1CRA | C78: 720 | D78: 722-731 | E78: If the map just needs a resend of only the data | F78: IF SEND-DATAONLY EXEC CICS SEND MAP('BNK1CD') MAPSET('BNK1CDM') FROM(BNK1CDO) DATAONLY RESP(WS-CICS-RESP) RESP2(WS-CICS-RESP2) END-EXEC IF WS-CICS-RESP NOT = DFHRESP(NORMAL) | G78: Decisão e falha | H78: IF, falha
A79: BNK1CRA-031 | B79: BNK1CRA | C79: 733-736 | D79: 738-740 | E79: Preserve the RESP and RESP2, then set up the standard ABEND info before getting the applid, date/time etc. and linking to the Abend Handler program. | F79: INITIALIZE ABNDINFO-REC MOVE EIBRESP TO ABND-RESPCODE MOVE EIBRESP2 TO ABND-RESP2CODE | G79: Falha | H79: falha
A80: BNK1CRA-033 | B80: BNK1CRA | C80: 794 | D80: 796-806 | E80: If we have elected to send the map and a beep | F80: IF SEND-DATAONLY-ALARM EXEC CICS SEND MAP('BNK1CD') MAPSET('BNK1CDM') FROM(BNK1CDO) DATAONLY ALARM RESP(WS-CICS-RESP) RESP2(WS-CICS-RESP2) END-EXEC IF WS-CICS-RESP NOT = DFHRESP(NORMAL) | G80: Decisão e falha | H80: IF, falha
A81: BNK1CRA-034 | B81: BNK1CRA | C81: 808-811 | D81: 813-815 | E81: Preserve the RESP and RESP2, then set up the standard ABEND info before getting the applid, date/time etc. and linking to the Abend Handler program. | F81: INITIALIZE ABNDINFO-REC MOVE EIBRESP TO ABND-RESPCODE MOVE EIBRESP2 TO ABND-RESP2CODE | G81: Falha | H81: falha
A82: BNK1CRA-036 | B82: BNK1CRA | C82: 874 | D82: 876-884 | E82: Send the termination message | F82: EXEC CICS SEND TEXT FROM(END-OF-SESSION-MESSAGE) ERASE FREEKB RESP(WS-CICS-RESP) RESP2(WS-CICS-RESP2) END-EXEC. IF WS-CICS-RESP NOT = DFHRESP(NORMAL) | G82: Decisão e falha | H82: IF, falha
A83: BNK1CRA-037 | B83: BNK1CRA | C83: 886-889 | D83: 891-893 | E83: Preserve the RESP and RESP2, then set up the standard ABEND info before getting the applid, date/time etc. and linking to the Abend Handler program. | F83: INITIALIZE ABNDINFO-REC MOVE EIBRESP TO ABND-RESPCODE MOVE EIBRESP2 TO ABND-RESP2CODE | G83: Falha | H83: falha
A84: BNK1CRA-039 | B84: BNK1CRA | C84: 986 | D84: 988-1024 | E84: It is entirely spaces | F84: IF WS-NUM-COUNT-TOTAL = AMTL MOVE 'The Amount entered must be numeric.' TO MESSAGEO MOVE 'N' TO VALID-DATA-SW MOVE -1 TO AMTL GO TO VA999 END-IF. COMPUTE WS-AMOUNT-UNSTR-L = AMTL - WS-NUM-COUNT-TOTAL. IF WS-NUM-COUNT-TOTAL = ZERO MOVE SPACES TO WS-AMOUNT-UNSTR UNSTRING AMTI(1:AMTL) INTO WS-AMOUNT-UNSTR ELSE MOVE SPACES TO WS-AMOUNT-UNSTR ADD 1 TO WS-NUM-COUNT-TOTAL GIVING WS-NUM-COUNT-TOTAL UNSTRING AMTI(WS-NUM-COUNT-TOTAL:AMTL) INTO WS-AMOUNT-UNSTR END-IF. MOVE ZERO TO WS-NUM-COUNT-TOTAL. MOVE FUNCTION REVERSE(WS-AMOUNT-UNSTR(1:WS-AMOUNT-UNSTR-L)) TO WS-AMOUNT-UNSTR-REVERSE INSPECT WS-AMOUNT-UNSTR-REVERSE TALLYING WS-NUM-COUNT-TOTAL FOR LEADING SPACES. SUBTRACT WS-NUM-COUNT-TOTAL FROM WS-AMOUNT-UNSTR-L GIVING WS-AMOUNT-UNSTR-L. MOVE ZERO TO WS-NUM-COUNT-TOTAL WS-NUM-COUNT-SPACE. INSPECT WS-AMOUNT-UNSTR(1:WS-AMOUNT-UNSTR-L) TALLYING WS-NUM-COUNT-TOTAL FOR ALL '0' | G84: Decisão | H84: IF | I84: trecho truncado (30 linhas)
A85: BNK1CRA-040 | B85: BNK1CRA | C85: 1038-1042 | D85: 1044-1064 | E85: If there is a decimal point, the field is not numeric. But if it is 1.1 then it is valid. So first of all we check to see that only the above chars are valid. We DO NOT tolerate embedded spaces too | F85: IF WS-NUM-COUNT-SPACE > 0 MOVE SPACES TO MESSAGEO STRING 'Please supply a numeric amount without embedded' DELIMITED BY SIZE, ' spaces.' DELIMITED BY SPACES INTO MESSAGEO MOVE 'N' TO VALID-DATA-SW MOVE -1 TO AMTL GO TO VA999 END-IF. IF WS-NUM-COUNT-TOTAL < WS-AMOUNT-UNSTR-L MOVE SPACES TO MESSAGEO STRING 'Please supply a numeric amount.' DELIMITED BY SIZE, INTO MESSAGEO MOVE 'N' TO VALID-DATA-SW MOVE -1 TO AMTL GO TO VA999 END-IF. | G85: Decisão | H85: IF
A86: BNK1CRA-041 | B86: BNK1CRA | C86: 1067 | D86: 1069-1083 | E86: Check that we have no or just one decimal point | F86: MOVE ZERO TO WS-NUM-COUNT-POINT INSPECT WS-AMOUNT-UNSTR(1:WS-AMOUNT-UNSTR-L) TALLYING WS-NUM-COUNT-POINT FOR ALL '.'. IF WS-NUM-COUNT-POINT > 1 MOVE SPACES TO MESSAGEO STRING 'Use one decimal point for amount only.' DELIMITED BY SIZE, INTO MESSAGEO MOVE 'N' TO VALID-DATA-SW MOVE -1 TO AMTL GO TO VA999 END-IF. | G86: Decisão | H86: IF
A87: BNK1CRA-042 | B87: BNK1CRA | C87: 1086 | D87: 1088-1114 | E87: Have we got too many decimals? | F87: IF WS-NUM-COUNT-POINT = 1 MOVE ZERO TO WS-NUM-COUNT-TOTAL INSPECT WS-AMOUNT-UNSTR(1:WS-AMOUNT-UNSTR-L) TALLYING WS-NUM-COUNT-TOTAL FOR CHARACTERS AFTER '.' IF WS-NUM-COUNT-TOTAL > 2 MOVE ZERO TO WS-NUM-COUNT-TOTAL WS-NUM-COUNT-POINT INSPECT WS-AMOUNT-UNSTR(1:WS-AMOUNT-UNSTR-L) TALLYING WS-NUM-COUNT-POINT FOR CHARACTERS BEFORE '.' ADD 2 TO WS-NUM-COUNT-POINT GIVING WS-NUM-COUNT-POINT INSPECT WS-AMOUNT-UNSTR(WS-NUM-COUNT-POINT:WS-AMOUNT-UNSTR-L) TALLYING WS-NUM-COUNT-TOTAL FOR ALL '0' WS-NUM-COUNT-TOTAL FOR ALL '1' WS-NUM-COUNT-TOTAL FOR ALL '2' WS-NUM-COUNT-TOTAL FOR ALL '3' WS-NUM-COUNT-TOTAL FOR ALL '4' WS-NUM-COUNT-TOTAL FOR ALL '5' WS-NUM-COUNT-TOTAL FOR ALL '6' WS-NUM-COUNT-TOTAL FOR ALL '7' WS-NUM-COUNT-TOTAL FOR ALL '8' WS-NUM-COUNT-TOTAL FOR ALL '9' AFTER '.' IF WS-NUM-COUNT-TOTAL > 2 | G87: Decisão | H87: IF
A88: BNK1CRA-043 | B88: BNK1CRA | C88: 1116 | D88: 1118-1154 | E88: There are two numerics | F88: MOVE SPACES TO MESSAGEO STRING 'Only up to two decimal places are supported.' DELIMITED BY SIZE, INTO MESSAGEO MOVE 'N' TO VALID-DATA-SW MOVE -1 TO AMTL GO TO VA999 END-IF END-IF END-IF. COMPUTE WS-AMOUNT-AS-FLOAT = FUNCTION NUMVAL(WS-AMOUNT-UNSTR(1:WS-AMOUNT-UNSTR-L)). IF WS-AMOUNT-AS-FLOAT = ZERO MOVE SPACES TO MESSAGEO STRING 'Please supply a non-zero amount.' DELIMITED BY SIZE, INTO MESSAGEO MOVE 'N' TO VALID-DATA-SW MOVE -1 TO AMTL GO TO VA999 END-IF. MOVE SPACES TO MESSAGEO. MOVE 'Y' TO VALID-DATA-SW. VA999. EXIT. POPULATE-TIME-DATE SECTION. PTD010. EXEC CICS ASKTIME | G88: Decisão | H88: IF | I88: trecho truncado (30 linhas)
A89: BNK1TFN-001 | B89: BNK1TFN | C89: 180-181 | D89: 183-186 | E89: Is it the first time through? If so, send the map with erased (empty) data fields. | F89: WHEN EIBCALEN = ZERO MOVE LOW-VALUE TO BNK1TFO SET SEND-ERASE TO TRUE PERFORM SEND-MAP | G89: Decisão | H89: WHEN
A90: BNK1TFN-002 | B90: BNK1TFN | C90: 189 | D90: 191-192 | E90: If a PA key is pressed, just carry on | F90: WHEN EIBAID = DFHPA1 OR DFHPA2 OR DFHPA3 CONTINUE | G90: Decisão | H90: WHEN
A91: BNK1TFN-003 | B91: BNK1TFN | C91: 195 | D91: 197-203 | E91: When Pf3 is pressed, return to the main menu | F91: WHEN EIBAID = DFHPF3 EXEC CICS RETURN TRANSID('OMEN') IMMEDIATE RESP(WS-CICS-RESP) RESP2(WS-CICS-RESP2) END-EXEC | G91: Decisão | H91: WHEN
A92: BNK1TFN-004 | B92: BNK1TFN | C92: 206-207 | D92: 209-213 | E92: If the aid or Pf12 is pressed, then send a termination message. | F92: WHEN EIBAID = DFHAID OR DFHPF12 PERFORM SEND-TERMINATION-MSG EXEC CICS RETURN END-EXEC | G92: Decisão | H92: WHEN
A93: BNK1TFN-005 | B93: BNK1TFN | C93: 216 | D93: 218-224 | E93: When CLEAR is pressed | F93: WHEN EIBAID = DFHCLEAR EXEC CICS SEND CONTROL ERASE FREEKB END-EXEC EXEC CICS RETURN END-EXEC | G93: Decisão | H93: WHEN
A94: BNK1TFN-006 | B94: BNK1TFN | C94: 227 | D94: 229-230 | E94: When enter is pressed then process the content | F94: WHEN EIBAID = DFHENTER PERFORM PROCESS-MAP | G94: Decisão | H94: WHEN
A95: BNK1TFN-007 | B95: BNK1TFN | C95: 233 | D95: 235-237 | E95: When anything else happens, send the invalid key message | F95: WHEN OTHER MOVE LOW-VALUES TO BNK1TFO MOVE 'Invalid key pressed.' TO MESSAGEO | G95: Decisão | H95: WHEN
A96: BNK1TFN-009 | B96: BNK1TFN | C96: 245 | D96: 247-255 | E96: Now RETURN | F96: EXEC CICS RETURN TRANSID('OTFN') COMMAREA(WS-COMMAREA) LENGTH(29) RESP(WS-CICS-RESP) RESP2(WS-CICS-RESP2) END-EXEC. IF WS-CICS-RESP NOT = DFHRESP(NORMAL) | G96: Decisão e falha | H96: IF, falha | I96: comentário curto
A97: BNK1TFN-010 | B97: BNK1TFN | C97: 257-260 | D97: 262-264 | E97: Preserve the RESP and RESP2, then set up the standard ABEND info before getting the applid, date/time etc. and linking to the Abend Handler program. | F97: INITIALIZE ABNDINFO-REC MOVE EIBRESP TO ABND-RESPCODE MOVE EIBRESP2 TO ABND-RESP2CODE | G97: Falha | H97: falha
A98: BNK1TFN-014 | B98: BNK1TFN | C98: 333-334 | D98: 336-340 | E98: If the data passes validation go on to get an account | F98: IF VALID-DATA PERFORM GET-ACC-DATA END-IF. SET SEND-DATAONLY-ALARM TO TRUE. | G98: Decisão | H98: IF
A99: BNK1TFN-016 | B99: BNK1TFN | C99: 354 | D99: 356-364 | E99: Retrieve the data | F99: EXEC CICS RECEIVE MAP('BNK1TF') MAPSET('BNK1TFM') INTO(BNK1TFI) RESP(WS-CICS-RESP) RESP2(WS-CICS-RESP2) END-EXEC. IF WS-CICS-RESP NOT = DFHRESP(NORMAL) | G99: Decisão e falha | H99: IF, falha | I99: comentário curto
A100: BNK1TFN-017 | B100: BNK1TFN | C100: 366-369 | D100: 371-373 | E100: Preserve the RESP and RESP2, then set up the standard ABEND info before getting the applid, date/time etc. and linking to the Abend Handler program. | F100: INITIALIZE ABNDINFO-REC MOVE EIBRESP TO ABND-RESPCODE MOVE EIBRESP2 TO ABND-RESP2CODE | G100: Falha | H100: falha
A101: BNK1TFN-019 | B101: BNK1TFN | C101: 431 | D101: 433-467 | E101: Perform validation on the incoming fields | F101: EXEC CICS BIF DEEDIT FIELD(FACCNOI) END-EXEC. IF FACCNOI NOT NUMERIC MOVE 'Please enter a FROM account no ' TO MESSAGEO MOVE 'N' TO VALID-DATA-SW GO TO ED999 END-IF. EXEC CICS BIF DEEDIT FIELD(TACCNOI) END-EXEC. IF TACCNOI NOT NUMERIC MOVE 'Please enter a TO account no ' TO MESSAGEO MOVE 'N' TO VALID-DATA-SW GO TO ED999 END-IF. IF FACCNOI = TACCNOI MOVE 'The FROM & TO account should be different ' TO MESSAGEO MOVE 'N' TO VALID-DATA-SW GO TO ED999 END-IF. IF FACCNOI = '00000000' OR TACCNOI = '00000000' MOVE 'Account no 00000000 is not valid ' TO MESSAGEO MOVE 'N' TO VALID-DATA-SW GO TO ED999 END-IF. | G101: Decisão | H101: IF
A102: BNK1TFN-022 | B102: BNK1TFN | C102: 492 | D102: 494-504 | E102: Provide the correct Amount | F102: MOVE WS-AMOUNT-AS-FLOAT TO SUBPGM-AMT. EXEC CICS LINK PROGRAM('XFRFUN') COMMAREA(SUBPGM-PARMS) RESP(WS-CICS-RESP) RESP2(WS-CICS-RESP2) SYNCONRETURN END-EXEC. IF WS-CICS-RESP NOT = DFHRESP(NORMAL) | G102: Decisão e falha | H102: IF, falha
A103: BNK1TFN-023 | B103: BNK1TFN | C103: 506-509 | D103: 511-513 | E103: Preserve the RESP and RESP2, then set up the standard ABEND info before getting the applid, date/time etc. and linking to the Abend Handler program. | F103: INITIALIZE ABNDINFO-REC MOVE EIBRESP TO ABND-RESPCODE MOVE EIBRESP2 TO ABND-RESP2CODE | G103: Falha | H103: falha
A104: BNK1TFN-026 | B104: BNK1TFN | C104: 580-581 | D104: 582-617 | E104: If an error was flagged by XFRFUN then set up an appropriate error message. | F104: IF SUBPGM-SUCCESS = 'N' MOVE 'N' TO VALID-DATA-SW EVALUATE SUBPGM-FAIL-CODE WHEN '1' MOVE SPACES TO MESSAGEO STRING 'Sorry the FROM ACCOUNT no was not found' '. Transfer not applied. ' DELIMITED BY SIZE INTO MESSAGEO GO TO GCD999 WHEN '2' MOVE SPACES TO MESSAGEO STRING 'Sorry the TO ACCOUNT no was not found' '. Transfer not applied. ' DELIMITED BY SIZE INTO MESSAGEO GO TO GCD999 WHEN '3' MOVE SPACES TO MESSAGEO STRING 'Sorry but the transfer could not be applied' ' due to an unexpected error.' DELIMITED BY SIZE INTO MESSAGEO WHEN '4' MOVE SPACES TO MESSAGEO STRING 'Please supply an amount greater than zero.' DELIMITED BY SIZE INTO MESSAGEO GO TO GCD999 WHEN OTHER | G104: Decisão | H104: IF, EVALUATE, WHEN | I104: trecho truncado (30 linhas)
A105: BNK1TFN-028 | B105: BNK1TFN | C105: 665-669 | D105: 671-680 | E105: Send/show the MAP If the map needs to have its data erased | F105: IF SEND-ERASE EXEC CICS SEND MAP('BNK1TF') MAPSET('BNK1TFM') FROM(BNK1TFO) ERASE RESP(WS-CICS-RESP) RESP2(WS-CICS-RESP2) END-EXEC IF WS-CICS-RESP NOT = DFHRESP(NORMAL) | G105: Decisão e falha | H105: IF, falha
A106: BNK1TFN-029 | B106: BNK1TFN | C106: 682-685 | D106: 687-689 | E106: Preserve the RESP and RESP2, then set up the standard ABEND info before getting the applid, date/time etc. and linking to the Abend Handler program. | F106: INITIALIZE ABNDINFO-REC MOVE EIBRESP TO ABND-RESPCODE MOVE EIBRESP2 TO ABND-RESP2CODE | G106: Falha | H106: falha
A107: BNK1TFN-031 | B107: BNK1TFN | C107: 743 | D107: 745-754 | E107: If the map just needs a resend of only the data | F107: IF SEND-DATAONLY EXEC CICS SEND MAP('BNK1TF') MAPSET('BNK1TFM') FROM(BNK1TFO) DATAONLY RESP(WS-CICS-RESP) RESP2(WS-CICS-RESP2) END-EXEC IF WS-CICS-RESP NOT = DFHRESP(NORMAL) | G107: Decisão e falha | H107: IF, falha
A108: BNK1TFN-032 | B108: BNK1TFN | C108: 756-759 | D108: 761-763 | E108: Preserve the RESP and RESP2, then set up the standard ABEND info before getting the applid, date/time etc. and linking to the Abend Handler program. | F108: INITIALIZE ABNDINFO-REC MOVE EIBRESP TO ABND-RESPCODE MOVE EIBRESP2 TO ABND-RESP2CODE | G108: Falha | H108: falha
A109: BNK1TFN-034 | B109: BNK1TFN | C109: 817 | D109: 819-829 | E109: If we have elected to send the map and a beep | F109: IF SEND-DATAONLY-ALARM EXEC CICS SEND MAP('BNK1TF') MAPSET('BNK1TFM') FROM(BNK1TFO) DATAONLY ALARM RESP(WS-CICS-RESP) RESP2(WS-CICS-RESP2) END-EXEC IF WS-CICS-RESP NOT = DFHRESP(NORMAL) | G109: Decisão e falha | H109: IF, falha
A110: BNK1TFN-035 | B110: BNK1TFN | C110: 831-834 | D110: 836-838 | E110: Preserve the RESP and RESP2, then set up the standard ABEND info before getting the applid, date/time etc. and linking to the Abend Handler program. | F110: INITIALIZE ABNDINFO-REC MOVE EIBRESP TO ABND-RESPCODE MOVE EIBRESP2 TO ABND-RESP2CODE | G110: Falha | H110: falha
A111: BNK1TFN-037 | B111: BNK1TFN | C111: 897 | D111: 899-907 | E111: Send the termination message | F111: EXEC CICS SEND TEXT FROM(END-OF-SESSION-MESSAGE) ERASE FREEKB RESP(WS-CICS-RESP) RESP2(WS-CICS-RESP2) END-EXEC. IF WS-CICS-RESP NOT = DFHRESP(NORMAL) | G111: Decisão e falha | H111: IF, falha
A112: BNK1TFN-038 | B112: BNK1TFN | C112: 909-912 | D112: 914-916 | E112: Preserve the RESP and RESP2, then set up the standard ABEND info before getting the applid, date/time etc. and linking to the Abend Handler program. | F112: INITIALIZE ABNDINFO-REC MOVE EIBRESP TO ABND-RESPCODE MOVE EIBRESP2 TO ABND-RESP2CODE | G112: Falha | H112: falha
A113: BNK1TFN-040 | B113: BNK1TFN | C113: 973 | D113: 975-986 | E113: Issue an abend | F113: DISPLAY WS-FAIL-INFO. EXEC CICS ABEND ABCODE('HBNK') NODUMP END-EXEC. ATT999. EXIT. VALIDATE-AMOUNT SECTION. VA010. | G113: Falha | H113: falha | I113: comentário curto
A114: BNK1TFN-041 | B114: BNK1TFN | C114: 988-989 | D114: 991-999 | E114: Validate the amount entered. Is it greater than 0? | F114: IF AMTL = ZERO MOVE 'The Amount entered must be numeric.' TO MESSAGEO MOVE 'N' TO VALID-DATA-SW MOVE -1 TO AMTL GO TO VA999 END-IF IF AMTI(1:AMTL) IS NUMERIC | G114: Decisão | H114: IF
A115: BNK1TFN-042 | B115: BNK1TFN | C115: 1001 | D115: 1003-1021 | E115: Is it a positive amount? | F115: COMPUTE WS-AMOUNT-AS-FLOAT = FUNCTION NUMVAL(AMTI(1:AMTL)) IF WS-AMOUNT-AS-FLOAT <= 0 MOVE SPACES TO MESSAGEO STRING 'Please supply a positive amount.' DELIMITED BY SIZE, INTO MESSAGEO MOVE 'N' TO VALID-DATA-SW MOVE -1 TO AMTL GO TO VA999 END-IF MOVE 'Y' TO VALID-DATA-SW GO TO VA999 END-IF. MOVE ZERO TO WS-NUM-COUNT-TOTAL. INSPECT AMTI(1:AMTL) TALLYING WS-NUM-COUNT-TOTAL FOR LEADING SPACES. | G115: Decisão | H115: IF
...

Sheet Descartados
A1: ID | B1: Programa | C1: Linhas do comentário | D1: Linhas do código | E1: Comentário | F1: Trecho de código | G1: Motivo do descarte | H1: Alertas | I1: Reavaliação
A2: DBCRFUN-002 | B2: DBCRFUN | C2: 215-221 | D2: 223 | E2: Determine what kind of ACCOUNT datastore we should be accessing Go and update the ACCOUNT record | F2: PERFORM UPDATE-ACCOUNT-DB2. | G2: Procedural (sem decisão nem tratamento de falha) | H2: comentário menciona condição: reavaliar
A3: DBCRFUN-003 | B3: DBCRFUN | C3: 225-226 | D3: 229-240 | E3: The COMMAREA values have now been set so all we need to do is finish | F3: PERFORM GET-ME-OUT-OF-HERE. A999. EXIT. UPDATE-ACCOUNT-DB2 SECTION. UAD010. MOVE COMM-ACCNO TO DESIRED-ACC-NO. MOVE DESIRED-SORT-CODE TO HV-ACCOUNT-SORTCODE. MOVE DESIRED-ACC-NO TO HV-ACCOUNT-ACC-NO. | G3: Procedural (sem decisão nem tratamento de falha)
A4: DBCRFUN-004 | B4: DBCRFUN | C4: 243 | D4: 245-273 | E4: Retrieve the account information | F4: EXEC SQL SELECT ACCOUNT_EYECATCHER, ACCOUNT_CUSTOMER_NUMBER, ACCOUNT_SORTCODE, ACCOUNT_NUMBER, ACCOUNT_TYPE, ACCOUNT_INTEREST_RATE, ACCOUNT_OPENED, ACCOUNT_OVERDRAFT_LIMIT, ACCOUNT_LAST_STATEMENT, ACCOUNT_NEXT_STATEMENT, ACCOUNT_AVAILABLE_BALANCE, ACCOUNT_ACTUAL_BALANCE INTO :HV-ACCOUNT-EYECATCHER, :HV-ACCOUNT-CUST-NO, :HV-ACCOUNT-SORTCODE, :HV-ACCOUNT-ACC-NO, :HV-ACCOUNT-ACC-TYPE, :HV-ACCOUNT-INT-RATE, :HV-ACCOUNT-OPENED, :HV-ACCOUNT-OVERDRAFT-LIM, :HV-ACCOUNT-LAST-STMT, :HV-ACCOUNT-NEXT-STMT, :HV-ACCOUNT-AVAIL-BAL, :HV-ACCOUNT-ACTUAL-BAL FROM ACCOUNT WHERE (ACCOUNT_SORTCODE = :HV-ACCOUNT-SORTCODE AND ACCOUNT_NUMBER = :HV-ACCOUNT-ACC-NO) END-EXEC. | G4: Procedural (sem decisão nem tratamento de falha)
A5: DBCRFUN-006 | B5: DBCRFUN | C5: 290-291 | D5: 293-297 | E5: Check if SQLCODE indicates that Storm Drain processing is applicable in a workload if activated | F5: PERFORM CHECK-FOR-STORM-DRAIN-DB2 GO TO UAD999 END-IF. | G5: Procedural (sem decisão nem tratamento de falha) | H5: comentário menciona condição: reavaliar
A6: DBCRFUN-010 | B6: DBCRFUN | C6: 380-382 | D6: 384-387 | E6: If the SQLCODE from the SELECT is OK then update the record and update the details on the PROCTRAN (Processed transaction) datastore. | F6: COMPUTE HV-ACCOUNT-AVAIL-BAL = HV-ACCOUNT-AVAIL-BAL + COMM-AMT. COMPUTE HV-ACCOUNT-ACTUAL-BAL = HV-ACCOUNT-ACTUAL-BAL + COMM-AMT. | G6: Procedural (sem decisão nem tratamento de falha) | H6: comentário menciona condição: reavaliar
A7: DBCRFUN-011 | B7: DBCRFUN | C7: 390 | D7: 392-408 | E7: Update the account record | F7: EXEC SQL UPDATE ACCOUNT SET ACCOUNT_EYECATCHER = :HV-ACCOUNT-EYECATCHER, ACCOUNT_CUSTOMER_NUMBER = :HV-ACCOUNT-CUST-NO, ACCOUNT_SORTCODE = :HV-ACCOUNT-SORTCODE, ACCOUNT_NUMBER = :HV-ACCOUNT-ACC-NO, ACCOUNT_TYPE = :HV-ACCOUNT-ACC-TYPE, ACCOUNT_INTEREST_RATE = :HV-ACCOUNT-INT-RATE, ACCOUNT_OPENED = :HV-ACCOUNT-OPENED, ACCOUNT_OVERDRAFT_LIMIT = :HV-ACCOUNT-OVERDRAFT-LIM, ACCOUNT_LAST_STATEMENT = :HV-ACCOUNT-LAST-STMT, ACCOUNT_NEXT_STATEMENT = :HV-ACCOUNT-NEXT-STMT, ACCOUNT_AVAILABLE_BALANCE = :HV-ACCOUNT-AVAIL-BAL, ACCOUNT_ACTUAL_BALANCE = :HV-ACCOUNT-ACTUAL-BAL WHERE (ACCOUNT_SORTCODE = :HV-ACCOUNT-SORTCODE AND ACCOUNT_NUMBER = :HV-ACCOUNT-ACC-NO) END-EXEC. | G7: Procedural (sem decisão nem tratamento de falha)
A8: DBCRFUN-014 | B8: DBCRFUN | C8: 429-430 | D8: 432-435 | E8: Check if SQLCODE indicates that Storm Drain processing is applicable in a workload if activated | F8: PERFORM CHECK-FOR-STORM-DRAIN-DB2 GO TO UAD999 END-IF. | G8: Procedural (sem decisão nem tratamento de falha) | H8: comentário menciona condição: reavaliar
A9: DBCRFUN-015 | B9: DBCRFUN | C9: 438-439 | D9: 441-448 | E9: If the RESP CODE was normal then we need to write to the PROCTRAN (processed transaction) datastore. | F9: PERFORM WRITE-TO-PROCTRAN. UAD999. EXIT. WRITE-TO-PROCTRAN SECTION. WTP010. | G9: Procedural (sem decisão nem tratamento de falha) | H9: comentário menciona condição: reavaliar
A10: DBCRFUN-016 | B10: DBCRFUN | C10: 451-452 | D10: 454-470 | E10: Write to the PROCTRAN datastore deatils regarding the successfully applied transaction. | F10: PERFORM WRITE-TO-PROCTRAN-DB2. WTP999. EXIT. WRITE-TO-PROCTRAN-DB2 SECTION. WTPD010. INITIALIZE HOST-PROCTRAN-ROW. INITIALIZE WS-EIBTASKN12. MOVE 'PRTR' TO HV-PROCTRAN-EYECATCHER. MOVE COMM-SORTC TO HV-PROCTRAN-SORT-CODE. MOVE COMM-ACCNO TO HV-PROCTRAN-ACC-NUMBER. MOVE EIBTASKN TO WS-EIBTASKN12. MOVE WS-EIBTASKN12 TO HV-PROCTRAN-REF. | G10: Procedural (sem decisão nem tratamento de falha)
A11: DBCRFUN-020 | B11: DBCRFUN | C11: 522 | D11: 524-549 | E11: Write a record to PROCTRAN | F11: EXEC SQL INSERT INTO PROCTRAN ( PROCTRAN_EYECATCHER, PROCTRAN_SORTCODE, PROCTRAN_NUMBER, PROCTRAN_DATE, PROCTRAN_TIME, PROCTRAN_REF, PROCTRAN_TYPE, PROCTRAN_DESC, PROCTRAN_AMOUNT ) VALUES ( :HV-PROCTRAN-EYECATCHER, :HV-PROCTRAN-SORT-CODE, :HV-PROCTRAN-ACC-NUMBER, :HV-PROCTRAN-DATE, :HV-PROCTRAN-TIME, :HV-PROCTRAN-REF, :HV-PROCTRAN-TYPE, :HV-PROCTRAN-DESC, :HV-PROCTRAN-AMOUNT ) END-EXEC. | G11: Procedural (sem decisão nem tratamento de falha)
A12: DBCRFUN-024 | B12: DBCRFUN | C12: 580 | D12: 582-618 | E12: Get supplemental information | F12: EXEC CICS ASSIGN APPLID(ABND-APPLID) END-EXEC MOVE EIBTASKN TO ABND-TASKNO-KEY MOVE EIBTRNID TO ABND-TRANID PERFORM POPULATE-TIME-DATE MOVE WS-ORIG-DATE TO ABND-DATE STRING WS-TIME-NOW-GRP-HH DELIMITED BY SIZE, ':' DELIMITED BY SIZE, WS-TIME-NOW-GRP-MM DELIMITED BY SIZE, ':' DELIMITED BY SIZE, WS-TIME-NOW-GRP-MM DELIMITED BY SIZE INTO ABND-TIME END-STRING MOVE WS-U-TIME TO ABND-UTIME-KEY MOVE 'HROL' TO ABND-CODE EXEC CICS ASSIGN PROGRAM(ABND-PROGRAM) END-EXEC MOVE ZEROS TO ABND-SQLCODE STRING 'WTPD010 - COULD NOT ROLL BACK, POSSIBLE DATA' DELIMITED BY SIZE, 'INTEGRITY ISSUE BETWEEN ACCOUNT AND PROCTRAN ' DELIMITED BY SIZE, 'FOR ROW:' DELIMITED BY SIZE, HOST-PROCTRAN-ROW DELIMITED BY SIZE, 'EIBRESP=' DELIMITED BY SIZE, ABND-RESPCODE DELIMITED BY SIZE, ' RESP2=' DELIMITED BY SIZE, ABND-RESP2CODE DELIMITED BY SIZE INTO ABND-FREEFORM END-STRING | G12: Procedural (sem decisão nem tratamento de falha) | H12: comentário curto; trecho truncado (30 linhas)
A13: DBCRFUN-025 | B13: DBCRFUN | C13: 639-640 | D13: 642-644 | E13: Check if SQLCODE indicates that Storm Drain processing is applicable in a workload if activated | F13: PERFORM CHECK-FOR-STORM-DRAIN-DB2 ELSE | G13: Procedural (sem decisão nem tratamento de falha) | H13: comentário menciona condição: reavaliar
A14: DBCRFUN-026 | B14: DBCRFUN | C14: 647 | D14: 649-669 | E14: If the WRITE to PROCTRAN worked then it was a success | F14: MOVE 'Y' TO COMM-SUCCESS MOVE '0' TO COMM-FAIL-CODE END-IF. WTPD999. EXIT. GET-ME-OUT-OF-HERE SECTION. GMOOH010. EXEC CICS RETURN END-EXEC. GOBACK. GMOOH999. EXIT. CHECK-FOR-STORM-DRAIN-DB2 SECTION. CFSDD010. | G14: Procedural (sem decisão nem tratamento de falha) | H14: comentário menciona condição: reavaliar
A15: DBCRFUN-028 | B15: DBCRFUN | C15: 699 | D15: 701-705 | E15: How ABENDs are dealt with | F15: ABEND-HANDLING SECTION. AH010. EXEC CICS ASSIGN ABCODE(MY-ABEND-CODE) END-EXEC. | G15: Procedural (sem decisão nem tratamento de falha)
A16: DBCRFUN-033 | B16: DBCRFUN | C16: 767 | D16: 769-805 | E16: Get supplemental information | F16: EXEC CICS ASSIGN APPLID(ABND-APPLID) END-EXEC MOVE EIBTASKN TO ABND-TASKNO-KEY MOVE EIBTRNID TO ABND-TRANID PERFORM POPULATE-TIME-DATE MOVE WS-ORIG-DATE TO ABND-DATE STRING WS-TIME-NOW-GRP-HH DELIMITED BY SIZE, ':' DELIMITED BY SIZE, WS-TIME-NOW-GRP-MM DELIMITED BY SIZE, ':' DELIMITED BY SIZE, WS-TIME-NOW-GRP-MM DELIMITED BY SIZE INTO ABND-TIME END-STRING MOVE WS-U-TIME TO ABND-UTIME-KEY MOVE 'HROL' TO ABND-CODE EXEC CICS ASSIGN PROGRAM(ABND-PROGRAM) END-EXEC MOVE ZEROS TO ABND-SQLCODE STRING 'AH010 - Unable to perform Synpoint ' DELIMITED BY SIZE, 'Rollback.' DELIMITED BY SIZE, ' Possible Integrity issue following VSAM RLS ' DELIMITED BY SIZE, 'abend.' DELIMITED BY SIZE, 'EIBRESP=' DELIMITED BY SIZE, ABND-RESPCODE DELIMITED BY SIZE, ' RESP2=' DELIMITED BY SIZE, ABND-RESP2CODE DELIMITED BY SIZE INTO ABND-FREEFORM END-STRING | G16: Procedural (sem decisão nem tratamento de falha) | H16: comentário curto; trecho truncado (30 linhas)
A17: XFRFUN-002 | B17: XFRFUN | C17: 299-300 | D17: 302-311 | E17: The COMMAREA values have now been set so all we need to do is finish | F17: PERFORM GET-ME-OUT-OF-HERE. A999. EXIT. UPDATE-ACCOUNT-DB2 SECTION. UAD010. MOVE 'N' TO COMM-SUCCESS. | G17: Procedural (sem decisão nem tratamento de falha)
A18: XFRFUN-005 | B18: XFRFUN | C18: 328 | D18: 330-368 | E18: Get supplemental information | F18: EXEC CICS ASSIGN APPLID(ABND-APPLID) END-EXEC MOVE EIBTASKN TO ABND-TASKNO-KEY MOVE EIBTRNID TO ABND-TRANID PERFORM POPULATE-TIME-DATE MOVE WS-ORIG-DATE TO ABND-DATE STRING WS-TIME-NOW-GRP-HH DELIMITED BY SIZE, ':' DELIMITED BY SIZE, WS-TIME-NOW-GRP-MM DELIMITED BY SIZE, ':' DELIMITED BY SIZE, WS-TIME-NOW-GRP-MM DELIMITED BY SIZE INTO ABND-TIME END-STRING MOVE WS-U-TIME TO ABND-UTIME-KEY MOVE 'SAME' TO ABND-CODE EXEC CICS ASSIGN PROGRAM(ABND-PROGRAM) END-EXEC MOVE ZEROS TO ABND-SQLCODE STRING 'UAD010 - Cannot transfer to the same account ' DELIMITED BY SIZE, ' EIBRESP=' DELIMITED BY SIZE, ABND-RESPCODE DELIMITED BY SIZE, ' RESP2=' DELIMITED BY SIZE, ABND-RESP2CODE DELIMITED BY SIZE INTO ABND-FREEFORM END-STRING EXEC CICS LINK PROGRAM(WS-ABEND-PGM) COMMAREA(ABNDINFO-REC) END-EXEC DISPLAY 'Cannot transfer to the same account' | G18: Procedural (sem decisão nem tratamento de falha) | H18: comentário curto; trecho truncado (30 linhas)
A19: XFRFUN-006 | B19: XFRFUN | C19: 380-381 | D19: 383-384 | E19: If the FROM account number is less than the TO account number | F19: MOVE COMM-FACCNO TO DESIRED-ACC-NO MOVE COMM-FSCODE TO DESIRED-SORT-CODE | G19: Procedural (sem decisão nem tratamento de falha) | H19: comentário menciona condição: reavaliar
A20: XFRFUN-007 | B20: XFRFUN | C20: 387 | D20: 389 | E20: Update the FROM account | F20: PERFORM UPDATE-ACCOUNT-DB2-FROM | G20: Procedural (sem decisão nem tratamento de falha)
A21: XFRFUN-011 | B21: XFRFUN | C21: 424 | D21: 426-463 | E21: Get supplemental information | F21: EXEC CICS ASSIGN APPLID(ABND-APPLID) END-EXEC MOVE EIBTASKN TO ABND-TASKNO-KEY MOVE EIBTRNID TO ABND-TRANID PERFORM POPULATE-TIME-DATE MOVE WS-ORIG-DATE TO ABND-DATE STRING WS-TIME-NOW-GRP-HH DELIMITED BY SIZE, ':' DELIMITED BY SIZE, WS-TIME-NOW-GRP-MM DELIMITED BY SIZE, ':' DELIMITED BY SIZE, WS-TIME-NOW-GRP-MM DELIMITED BY SIZE INTO ABND-TIME END-STRING MOVE WS-U-TIME TO ABND-UTIME-KEY MOVE 'HROL' TO ABND-CODE EXEC CICS ASSIGN PROGRAM(ABND-PROGRAM) END-EXEC MOVE ZEROS TO ABND-SQLCODE STRING 'UAD010(2) - Error on SYNCPOINT' DELIMITED BY SIZE, ' ROLLBACK' DELIMITED BY SIZE, ' after UPDATING TO account ' DELIMITED BY SIZE, ' EIBRESP=' DELIMITED BY SIZE, ABND-RESPCODE DELIMITED BY SIZE, ' RESP2=' DELIMITED BY SIZE, ABND-RESP2CODE DELIMITED BY SIZE INTO ABND-FREEFORM END-STRING EXEC CICS LINK PROGRAM(WS-ABEND-PGM) | G21: Procedural (sem decisão nem tratamento de falha) | H21: comentário curto; trecho truncado (30 linhas)
A22: XFRFUN-016 | B22: XFRFUN | C22: 537 | D22: 539-577 | E22: Get supplemental information | F22: EXEC CICS ASSIGN APPLID(ABND-APPLID) END-EXEC MOVE EIBTASKN TO ABND-TASKNO-KEY MOVE EIBTRNID TO ABND-TRANID PERFORM POPULATE-TIME-DATE MOVE WS-ORIG-DATE TO ABND-DATE STRING WS-TIME-NOW-GRP-HH DELIMITED BY SIZE, ':' DELIMITED BY SIZE, WS-TIME-NOW-GRP-MM DELIMITED BY SIZE, ':' DELIMITED BY SIZE, WS-TIME-NOW-GRP-MM DELIMITED BY SIZE INTO ABND-TIME END-STRING MOVE WS-U-TIME TO ABND-UTIME-KEY MOVE 'FROM' TO ABND-CODE EXEC CICS ASSIGN PROGRAM(ABND-PROGRAM) END-EXEC MOVE ZEROS TO ABND-SQLCODE STRING 'UAD010(3) - Error updating FROM account ' DELIMITED BY SIZE, ' EIBRESP=' DELIMITED BY SIZE, ABND-RESPCODE DELIMITED BY SIZE, ' RESP2=' DELIMITED BY SIZE, ABND-RESP2CODE DELIMITED BY SIZE INTO ABND-FREEFORM END-STRING EXEC CICS LINK PROGRAM(WS-ABEND-PGM) COMMAREA(ABNDINFO-REC) END-EXEC DISPLAY 'Error updating FROM account' | G22: Procedural (sem decisão nem tratamento de falha) | H22: comentário curto; trecho truncado (30 linhas)
A23: XFRFUN-017 | B23: XFRFUN | C23: 591-592 | D23: 594-595 | E23: The FROM account number is greater than the TO account number | F23: MOVE COMM-TACCNO TO DESIRED-ACC-NO MOVE COMM-TSCODE TO DESIRED-SORT-CODE | G23: Procedural (sem decisão nem tratamento de falha)
A24: XFRFUN-018 | B24: XFRFUN | C24: 598 | D24: 600 | E24: Update the TO account number | F24: PERFORM UPDATE-ACCOUNT-DB2-TO | G24: Procedural (sem decisão nem tratamento de falha)
A25: XFRFUN-022 | B25: XFRFUN | C25: 628 | D25: 630-668 | E25: Get supplemental information | F25: EXEC CICS ASSIGN APPLID(ABND-APPLID) END-EXEC MOVE EIBTASKN TO ABND-TASKNO-KEY MOVE EIBTRNID TO ABND-TRANID PERFORM POPULATE-TIME-DATE MOVE WS-ORIG-DATE TO ABND-DATE STRING WS-TIME-NOW-GRP-HH DELIMITED BY SIZE, ':' DELIMITED BY SIZE, WS-TIME-NOW-GRP-MM DELIMITED BY SIZE, ':' DELIMITED BY SIZE, WS-TIME-NOW-GRP-MM DELIMITED BY SIZE INTO ABND-TIME END-STRING MOVE WS-U-TIME TO ABND-UTIME-KEY MOVE 'FROM' TO ABND-CODE EXEC CICS ASSIGN PROGRAM(ABND-PROGRAM) END-EXEC MOVE ZEROS TO ABND-SQLCODE STRING 'UAD010(4) - Error updating FROM account ' DELIMITED BY SIZE, ' EIBRESP=' DELIMITED BY SIZE, ABND-RESPCODE DELIMITED BY SIZE, ' RESP2=' DELIMITED BY SIZE, ABND-RESP2CODE DELIMITED BY SIZE INTO ABND-FREEFORM END-STRING EXEC CICS LINK PROGRAM(WS-ABEND-PGM) COMMAREA(ABNDINFO-REC) END-EXEC DISPLAY 'Error updating FROM account' | G25: Procedural (sem decisão nem tratamento de falha) | H25: comentário curto; trecho truncado (30 linhas)
A26: XFRFUN-023 | B26: XFRFUN | C26: 677 | D26: 679-683 | E26: If the FAIL code is something else | F26: EXEC CICS SYNCPOINT ROLLBACK RESP(WS-CICS-RESP) RESP2(WS-CICS-RESP2) END-EXEC | G26: Procedural (sem decisão nem tratamento de falha) | H26: comentário menciona condição: reavaliar
A27: XFRFUN-026 | B27: XFRFUN | C27: 698 | D27: 700-737 | E27: Get supplemental information | F27: EXEC CICS ASSIGN APPLID(ABND-APPLID) END-EXEC MOVE EIBTASKN TO ABND-TASKNO-KEY MOVE EIBTRNID TO ABND-TRANID PERFORM POPULATE-TIME-DATE MOVE WS-ORIG-DATE TO ABND-DATE STRING WS-TIME-NOW-GRP-HH DELIMITED BY SIZE, ':' DELIMITED BY SIZE, WS-TIME-NOW-GRP-MM DELIMITED BY SIZE, ':' DELIMITED BY SIZE, WS-TIME-NOW-GRP-MM DELIMITED BY SIZE INTO ABND-TIME END-STRING MOVE WS-U-TIME TO ABND-UTIME-KEY MOVE 'HROL' TO ABND-CODE EXEC CICS ASSIGN PROGRAM(ABND-PROGRAM) END-EXEC MOVE ZEROS TO ABND-SQLCODE STRING 'UAD010(5) - Error on SYNCPOINT ' DELIMITED BY SIZE, ' ROLLBACK ' DELIMITED BY SIZE, ' after UPDATING the FROM account' DELIMITED BY SIZE, ' EIBRESP=' DELIMITED BY SIZE, ABND-RESPCODE DELIMITED BY SIZE, ' RESP2=' DELIMITED BY SIZE, ABND-RESP2CODE DELIMITED BY SIZE INTO ABND-FREEFORM END-STRING EXEC CICS LINK PROGRAM(WS-ABEND-PGM) | G27: Procedural (sem decisão nem tratamento de falha) | H27: comentário curto; trecho truncado (30 linhas)
A28: XFRFUN-029 | B28: XFRFUN | C28: 777 | D28: 779-817 | E28: Get supplemental information | F28: EXEC CICS ASSIGN APPLID(ABND-APPLID) END-EXEC MOVE EIBTASKN TO ABND-TASKNO-KEY MOVE EIBTRNID TO ABND-TRANID PERFORM POPULATE-TIME-DATE MOVE WS-ORIG-DATE TO ABND-DATE STRING WS-TIME-NOW-GRP-HH DELIMITED BY SIZE, ':' DELIMITED BY SIZE, WS-TIME-NOW-GRP-MM DELIMITED BY SIZE, ':' DELIMITED BY SIZE, WS-TIME-NOW-GRP-MM DELIMITED BY SIZE INTO ABND-TIME END-STRING MOVE WS-U-TIME TO ABND-UTIME-KEY MOVE 'TO ' TO ABND-CODE EXEC CICS ASSIGN PROGRAM(ABND-PROGRAM) END-EXEC MOVE ZEROS TO ABND-SQLCODE STRING 'UAD010(6) - Error updating TO account ' DELIMITED BY SIZE, ' EIBRESP=' DELIMITED BY SIZE, ABND-RESPCODE DELIMITED BY SIZE, ' RESP2=' DELIMITED BY SIZE, ABND-RESP2CODE DELIMITED BY SIZE INTO ABND-FREEFORM END-STRING EXEC CICS LINK PROGRAM(WS-ABEND-PGM) COMMAREA(ABNDINFO-REC) END-EXEC DISPLAY 'Error updating TO account' | G28: Procedural (sem decisão nem tratamento de falha) | H28: comentário curto; trecho truncado (30 linhas)
A29: XFRFUN-031 | B29: XFRFUN | C29: 843 | D29: 845-882 | E29: Get supplemental information | F29: EXEC CICS ASSIGN APPLID(ABND-APPLID) END-EXEC MOVE EIBTASKN TO ABND-TASKNO-KEY MOVE EIBTRNID TO ABND-TRANID PERFORM POPULATE-TIME-DATE MOVE WS-ORIG-DATE TO ABND-DATE STRING WS-TIME-NOW-GRP-HH DELIMITED BY SIZE, ':' DELIMITED BY SIZE, WS-TIME-NOW-GRP-MM DELIMITED BY SIZE, ':' DELIMITED BY SIZE, WS-TIME-NOW-GRP-MM DELIMITED BY SIZE INTO ABND-TIME END-STRING MOVE WS-U-TIME TO ABND-UTIME-KEY MOVE 'HROL' TO ABND-CODE EXEC CICS ASSIGN PROGRAM(ABND-PROGRAM) END-EXEC MOVE ZEROS TO ABND-SQLCODE STRING 'UAD010(7) - Error on SYNCPOINT ROLLBACK' DELIMITED BY SIZE, ' after UPDATING the TO account' DELIMITED BY SIZE, ' EIBRESP=' DELIMITED BY SIZE, ABND-RESPCODE DELIMITED BY SIZE, ' RESP2=' DELIMITED BY SIZE, ABND-RESP2CODE DELIMITED BY SIZE INTO ABND-FREEFORM END-STRING EXEC CICS LINK PROGRAM(WS-ABEND-PGM) COMMAREA(ABNDINFO-REC) | G29: Procedural (sem decisão nem tratamento de falha) | H29: comentário curto; trecho truncado (30 linhas)
A30: XFRFUN-032 | B30: XFRFUN | C30: 907-909 | D30: 911-920 | E30: If the updates to the TO and FROM accounts were successful then we need to write to PROCTRAN (processed transaction) to record the successful transfer. | F30: PERFORM WRITE-TO-PROCTRAN. MOVE 'Y' TO COMM-SUCCESS. UAD999. EXIT. UPDATE-ACCOUNT-DB2-FROM SECTION. UADF010. | G30: Procedural (sem decisão nem tratamento de falha) | H30: comentário menciona condição: reavaliar
A31: XFRFUN-033 | B31: XFRFUN | C31: 922 | D31: 924-955 | E31: Position ourself at the matching FROM account record | F31: MOVE COMM-FACCNO TO DESIRED-ACC-NO. MOVE COMM-FSCODE TO DESIRED-SORT-CODE. MOVE DESIRED-SORT-CODE TO HV-ACCOUNT-SORTCODE. MOVE DESIRED-ACC-NO TO HV-ACCOUNT-ACC-NO. EXEC SQL SELECT ACCOUNT_EYECATCHER, ACCOUNT_CUSTOMER_NUMBER, ACCOUNT_SORTCODE, ACCOUNT_NUMBER, ACCOUNT_TYPE, ACCOUNT_INTEREST_RATE, ACCOUNT_OPENED, ACCOUNT_OVERDRAFT_LIMIT, ACCOUNT_LAST_STATEMENT, ACCOUNT_NEXT_STATEMENT, ACCOUNT_AVAILABLE_BALANCE, ACCOUNT_ACTUAL_BALANCE INTO :HV-ACCOUNT-EYECATCHER, :HV-ACCOUNT-CUST-NO, :HV-ACCOUNT-SORTCODE, :HV-ACCOUNT-ACC-NO, :HV-ACCOUNT-ACC-TYPE, :HV-ACCOUNT-INT-RATE, :HV-ACCOUNT-OPENED, :HV-ACCOUNT-OVERDRAFT-LIM, :HV-ACCOUNT-LAST-STMT, :HV-ACCOUNT-NEXT-STMT, :HV-ACCOUNT-AVAIL-BAL, :HV-ACCOUNT-ACTUAL-BAL FROM ACCOUNT | G31: Procedural (sem decisão nem tratamento de falha) | H31: trecho truncado (30 linhas)
A32: XFRFUN-035 | B32: XFRFUN | C32: 973-974 | D32: 976-980 | E32: Check if SQLCODE indicates that Storm Drain processing is applicable in a workload if activated | F32: PERFORM CHECK-FOR-STORM-DRAIN-DB2 GO TO UADF999 END-IF. | G32: Procedural (sem decisão nem tratamento de falha) | H32: comentário menciona condição: reavaliar
A33: XFRFUN-036 | B33: XFRFUN | C33: 983-984 | D33: 986-1008 | E33: If the SQLCODE is OK then update the row on ACCOUNT for the FROM account. | F33: COMPUTE HV-ACCOUNT-AVAIL-BAL = HV-ACCOUNT-AVAIL-BAL - COMM-AMT. COMPUTE HV-ACCOUNT-ACTUAL-BAL = HV-ACCOUNT-ACTUAL-BAL - COMM-AMT. EXEC SQL UPDATE ACCOUNT SET ACCOUNT_EYECATCHER = :HV-ACCOUNT-EYECATCHER, ACCOUNT_CUSTOMER_NUMBER = :HV-ACCOUNT-CUST-NO, ACCOUNT_SORTCODE = :HV-ACCOUNT-SORTCODE, ACCOUNT_NUMBER = :HV-ACCOUNT-ACC-NO, ACCOUNT_TYPE = :HV-ACCOUNT-ACC-TYPE, ACCOUNT_INTEREST_RATE = :HV-ACCOUNT-INT-RATE, ACCOUNT_OPENED = :HV-ACCOUNT-OPENED, ACCOUNT_OVERDRAFT_LIMIT = :HV-ACCOUNT-OVERDRAFT-LIM, ACCOUNT_LAST_STATEMENT = :HV-ACCOUNT-LAST-STMT, ACCOUNT_NEXT_STATEMENT = :HV-ACCOUNT-NEXT-STMT, ACCOUNT_AVAILABLE_BALANCE = :HV-ACCOUNT-AVAIL-BAL, ACCOUNT_ACTUAL_BALANCE = :HV-ACCOUNT-ACTUAL-BAL WHERE (ACCOUNT_SORTCODE = :HV-ACCOUNT-SORTCODE AND ACCOUNT_NUMBER = :HV-ACCOUNT-ACC-NO) END-EXEC. | G33: Procedural (sem decisão nem tratamento de falha) | H33: comentário menciona condição: reavaliar
A34: XFRFUN-038 | B34: XFRFUN | C34: 1020-1021 | D34: 1023-1027 | E34: Check if SQLCODE indicates that Storm Drain processing is applicable in a workload if activated | F34: PERFORM CHECK-FOR-STORM-DRAIN-DB2 GO TO UADF999 END-IF. | G34: Procedural (sem decisão nem tratamento de falha) | H34: comentário menciona condição: reavaliar
A35: XFRFUN-039 | B35: XFRFUN | C35: 1030-1031 | D35: 1033-1044 | E35: If the update to the FROM account was OK store the updated balances away. | F35: MOVE HV-ACCOUNT-AVAIL-BAL TO COMM-FAVBAL. MOVE HV-ACCOUNT-ACTUAL-BAL TO COMM-FACTBAL. MOVE 'Y' TO COMM-SUCCESS. UADF999. EXIT. UPDATE-ACCOUNT-DB2-TO SECTION. UADT010. MOVE 'N' TO COMM-SUCCESS. | G35: Procedural (sem decisão nem tratamento de falha) | H35: comentário menciona condição: reavaliar
A36: XFRFUN-040 | B36: XFRFUN | C36: 1046-1047 | D36: 1049-1081 | E36: Position ourself at the matching account record for the TO account | F36: INITIALIZE HOST-ACCOUNT-ROW. MOVE COMM-TACCNO TO DESIRED-ACC-NO. MOVE COMM-TSCODE TO DESIRED-SORT-CODE. MOVE DESIRED-SORT-CODE TO HV-ACCOUNT-SORTCODE. MOVE DESIRED-ACC-NO TO HV-ACCOUNT-ACC-NO. EXEC SQL SELECT ACCOUNT_EYECATCHER, ACCOUNT_CUSTOMER_NUMBER, ACCOUNT_SORTCODE, ACCOUNT_NUMBER, ACCOUNT_TYPE, ACCOUNT_INTEREST_RATE, ACCOUNT_OPENED, ACCOUNT_OVERDRAFT_LIMIT, ACCOUNT_LAST_STATEMENT, ACCOUNT_NEXT_STATEMENT, ACCOUNT_AVAILABLE_BALANCE, ACCOUNT_ACTUAL_BALANCE INTO :HV-ACCOUNT-EYECATCHER, :HV-ACCOUNT-CUST-NO, :HV-ACCOUNT-SORTCODE, :HV-ACCOUNT-ACC-NO, :HV-ACCOUNT-ACC-TYPE, :HV-ACCOUNT-INT-RATE, :HV-ACCOUNT-OPENED, :HV-ACCOUNT-OVERDRAFT-LIM, :HV-ACCOUNT-LAST-STMT, :HV-ACCOUNT-NEXT-STMT, :HV-ACCOUNT-AVAIL-BAL, :HV-ACCOUNT-ACTUAL-BAL | G36: Procedural (sem decisão nem tratamento de falha) | H36: trecho truncado (30 linhas)
... A41: XFRFUN-055 | B41: XFRFUN | C41: 1421 | D41: 1423-1460 | E41: Get supplemental information | F41: EXEC CICS ASSIGN APPLID(ABND-APPLID) END-EXEC MOVE EIBTASKN TO ABND-TASKNO-KEY MOVE EIBTRNID TO ABND-TRANID PERFORM POPULATE-TIME-DATE MOVE WS-ORIG-DATE TO ABND-DATE STRING WS-TIME-NOW-GRP-HH DELIMITED BY SIZE, ':' DELIMITED BY SIZE, WS-TIME-NOW-GRP-MM DELIMITED BY SIZE, ':' DELIMITED BY SIZE, WS-TIME-NOW-GRP-MM DELIMITED BY SIZE INTO ABND-TIME END-STRING MOVE WS-U-TIME TO ABND-UTIME-KEY MOVE 'HROL' TO ABND-CODE EXEC CICS ASSIGN PROGRAM(ABND-PROGRAM) END-EXEC MOVE ZEROS TO ABND-SQLCODE STRING 'UAD010-TO(4) - Error on SYNCPOINT ' DELIMITED BY SIZE, 'ROLLBACK after Updating TO account' DELIMITED BY SIZE, ' EIBRESP=' DELIMITED BY SIZE, ABND-RESPCODE DELIMITED BY SIZE, ' RESP2=' DELIMITED BY SIZE, ABND-RESP2CODE DELIMITED BY SIZE INTO ABND-FREEFORM END-STRING EXEC CICS LINK PROGRAM(WS-ABEND-PGM) COMMAREA(ABNDINFO-REC) | G41: Procedural (sem decisão nem tratamento de falha) | H41: comentário curto; trecho truncado (30 linhas)
A42: XFRFUN-058 | B42: XFRFUN | C42: 1552 | D42: 1554-1572 | E42: Store the data away | F42: MOVE HV-ACCOUNT-AVAIL-BAL TO COMM-TAVBAL. MOVE HV-ACCOUNT-ACTUAL-BAL TO COMM-TACTBAL. MOVE 'Y' TO COMM-SUCCESS. UADT999. EXIT. WRITE-TO-PROCTRAN SECTION. WTP010. PERFORM WRITE-TO-PROCTRAN-DB2. WTP999. EXIT. WRITE-TO-PROCTRAN-DB2 SECTION. WTPD010. | G42: Procedural (sem decisão nem tratamento de falha)
A43: XFRFUN-059 | B43: XFRFUN | C43: 1574-1575 | D43: 1577-1584 | E43: Writes details of the successful transfer to the PROCTRAN (Processed Transaction) datastore. | F43: INITIALIZE HOST-PROCTRAN-ROW. INITIALIZE WS-EIBTASKN12. MOVE 'PRTR' TO HV-PROCTRAN-EYECATCHER. MOVE COMM-FSCODE TO HV-PROCTRAN-SORT-CODE. MOVE COMM-FACCNO TO HV-PROCTRAN-ACC-NUMBER. MOVE EIBTASKN TO WS-EIBTASKN12. MOVE WS-EIBTASKN12 TO HV-PROCTRAN-REF. | G43: Procedural (sem decisão nem tratamento de falha)
A44: XFRFUN-060 | B44: XFRFUN | C44: 1587 | D44: 1589-1625 | E44: Populate the time and date | F44: EXEC CICS ASKTIME ABSTIME(WS-U-TIME) END-EXEC. EXEC CICS FORMATTIME ABSTIME(WS-U-TIME) DDMMYYYY(WS-ORIG-DATE) TIME(HV-PROCTRAN-TIME) DATESEP('.') END-EXEC. MOVE WS-ORIG-DATE TO WS-ORIG-DATE-GRP-X. MOVE WS-ORIG-DATE-GRP-X TO HV-PROCTRAN-DATE. SET PROC-TY-TRANSFER IN PROCTRAN-AREA TO TRUE MOVE PROC-TRAN-TYPE IN PROCTRAN-AREA TO HV-PROCTRAN-TYPE. MOVE COMM-AMT TO HV-PROCTRAN-AMOUNT. SET PROC-TRAN-DESC-XFR-FLAG IN PROCTRAN-AREA TO TRUE. MOVE COMM-TSCODE TO PROC-TRAN-DESC-XFR-SORTCODE IN PROCTRAN-AREA. MOVE COMM-TACCNO TO PROC-TRAN-DESC-XFR-ACCOUNT IN PROCTRAN-AREA. MOVE PROC-TRAN-DESC IN PROCTRAN-AREA TO HV-PROCTRAN-DESC. EXEC SQL INSERT INTO PROCTRAN ( PROCTRAN_EYECATCHER, PROCTRAN_SORTCODE, PROCTRAN_NUMBER, PROCTRAN_DATE, PROCTRAN_TIME, PROCTRAN_REF, PROCTRAN_TYPE, | G44: Procedural (sem decisão nem tratamento de falha) | H44: trecho truncado (30 linhas)
A45: XFRFUN-063 | B45: XFRFUN | C45: 1659 | D45: 1661-1697 | E45: Get supplemental information | F45: EXEC CICS ASSIGN APPLID(ABND-APPLID) END-EXEC MOVE EIBTASKN TO ABND-TASKNO-KEY MOVE EIBTRNID TO ABND-TRANID PERFORM POPULATE-TIME-DATE MOVE WS-ORIG-DATE TO ABND-DATE STRING WS-TIME-NOW-GRP-HH DELIMITED BY SIZE, ':' DELIMITED BY SIZE, WS-TIME-NOW-GRP-MM DELIMITED BY SIZE, ':' DELIMITED BY SIZE, WS-TIME-NOW-GRP-MM DELIMITED BY SIZE INTO ABND-TIME END-STRING MOVE WS-U-TIME TO ABND-UTIME-KEY MOVE 'WPCD' TO ABND-CODE EXEC CICS ASSIGN PROGRAM(ABND-PROGRAM) END-EXEC MOVE WS-SQLCODE-DISP TO ABND-SQLCODE STRING 'WTPD010 - Unable to WRITE to PROCTRAN DB2 ' DELIMITED BY SIZE, 'datastore. Data=' DELIMITED BY SIZE, HOST-PROCTRAN-ROW DELIMITED BY SIZE, '.Data inconsistency, data UPDATED on ACCOUNT file' DELIMITED BY SIZE, ' EIBRESP=' DELIMITED BY SIZE, ABND-RESPCODE DELIMITED BY SIZE, ' RESP2=' DELIMITED BY SIZE, ABND-RESP2CODE DELIMITED BY SIZE | G45: Procedural (sem decisão nem tratamento de falha) | H45: comentário curto; trecho truncado (30 linhas)
A46: XFRFUN-066 | B46: XFRFUN | C46: 1772 | D46: 1774-1776 | E46: Deal with any abends | F46: EXEC CICS ASSIGN ABCODE(MY-ABEND-CODE) END-EXEC. | G46: Procedural (sem decisão nem tratamento de falha)
A47: XFRFUN-070 | B47: XFRFUN | C47: 1832 | D47: 1834-1870 | E47: Get supplemental information | F47: EXEC CICS ASSIGN APPLID(ABND-APPLID) END-EXEC MOVE EIBTASKN TO ABND-TASKNO-KEY MOVE EIBTRNID TO ABND-TRANID PERFORM POPULATE-TIME-DATE MOVE WS-ORIG-DATE TO ABND-DATE STRING WS-TIME-NOW-GRP-HH DELIMITED BY SIZE, ':' DELIMITED BY SIZE, WS-TIME-NOW-GRP-MM DELIMITED BY SIZE, ':' DELIMITED BY SIZE, WS-TIME-NOW-GRP-MM DELIMITED BY SIZE INTO ABND-TIME END-STRING MOVE WS-U-TIME TO ABND-UTIME-KEY MOVE 'HROL' TO ABND-CODE EXEC CICS ASSIGN PROGRAM(ABND-PROGRAM) END-EXEC MOVE ZEROS TO ABND-SQLCODE STRING 'AH010 - Unable to perform SYNCPOINT ' DELIMITED BY SIZE, 'ROLLBACK.' DELIMITED BY SIZE, ' Possible integrity issue following VSAM RLS ' DELIMITED BY SIZE, 'abend.' DELIMITED BY SIZE, ' EIBRESP=' DELIMITED BY SIZE, ABND-RESPCODE DELIMITED BY SIZE, ' RESP2=' DELIMITED BY SIZE, ABND-RESP2CODE DELIMITED BY SIZE INTO ABND-FREEFORM | G47: Procedural (sem decisão nem tratamento de falha) | H47: comentário curto; trecho truncado (30 linhas)
A48: BNK1CRA-010 | B48: BNK1CRA | C48: 282 | D48: 284-322 | E48: Get supplemental information | F48: EXEC CICS ASSIGN APPLID(ABND-APPLID) END-EXEC MOVE EIBTASKN TO ABND-TASKNO-KEY MOVE EIBTRNID TO ABND-TRANID PERFORM POPULATE-TIME-DATE MOVE WS-ORIG-DATE TO ABND-DATE STRING WS-TIME-NOW-GRP-HH DELIMITED BY SIZE, ':' DELIMITED BY SIZE, WS-TIME-NOW-GRP-MM DELIMITED BY SIZE, ':' DELIMITED BY SIZE, WS-TIME-NOW-GRP-MM DELIMITED BY SIZE INTO ABND-TIME END-STRING MOVE WS-U-TIME TO ABND-UTIME-KEY MOVE 'HBNK' TO ABND-CODE EXEC CICS ASSIGN PROGRAM(ABND-PROGRAM) END-EXEC MOVE ZEROS TO ABND-SQLCODE STRING 'A010 - RETURN TRANSID(OCRA) FAIL.' DELIMITED BY SIZE, 'EIBRESP=' DELIMITED BY SIZE, ABND-RESPCODE DELIMITED BY SIZE, ' RESP2=' DELIMITED BY SIZE, ABND-RESP2CODE DELIMITED BY SIZE INTO ABND-FREEFORM END-STRING EXEC CICS LINK PROGRAM(WS-ABEND-PGM) COMMAREA(ABNDINFO-REC) END-EXEC INITIALIZE WS-FAIL-INFO | G48: Procedural (sem decisão nem tratamento de falha) | H48: comentário curto; trecho truncado (30 linhas)
A49: BNK1CRA-011 | B49: BNK1CRA | C49: 337 | D49: 339 | E49: Retrieve the data from the map | F49: PERFORM RECEIVE-MAP. | G49: Procedural (sem decisão nem tratamento de falha)
A50: BNK1CRA-012 | B50: BNK1CRA | C50: 342 | D50: 344 | E50: Validate the received data | F50: PERFORM EDIT-DATA. | G50: Procedural (sem decisão nem tratamento de falha)
A51: BNK1CRA-014 | B51: BNK1CRA | C51: 357 | D51: 359-366 | E51: Output the data to the screen | F51: PERFORM SEND-MAP. PM999. EXIT. RECEIVE-MAP SECTION. RM010. | G51: Procedural (sem decisão nem tratamento de falha)
A52: BNK1CRA-017 | B52: BNK1CRA | C52: 389 | D52: 391-429 | E52: Get supplemental information | F52: EXEC CICS ASSIGN APPLID(ABND-APPLID) END-EXEC MOVE EIBTASKN TO ABND-TASKNO-KEY MOVE EIBTRNID TO ABND-TRANID PERFORM POPULATE-TIME-DATE MOVE WS-ORIG-DATE TO ABND-DATE STRING WS-TIME-NOW-GRP-HH DELIMITED BY SIZE, ':' DELIMITED BY SIZE, WS-TIME-NOW-GRP-MM DELIMITED BY SIZE, ':' DELIMITED BY SIZE, WS-TIME-NOW-GRP-MM DELIMITED BY SIZE INTO ABND-TIME END-STRING MOVE WS-U-TIME TO ABND-UTIME-KEY MOVE 'HBNK' TO ABND-CODE EXEC CICS ASSIGN PROGRAM(ABND-PROGRAM) END-EXEC MOVE ZEROS TO ABND-SQLCODE STRING 'RM010 - RECEIVE MAP FAIL.' DELIMITED BY SIZE, 'EIBRESP=' DELIMITED BY SIZE, ABND-RESPCODE DELIMITED BY SIZE, ' RESP2=' DELIMITED BY SIZE, ABND-RESP2CODE DELIMITED BY SIZE INTO ABND-FREEFORM END-STRING EXEC CICS LINK PROGRAM(WS-ABEND-PGM) COMMAREA(ABNDINFO-REC) END-EXEC INITIALIZE WS-FAIL-INFO | G52: Procedural (sem decisão nem tratamento de falha) | H52: comentário curto; trecho truncado (30 linhas)
A53: BNK1CRA-019 | B53: BNK1CRA | C53: 472 | D53: 474-481 | E53: Validate the Amount entered | F53: PERFORM VALIDATE-AMOUNT. ED999. EXIT. UPD-CRED-DATA SECTION. UCD010. | G53: Procedural (sem decisão nem tratamento de falha)
A54: BNK1CRA-020 | B54: BNK1CRA | C54: 483-484 | D54: 486-489 | E54: Set up the COMMAREA fields required by DBCRFUN and then link to it. | F54: INITIALIZE SUBPGM-PARMS. MOVE ACCNOI TO SUBPGM-ACCNO. MOVE 0 TO SUBPGM-AMT. | G54: Procedural (sem decisão nem tratamento de falha)
A55: BNK1CRA-024 | B55: BNK1CRA | C55: 530 | D55: 532-570 | E55: Get supplemental information | F55: EXEC CICS ASSIGN APPLID(ABND-APPLID) END-EXEC MOVE EIBTASKN TO ABND-TASKNO-KEY MOVE EIBTRNID TO ABND-TRANID PERFORM POPULATE-TIME-DATE MOVE WS-ORIG-DATE TO ABND-DATE STRING WS-TIME-NOW-GRP-HH DELIMITED BY SIZE, ':' DELIMITED BY SIZE, WS-TIME-NOW-GRP-MM DELIMITED BY SIZE, ':' DELIMITED BY SIZE, WS-TIME-NOW-GRP-MM DELIMITED BY SIZE INTO ABND-TIME END-STRING MOVE WS-U-TIME TO ABND-UTIME-KEY MOVE 'HBNK' TO ABND-CODE EXEC CICS ASSIGN PROGRAM(ABND-PROGRAM) END-EXEC MOVE ZEROS TO ABND-SQLCODE STRING 'UCD010 - LINK DBCRFUN FAIL.' DELIMITED BY SIZE, 'EIBRESP=' DELIMITED BY SIZE, ABND-RESPCODE DELIMITED BY SIZE, ' RESP2=' DELIMITED BY SIZE, ABND-RESP2CODE DELIMITED BY SIZE INTO ABND-FREEFORM END-STRING EXEC CICS LINK PROGRAM(WS-ABEND-PGM) COMMAREA(ABNDINFO-REC) END-EXEC INITIALIZE WS-FAIL-INFO | G55: Procedural (sem decisão nem tratamento de falha) | H55: comentário curto; trecho truncado (30 linhas)
A56: BNK1CRA-026 | B56: BNK1CRA | C56: 629 | D56: 631-644 | E56: Set up the values on the map | F56: MOVE SUBPGM-ACCNO TO ACCNOO. MOVE SUBPGM-SORTC TO SORTCO. MOVE SUBPGM-ACT-BAL TO ACTUAL-BALANCE-DISPLAY. MOVE SUBPGM-AV-BAL TO AVAILABLE-BALANCE-DISPLAY. MOVE ACTUAL-BALANCE-DISPLAY TO ACTBALO. MOVE AVAILABLE-BALANCE-DISPLAY TO AVBALO. UCD999. EXIT. SEND-MAP SECTION. SM010. | G56: Procedural (sem decisão nem tratamento de falha)
A57: BNK1CRA-029 | B57: BNK1CRA | C57: 668 | D57: 670-708 | E57: Get supplemental information | F57: EXEC CICS ASSIGN APPLID(ABND-APPLID) END-EXEC MOVE EIBTASKN TO ABND-TASKNO-KEY MOVE EIBTRNID TO ABND-TRANID PERFORM POPULATE-TIME-DATE MOVE WS-ORIG-DATE TO ABND-DATE STRING WS-TIME-NOW-GRP-HH DELIMITED BY SIZE, ':' DELIMITED BY SIZE, WS-TIME-NOW-GRP-MM DELIMITED BY SIZE, ':' DELIMITED BY SIZE, WS-TIME-NOW-GRP-MM DELIMITED BY SIZE INTO ABND-TIME END-STRING MOVE WS-U-TIME TO ABND-UTIME-KEY MOVE 'HBNK' TO ABND-CODE EXEC CICS ASSIGN PROGRAM(ABND-PROGRAM) END-EXEC MOVE ZEROS TO ABND-SQLCODE STRING 'SM010 - SEND MAP ERASE FAIL.' DELIMITED BY SIZE, 'EIBRESP=' DELIMITED BY SIZE, ABND-RESPCODE DELIMITED BY SIZE, ' RESP2=' DELIMITED BY SIZE, ABND-RESP2CODE DELIMITED BY SIZE INTO ABND-FREEFORM END-STRING EXEC CICS LINK PROGRAM(WS-ABEND-PGM) COMMAREA(ABNDINFO-REC) END-EXEC INITIALIZE WS-FAIL-INFO | G57: Procedural (sem decisão nem tratamento de falha) | H57: comentário curto; trecho truncado (30 linhas)
A58: BNK1CRA-032 | B58: BNK1CRA | C58: 742 | D58: 744-782 | E58: Get supplemental information | F58: EXEC CICS ASSIGN APPLID(ABND-APPLID) END-EXEC MOVE EIBTASKN TO ABND-TASKNO-KEY MOVE EIBTRNID TO ABND-TRANID PERFORM POPULATE-TIME-DATE MOVE WS-ORIG-DATE TO ABND-DATE STRING WS-TIME-NOW-GRP-HH DELIMITED BY SIZE, ':' DELIMITED BY SIZE, WS-TIME-NOW-GRP-MM DELIMITED BY SIZE, ':' DELIMITED BY SIZE, WS-TIME-NOW-GRP-MM DELIMITED BY SIZE INTO ABND-TIME END-STRING MOVE WS-U-TIME TO ABND-UTIME-KEY MOVE 'HBNK' TO ABND-CODE EXEC CICS ASSIGN PROGRAM(ABND-PROGRAM) END-EXEC MOVE ZEROS TO ABND-SQLCODE STRING 'SM010 - SEND MAP DATAONLY FAIL.' DELIMITED BY SIZE, 'EIBRESP=' DELIMITED BY SIZE, ABND-RESPCODE DELIMITED BY SIZE, ' RESP2=' DELIMITED BY SIZE, ABND-RESP2CODE DELIMITED BY SIZE INTO ABND-FREEFORM END-STRING EXEC CICS LINK PROGRAM(WS-ABEND-PGM) COMMAREA(ABNDINFO-REC) END-EXEC INITIALIZE WS-FAIL-INFO | G58: Procedural (sem decisão nem tratamento de falha) | H58: comentário curto; trecho truncado (30 linhas)
A59: BNK1CRA-035 | B59: BNK1CRA | C59: 817 | D59: 819-857 | E59: Get supplemental information | F59: EXEC CICS ASSIGN APPLID(ABND-APPLID) END-EXEC MOVE EIBTASKN TO ABND-TASKNO-KEY MOVE EIBTRNID TO ABND-TRANID PERFORM POPULATE-TIME-DATE MOVE WS-ORIG-DATE TO ABND-DATE STRING WS-TIME-NOW-GRP-HH DELIMITED BY SIZE, ':' DELIMITED BY SIZE, WS-TIME-NOW-GRP-MM DELIMITED BY SIZE, ':' DELIMITED BY SIZE, WS-TIME-NOW-GRP-MM DELIMITED BY SIZE INTO ABND-TIME END-STRING MOVE WS-U-TIME TO ABND-UTIME-KEY MOVE 'HBNK' TO ABND-CODE EXEC CICS ASSIGN PROGRAM(ABND-PROGRAM) END-EXEC MOVE ZEROS TO ABND-SQLCODE STRING 'SM010 - SEND MAP DATAONLY ALARM FAIL.' DELIMITED BY SIZE, 'EIBRESP=' DELIMITED BY SIZE, ABND-RESPCODE DELIMITED BY SIZE, ' RESP2=' DELIMITED BY SIZE, ABND-RESP2CODE DELIMITED BY SIZE INTO ABND-FREEFORM END-STRING EXEC CICS LINK PROGRAM(WS-ABEND-PGM) COMMAREA(ABNDINFO-REC) END-EXEC INITIALIZE WS-FAIL-INFO | G59: Procedural (sem decisão nem tratamento de falha) | H59: comentário curto; trecho truncado (30 linhas)
A60: BNK1CRA-038 | B60: BNK1CRA | C60: 895 | D60: 897-935 | E60: Get supplemental information | F60: EXEC CICS ASSIGN APPLID(ABND-APPLID) END-EXEC MOVE EIBTASKN TO ABND-TASKNO-KEY MOVE EIBTRNID TO ABND-TRANID PERFORM POPULATE-TIME-DATE MOVE WS-ORIG-DATE TO ABND-DATE STRING WS-TIME-NOW-GRP-HH DELIMITED BY SIZE, ':' DELIMITED BY SIZE, WS-TIME-NOW-GRP-MM DELIMITED BY SIZE, ':' DELIMITED BY SIZE, WS-TIME-NOW-GRP-MM DELIMITED BY SIZE INTO ABND-TIME END-STRING MOVE WS-U-TIME TO ABND-UTIME-KEY MOVE 'HBNK' TO ABND-CODE EXEC CICS ASSIGN PROGRAM(ABND-PROGRAM) END-EXEC MOVE ZEROS TO ABND-SQLCODE STRING 'STM010 - SEND TEXT FAIL.' DELIMITED BY SIZE, 'EIBRESP=' DELIMITED BY SIZE, ABND-RESPCODE DELIMITED BY SIZE, ' RESP2=' DELIMITED BY SIZE, ABND-RESP2CODE DELIMITED BY SIZE INTO ABND-FREEFORM END-STRING EXEC CICS LINK PROGRAM(WS-ABEND-PGM) COMMAREA(ABNDINFO-REC) END-EXEC INITIALIZE WS-FAIL-INFO | G60: Procedural (sem decisão nem tratamento de falha) | H60: comentário curto; trecho truncado (30 linhas)
A61: BNK1TFN-008 | B61: BNK1TFN | C61: 238 | D61: 239-242 | E61: MOVE 10 TO CUSTNOL | F61: SET SEND-DATAONLY-ALARM TO TRUE PERFORM SEND-MAP END-EVALUATE. | G61: Procedural (sem decisão nem tratamento de falha) | H61: possível código desativado
A62: BNK1TFN-011 | B62: BNK1TFN | C62: 266 | D62: 268-307 | E62: Get supplemental information | F62: EXEC CICS ASSIGN APPLID(ABND-APPLID) END-EXEC MOVE EIBTASKN TO ABND-TASKNO-KEY MOVE EIBTRNID TO ABND-TRANID PERFORM POPULATE-TIME-DATE MOVE WS-ORIG-DATE TO ABND-DATE STRING WS-TIME-NOW-GRP-HH DELIMITED BY SIZE, ':' DELIMITED BY SIZE, WS-TIME-NOW-GRP-MM DELIMITED BY SIZE, ':' DELIMITED BY SIZE, WS-TIME-NOW-GRP-MM DELIMITED BY SIZE INTO ABND-TIME END-STRING MOVE WS-U-TIME TO ABND-UTIME-KEY MOVE 'HBNK' TO ABND-CODE EXEC CICS ASSIGN PROGRAM(ABND-PROGRAM) END-EXEC MOVE ZEROS TO ABND-SQLCODE STRING 'A010 - RETURN TRANSID(OCCS) FAIL.' DELIMITED BY SIZE, ' EIBRESP=' DELIMITED BY SIZE, ABND-RESPCODE DELIMITED BY SIZE, ' RESP2=' DELIMITED BY SIZE, ABND-RESP2CODE DELIMITED BY SIZE INTO ABND-FREEFORM END-STRING EXEC CICS LINK PROGRAM(WS-ABEND-PGM) COMMAREA(ABNDINFO-REC) END-EXEC INITIALIZE WS-FAIL-INFO | G62: Procedural (sem decisão nem tratamento de falha) | H62: comentário curto; trecho truncado (30 linhas)
A63: BNK1TFN-012 | B63: BNK1TFN | C63: 322 | D63: 325 | E63: Retrieve the data from the map | F63: PERFORM RECEIVE-MAP. | G63: Procedural (sem decisão nem tratamento de falha)
A64: BNK1TFN-013 | B64: BNK1TFN | C64: 328 | D64: 330 | E64: Validate the received data | F64: PERFORM EDIT-DATA. | G64: Procedural (sem decisão nem tratamento de falha)
A65: BNK1TFN-015 | B65: BNK1TFN | C65: 343 | D65: 345-352 | E65: Output the data to the screen | F65: PERFORM SEND-MAP. PM999. EXIT. RECEIVE-MAP SECTION. RM010. | G65: Procedural (sem decisão nem tratamento de falha)
A66: BNK1TFN-018 | B66: BNK1TFN | C66: 375 | D66: 377-416 | E66: Get supplemental information | F66: EXEC CICS ASSIGN APPLID(ABND-APPLID) END-EXEC MOVE EIBTASKN TO ABND-TASKNO-KEY MOVE EIBTRNID TO ABND-TRANID PERFORM POPULATE-TIME-DATE MOVE WS-ORIG-DATE TO ABND-DATE STRING WS-TIME-NOW-GRP-HH DELIMITED BY SIZE, ':' DELIMITED BY SIZE, WS-TIME-NOW-GRP-MM DELIMITED BY SIZE, ':' DELIMITED BY SIZE, WS-TIME-NOW-GRP-MM DELIMITED BY SIZE INTO ABND-TIME END-STRING MOVE WS-U-TIME TO ABND-UTIME-KEY MOVE 'HBNK' TO ABND-CODE EXEC CICS ASSIGN PROGRAM(ABND-PROGRAM) END-EXEC MOVE ZEROS TO ABND-SQLCODE STRING 'RM010 - RECEIVE MAP FAIL.' DELIMITED BY SIZE, ' EIBRESP=' DELIMITED BY SIZE, ABND-RESPCODE DELIMITED BY SIZE, ' RESP2=' DELIMITED BY SIZE, ABND-RESP2CODE DELIMITED BY SIZE INTO ABND-FREEFORM END-STRING EXEC CICS LINK PROGRAM(WS-ABEND-PGM) COMMAREA(ABNDINFO-REC) END-EXEC INITIALIZE WS-FAIL-INFO | G66: Procedural (sem decisão nem tratamento de falha) | H66: comentário curto; trecho truncado (30 linhas)
A67: BNK1TFN-020 | B67: BNK1TFN | C67: 470 | D67: 472-479 | E67: Validate the Amount entered | F67: PERFORM VALIDATE-AMOUNT. ED999. EXIT. GET-ACC-DATA SECTION. GCD010. | G67: Procedural (sem decisão nem tratamento de falha)
A68: BNK1TFN-021 | B68: BNK1TFN | C68: 481-483 | D68: 485-489 | E68: Set up the fields required by XFRFUN then link to it to get account information and perform the transfer, then check what gets returned. | F68: INITIALIZE SUBPGM-PARMS. MOVE FACCNOI TO SUBPGM-FACCNO. MOVE TACCNOI TO SUBPGM-TACCNO. MOVE 'N' TO SUBPGM-SUCCESS. | G68: Procedural (sem decisão nem tratamento de falha) | H68: comentário menciona condição: reavaliar
A69: BNK1TFN-024 | B69: BNK1TFN | C69: 515 | D69: 517-555 | E69: Get supplemental information | F69: EXEC CICS ASSIGN APPLID(ABND-APPLID) END-EXEC MOVE EIBTASKN TO ABND-TASKNO-KEY MOVE EIBTRNID TO ABND-TRANID PERFORM POPULATE-TIME-DATE MOVE WS-ORIG-DATE TO ABND-DATE STRING WS-TIME-NOW-GRP-HH DELIMITED BY SIZE, ':' DELIMITED BY SIZE, WS-TIME-NOW-GRP-MM DELIMITED BY SIZE, ':' DELIMITED BY SIZE, WS-TIME-NOW-GRP-MM DELIMITED BY SIZE INTO ABND-TIME END-STRING MOVE WS-U-TIME TO ABND-UTIME-KEY MOVE 'HBNK' TO ABND-CODE EXEC CICS ASSIGN PROGRAM(ABND-PROGRAM) END-EXEC MOVE ZEROS TO ABND-SQLCODE STRING 'GCD010 - LINK XFRFUN FAIL.' DELIMITED BY SIZE, ' EIBRESP=' DELIMITED BY SIZE, ABND-RESPCODE DELIMITED BY SIZE, ' RESP2=' DELIMITED BY SIZE, ABND-RESP2CODE DELIMITED BY SIZE INTO ABND-FREEFORM END-STRING EXEC CICS LINK PROGRAM(WS-ABEND-PGM) COMMAREA(ABNDINFO-REC) END-EXEC INITIALIZE WS-FAIL-INFO | G69: Procedural (sem decisão nem tratamento de falha) | H69: comentário curto; trecho truncado (30 linhas)
A70: BNK1TFN-025 | B70: BNK1TFN | C70: 564 | D70: 566-577 | E70: Map the returned data to the screen output fields | F70: MOVE SUBPGM-FACCNO TO FACCNO2O MOVE SUBPGM-FSCODE TO FSORTCO MOVE SUBPGM-TACCNO TO TACCNO2O MOVE SUBPGM-TSCODE TO TSORTCO MOVE ZERO TO FROM-ACTUAL-BALANCE-DISPLAY MOVE ZERO TO FROM-AVAILABLE-BALANCE-DISPLAY MOVE ZERO TO TO-ACTUAL-BALANCE-DISPLAY MOVE ZERO TO TO-AVAILABLE-BALANCE-DISPLAY MOVE FROM-ACTUAL-BALANCE-DISPLAY TO FACTBALO MOVE FROM-AVAILABLE-BALANCE-DISPLAY TO FAVBALO MOVE TO-ACTUAL-BALANCE-DISPLAY TO TACTBALO MOVE TO-AVAILABLE-BALANCE-DISPLAY TO TAVBALO | G70: Procedural (sem decisão nem tratamento de falha)
A71: BNK1TFN-027 | B71: BNK1TFN | C71: 643 | D71: 645-663 | E71: Map the remaining fields | F71: MOVE SUBPGM-FACCNO TO FACCNO2O. MOVE SUBPGM-FSCODE TO FSORTCO. MOVE SUBPGM-TACCNO TO TACCNO2O. MOVE SUBPGM-TSCODE TO TSORTCO. MOVE SUBPGM-FACTBAL TO FROM-ACTUAL-BALANCE-DISPLAY. MOVE SUBPGM-FAVBAL TO FROM-AVAILABLE-BALANCE-DISPLAY. MOVE SUBPGM-TACTBAL TO TO-ACTUAL-BALANCE-DISPLAY. MOVE SUBPGM-TAVBAL TO TO-AVAILABLE-BALANCE-DISPLAY. MOVE FROM-ACTUAL-BALANCE-DISPLAY TO FACTBALO. MOVE FROM-AVAILABLE-BALANCE-DISPLAY TO FAVBALO. MOVE TO-ACTUAL-BALANCE-DISPLAY TO TACTBALO. MOVE TO-AVAILABLE-BALANCE-DISPLAY TO TAVBALO. GCD999. EXIT. SEND-MAP SECTION. SM010. | G71: Procedural (sem decisão nem tratamento de falha)
A72: BNK1TFN-030 | B72: BNK1TFN | C72: 691 | D72: 693-731 | E72: Get supplemental information | F72: EXEC CICS ASSIGN APPLID(ABND-APPLID) END-EXEC MOVE EIBTASKN TO ABND-TASKNO-KEY MOVE EIBTRNID TO ABND-TRANID PERFORM POPULATE-TIME-DATE MOVE WS-ORIG-DATE TO ABND-DATE STRING WS-TIME-NOW-GRP-HH DELIMITED BY SIZE, ':' DELIMITED BY SIZE, WS-TIME-NOW-GRP-MM DELIMITED BY SIZE, ':' DELIMITED BY SIZE, WS-TIME-NOW-GRP-MM DELIMITED BY SIZE INTO ABND-TIME END-STRING MOVE WS-U-TIME TO ABND-UTIME-KEY MOVE 'HBNK' TO ABND-CODE EXEC CICS ASSIGN PROGRAM(ABND-PROGRAM) END-EXEC MOVE ZEROS TO ABND-SQLCODE STRING 'SM010 - SEND MAP ERASE FAIL.' DELIMITED BY SIZE, ' EIBRESP=' DELIMITED BY SIZE, ABND-RESPCODE DELIMITED BY SIZE, ' RESP2=' DELIMITED BY SIZE, ABND-RESP2CODE DELIMITED BY SIZE INTO ABND-FREEFORM END-STRING EXEC CICS LINK PROGRAM(WS-ABEND-PGM) COMMAREA(ABNDINFO-REC) END-EXEC INITIALIZE WS-FAIL-INFO | G72: Procedural (sem decisão nem tratamento de falha) | H72: comentário curto; trecho truncado (30 linhas)
A73: BNK1TFN-033 | B73: BNK1TFN | C73: 765 | D73: 767-805 | E73: Get supplemental information | F73: EXEC CICS ASSIGN APPLID(ABND-APPLID) END-EXEC MOVE EIBTASKN TO ABND-TASKNO-KEY MOVE EIBTRNID TO ABND-TRANID PERFORM POPULATE-TIME-DATE MOVE WS-ORIG-DATE TO ABND-DATE STRING WS-TIME-NOW-GRP-HH DELIMITED BY SIZE, ':' DELIMITED BY SIZE, WS-TIME-NOW-GRP-MM DELIMITED BY SIZE, ':' DELIMITED BY SIZE, WS-TIME-NOW-GRP-MM DELIMITED BY SIZE INTO ABND-TIME END-STRING MOVE WS-U-TIME TO ABND-UTIME-KEY MOVE 'HBNK' TO ABND-CODE EXEC CICS ASSIGN PROGRAM(ABND-PROGRAM) END-EXEC MOVE ZEROS TO ABND-SQLCODE STRING 'SM010 - SEND MAP DATAONLY FAIL.' DELIMITED BY SIZE, ' EIBRESP=' DELIMITED BY SIZE, ABND-RESPCODE DELIMITED BY SIZE, ' RESP2=' DELIMITED BY SIZE, ABND-RESP2CODE DELIMITED BY SIZE INTO ABND-FREEFORM END-STRING EXEC CICS LINK PROGRAM(WS-ABEND-PGM) COMMAREA(ABNDINFO-REC) END-EXEC INITIALIZE WS-FAIL-INFO | G73: Procedural (sem decisão nem tratamento de falha) | H73: comentário curto; trecho truncado (30 linhas)
A74: BNK1TFN-036 | B74: BNK1TFN | C74: 840 | D74: 842-880 | E74: Get supplemental information | F74: EXEC CICS ASSIGN APPLID(ABND-APPLID) END-EXEC MOVE EIBTASKN TO ABND-TASKNO-KEY MOVE EIBTRNID TO ABND-TRANID PERFORM POPULATE-TIME-DATE MOVE WS-ORIG-DATE TO ABND-DATE STRING WS-TIME-NOW-GRP-HH DELIMITED BY SIZE, ':' DELIMITED BY SIZE, WS-TIME-NOW-GRP-MM DELIMITED BY SIZE, ':' DELIMITED BY SIZE, WS-TIME-NOW-GRP-MM DELIMITED BY SIZE INTO ABND-TIME END-STRING MOVE WS-U-TIME TO ABND-UTIME-KEY MOVE 'HBNK' TO ABND-CODE EXEC CICS ASSIGN PROGRAM(ABND-PROGRAM) END-EXEC MOVE ZEROS TO ABND-SQLCODE STRING 'SM010 - SEND MAP DATAONLY ALARM FAIL.' DELIMITED BY SIZE, ' EIBRESP=' DELIMITED BY SIZE, ABND-RESPCODE DELIMITED BY SIZE, ' RESP2=' DELIMITED BY SIZE, ABND-RESP2CODE DELIMITED BY SIZE INTO ABND-FREEFORM END-STRING EXEC CICS LINK PROGRAM(WS-ABEND-PGM) COMMAREA(ABNDINFO-REC) END-EXEC INITIALIZE WS-FAIL-INFO | G74: Procedural (sem decisão nem tratamento de falha) | H74: comentário curto; trecho truncado (30 linhas)
A75: BNK1TFN-039 | B75: BNK1TFN | C75: 918 | D75: 920-958 | E75: Get supplemental information | F75: EXEC CICS ASSIGN APPLID(ABND-APPLID) END-EXEC MOVE EIBTASKN TO ABND-TASKNO-KEY MOVE EIBTRNID TO ABND-TRANID PERFORM POPULATE-TIME-DATE MOVE WS-ORIG-DATE TO ABND-DATE STRING WS-TIME-NOW-GRP-HH DELIMITED BY SIZE, ':' DELIMITED BY SIZE, WS-TIME-NOW-GRP-MM DELIMITED BY SIZE, ':' DELIMITED BY SIZE, WS-TIME-NOW-GRP-MM DELIMITED BY SIZE INTO ABND-TIME END-STRING MOVE WS-U-TIME TO ABND-UTIME-KEY MOVE 'HBNK' TO ABND-CODE EXEC CICS ASSIGN PROGRAM(ABND-PROGRAM) END-EXEC MOVE ZEROS TO ABND-SQLCODE STRING 'STM010 - SEND TEXT FAIL.' DELIMITED BY SIZE, ' EIBRESP=' DELIMITED BY SIZE, ABND-RESPCODE DELIMITED BY SIZE, ' RESP2=' DELIMITED BY SIZE, ABND-RESP2CODE DELIMITED BY SIZE INTO ABND-FREEFORM END-STRING EXEC CICS LINK PROGRAM(WS-ABEND-PGM) COMMAREA(ABNDINFO-REC) END-EXEC INITIALIZE WS-FAIL-INFO | G75: Procedural (sem decisão nem tratamento de falha) | H75: comentário curto; trecho truncado (30 linhas)
A76: BNK1TFN-049 | B76: BNK1TFN | C76: 1210 | D76: 1212-1224 | E76: Fomate the date and time | F76: EXEC CICS ASKTIME ABSTIME(WS-U-TIME) END-EXEC. EXEC CICS FORMATTIME ABSTIME(WS-U-TIME) DDMMYYYY(WS-ORIG-DATE) TIME(WS-TIME-NOW) DATESEP END-EXEC. PTD999. EXIT. | G76: Procedural (sem decisão nem tratamento de falha)
